Workbook
Name FFFF: Tracking!$E:$E,Tracking!$3:$25
Name FOCUS: Fondi_PE!#REF!
Name FOCUS: 'Int''l'!#REF!
Name FOCUS: Staffing!#REF!
Name FOCUS: Tracking!#REF!
Name FOCUS: '[1]Orig Dash (OLD)'!#REF!
Name Print: Tracking!$E:$E,Tracking!$3:$25
Name Print_Titles1: Tracking!$E:$E,Tracking!$3:$25

Sheet Tracking
BC1: |
E2: =+WEEKNUM(TODAY()) -> 2 | G2: NON MODIFICARE CELLE CONTENTENTI FORMULE (ES. B,C,D) | AI2: cls | AJ2: =+COUNTIF($D:$D,AI2) -> 24 | AM2: sgn | AN2: =+COUNTIF($D:$D,AM2) -> 7 | AP2: wip | AQ2: =+COUNTIF($D:$D,AP2) -> 10 | AS2: hld | AT2: =+COUNTIF($D:$D,AS2) -> 120 | AV2: abt | AW2: =+COUNTIF($D:$D,AV2) -> 345 | AY2: RIP | AZ2: =+COUNTIF($D:$D,AY2) -> 0 | BC2: |
B3: Ordine | C3: # | D3: Status | E3: Nome | F3: Codename | G3: Provincia | H3: P.IVA | I3: ATECO 2007 | J3: Settore | K3: Attività | L3: Riferimento cliente | M3: Azionista_1 | N3: Azionista_2 | O3: Presidente | P3: AD | Q3: Pres.Col.Sind | S3: Cons | T3: Anno | U3: Sales | V3: Ebitda | W3: Ebitda(%) | X3: Ut. Netto | Y3: IFN | AA3: Fonte | AB3: Segnalatore EXT | AC3: Relazione @BCA | AD3: In Charge @BCA | AE3: Staff_1 | AF3: Staff_2 | AG3: Note | AI3: Days since idea | AJ3: Days since progress | AK3: Tipologia di Incarico | AL3: Progress | AM3: Idea | AN3: 1° Contatto | AO3: Re-call | AP3: Contatto aperto | AQ3: Meet_1 / Call | AR3: Meet_2 | AS3: Meet_3 (Pitch) | AT3: (Draft EL) Meet_4 | AU3: Meet_5 | AV3: Signed | AW3: Progress | AX3: On-hold | AY3: Aborted | AZ3: Closed | BA3: % @abor | BB3: RIP | BC3: |
B5: =IF(D5=$A$516,1,IF(D5=$A$517,2,IF(D5=$A$518,3,IF(D5=$A$519,4,IF(D5=$A$520,5,IF(D5=$A$521,6)))))) -> 1 | C5: =+COUNTIF(D:D,"cls") -> 24 | D5: =IF(AL5="Closed","cls",IF(AL5=1,"sgn",IF(AL5="On-hold","hld",IF(AL5="Aborted","abt",IF(AL5<1,"wip","RIP"))))) -> cls | E5: P&B C.so Italia | J5: Education | K5: Gestione di strutture scolastiche | L5: Odile Broglin | AA5: Relazione | AC5: LOM | AD5: LOM | AE5: LUS | AG5: Fee Sharing con Alessandro Piona | AI5: =+TODAY()-AM5 -> 1467 | AJ5: =+(IF(AL5="Closed","-",IF(TODAY()-MAX(AN5:BA5)>0,TODAY()-MAX(AN5:BA5),0))) -> - | AK5: Buy Side | AL5: =+IF(BB5="",IF(AZ5="",IF(AY5="",IF(AX5="",COUNTA(AN5:AV5)/9,"On-hold"),"Aborted"),"Closed"),"RIP") -> Closed | AM5: 44197 | AN5: =+AM5 -> 44197 | AO5: na | AP5: na | AQ5: =+AN5 -> 44197 | AR5: =+AQ5 -> 44197 | AS5: na | AT5: na | AU5: na | AV5: na | AZ5: 44377 | BC5: |
B6: =IF(D6=$A$516,1,IF(D6=$A$517,2,IF(D6=$A$518,3,IF(D6=$A$519,4,IF(D6=$A$520,5,IF(D6=$A$521,6)))))) -> 1 | D6: =IF(AL6="Closed","cls",IF(AL6=1,"sgn",IF(AL6="On-hold","hld",IF(AL6="Aborted","abt",IF(AL6<1,"wip","RIP"))))) -> cls | E6: Ala | G6: TO | H6: 06239191213 | J6: Aerospace | K6: Components for aerospace industry | AA6: Relazione | AC6: LOM | AD6: LOM | AI6: =+TODAY()-AM6 -> 1286 | AJ6: =+(IF(AL6="Closed","-",IF(TODAY()-MAX(AN6:BA6)>0,TODAY()-MAX(AN6:BA6),0))) -> - | AK6: Altro | AL6: =+IF(BB6="",IF(AZ6="",IF(AY6="",IF(AX6="",COUNTA(AN6:AV6)/9,"On-hold"),"Aborted"),"Closed"),"RIP") -> Closed | AM6: 44378 | AN6: 44378 | AO6: na | AP6: na | AQ6: =+AN6 -> 44378 | AR6: na | AS6: na | AT6: na | AU6: na | AV6: na | AZ6: 44467 | BC6: |
B7: =IF(D7=$A$516,1,IF(D7=$A$517,2,IF(D7=$A$518,3,IF(D7=$A$519,4,IF(D7=$A$520,5,IF(D7=$A$521,6)))))) -> 1 | D7: =IF(AL7="Closed","cls",IF(AL7=1,"sgn",IF(AL7="On-hold","hld",IF(AL7="Aborted","abt",IF(AL7<1,"wip","RIP"))))) -> cls | E7: Bolaffi (Beyoncé - Minoranza) | F7: Beyonce | G7: TO | H7: 10156770017 | I7: 477700 | J7: Retail | K7: Commercio oro da investimento | L7: F. Bolaffi | S7: no | T7: 2019 | U7: 23.32 | V7: 0.77 | W7: 0.033018868 | X7: 0.52 | Y7: -0.1 | AA7: Relazione | AC7: LOM | AD7: ASC | AE7: PAD | AH7: 1 | AI7: =+TODAY()-AM7 -> 1528 | AJ7: =+(IF(AL7="Closed","-",IF(TODAY()-MAX(AN7:BA7)>0,TODAY()-MAX(AN7:BA7),0))) -> - | AK7: Buy Side | AL7: =+IF(BB7="",IF(AZ7="",IF(AY7="",IF(AX7="",COUNTA(AN7:AV7)/9,"On-hold"),"Aborted"),"Closed"),"RIP") -> Closed | AM7: 44136 | AN7: 44136 | AO7: na | AP7: 44136 | AQ7: 44136 | AR7: na | AS7: na | AT7: 44142 | AU7: na | AV7: 44158 | AZ7: 44523 | BC7: |
B8: =IF(D8=$A$516,1,IF(D8=$A$517,2,IF(D8=$A$518,3,IF(D8=$A$519,4,IF(D8=$A$520,5,IF(D8=$A$521,6)))))) -> 1 | D8: =IF(AL8="Closed","cls",IF(AL8=1,"sgn",IF(AL8="On-hold","hld",IF(AL8="Aborted","abt",IF(AL8<1,"wip","RIP"))))) -> cls | E8: Fra Diavolo (Pj Hell) | F8: Hell | G8: TO | H8: 01217560015 | I8: 642000 | J8: Food | K8: Catena di ristoranti pizzeria | L8: Mauro D'errico | S8: no | T8: 2020 | U8: 2.558 | V8: 0.127 | W8: 0.049648163 | X8: 0.005 | Y8: 1.739 | AA8: Relazione | AC8: LOM | AD8: LOM | AE8: RIM | AF8: LUS | AI8: =+TODAY()-AM8 -> 1215 | AJ8: =+(IF(AL8="Closed","-",IF(TODAY()-MAX(AN8:BA8)>0,TODAY()-MAX(AN8:BA8),0))) -> - | AK8: Sell Side | AL8: =+IF(BB8="",IF(AZ8="",IF(AY8="",IF(AX8="",COUNTA(AN8:AV8)/9,"On-hold"),"Aborted"),"Closed"),"RIP") -> Closed | AM8: 44449 | AN8: 44449 | AO8: 44449 | AP8: 44449 | AQ8: 44449 | AR8: na | AS8: na | AT8: 44453 | AU8: na | AV8: 44453 | AZ8: 44572 | BC8: |
B9: =IF(D9=$A$516,1,IF(D9=$A$517,2,IF(D9=$A$518,3,IF(D9=$A$519,4,IF(D9=$A$520,5,IF(D9=$A$521,6)))))) -> 1 | D9: =IF(AL9="Closed","cls",IF(AL9=1,"sgn",IF(AL9="On-hold","hld",IF(AL9="Aborted","abt",IF(AL9<1,"wip","RIP"))))) -> cls | E9: Bolaffi (Pj Mango) | F9: Mango | G9: TO | H9: 10156770017 | I9: 477700 | J9: Retail | K9: Commercio oro da investimento | L9: F. Bolaffi | S9: no | T9: 2019 | U9: 23.32 | V9: 0.77 | W9: 0.033018868 | X9: 0.52 | Y9: -0.1 | AA9: Relazione | AC9: LOM | AD9: ASC | AE9: PAD | AH9: 1 | AI9: =+TODAY()-AM9 -> 1347 | AJ9: =+(IF(AL9="Closed","-",IF(TODAY()-MAX(AN9:BA9)>0,TODAY()-MAX(AN9:BA9),0))) -> - | AK9: Buy Side | AL9: =+IF(BB9="",IF(AZ9="",IF(AY9="",IF(AX9="",COUNTA(AN9:AV9)/9,"On-hold"),"Aborted"),"Closed"),"RIP") -> Closed | AM9: 44317 | AN9: =+AM9 -> 44317 | AO9: na | AP9: na | AQ9: =+AN9 -> 44317 | AR9: na | AS9: na | AT9: na | AU9: na | AV9: 44376 | AZ9: 44530 | BC9: |
B10: =IF(D10=$A$516,1,IF(D10=$A$517,2,IF(D10=$A$518,3,IF(D10=$A$519,4,IF(D10=$A$520,5,IF(D10=$A$521,6)))))) -> 1 | D10: =IF(AL10="Closed","cls",IF(AL10=1,"sgn",IF(AL10="On-hold","hld",IF(AL10="Aborted","abt",IF(AL10<1,"wip","RIP"))))) -> cls | E10: P&B Melabimbi | G10: Francia | J10: Education | K10: Gestione di strutture scolastiche | L10: Odile Broglin | AA10: Relazione | AC10: LOM | AD10: LOM | AE10: LUS | AI10: =+TODAY()-AM10 -> 1292 | AJ10: =+(IF(AL10="Closed","-",IF(TODAY()-MAX(AN10:BA10)>0,TODAY()-MAX(AN10:BA10),0))) -> - | AK10: Buy Side | AL10: =+IF(BB10="",IF(AZ10="",IF(AY10="",IF(AX10="",COUNTA(AN10:AV10)/9,"On-hold"),"Aborted"),"Closed"),"RIP") -> Closed | AM10: 44372 | AN10: =+AM10 -> 44372 | AO10: na | AP10: na | AQ10: =+AN10 -> 44372 | AR10: na | AS10: na | AT10: na | AU10: na | AV10: na | AZ10: 44511 | BC10: |
B11: =IF(D11=$A$516,1,IF(D11=$A$517,2,IF(D11=$A$518,3,IF(D11=$A$519,4,IF(D11=$A$520,5,IF(D11=$A$521,6)))))) -> 1 | D11: =IF(AL11="Closed","cls",IF(AL11=1,"sgn",IF(AL11="On-hold","hld",IF(AL11="Aborted","abt",IF(AL11<1,"wip","RIP"))))) -> cls | E11: P&B Ristori | G11: Francia | J11: Education | K11: Gestione di strutture scolastiche | L11: Odile Broglin | AA11: Relazione | AC11: LOM | AD11: LOM | AE11: LUS | AI11: =+TODAY()-AM11 -> 1377 | AJ11: =+(IF(AL11="Closed","-",IF(TODAY()-MAX(AN11:BA11)>0,TODAY()-MAX(AN11:BA11),0))) -> - | AK11: Buy Side | AL11: =+IF(BB11="",IF(AZ11="",IF(AY11="",IF(AX11="",COUNTA(AN11:AV11)/9,"On-hold"),"Aborted"),"Closed"),"RIP") -> Closed | AM11: 44287 | AN11: =+AM11 -> 44287 | AO11: na | AP11: na | AQ11: =+AN11 -> 44287 | AR11: na | AS11: na | AT11: na | AU11: na | AV11: na | AZ11: 44491 | BC11: |
B12: =IF(D12=$A$516,1,IF(D12=$A$517,2,IF(D12=$A$518,3,IF(D12=$A$519,4,IF(D12=$A$520,5,IF(D12=$A$521,6)))))) -> 1 | D12: =IF(AL12="Closed","cls",IF(AL12=1,"sgn",IF(AL12="On-hold","hld",IF(AL12="Aborted","abt",IF(AL12<1,"wip","RIP"))))) -> cls | E12: Pezzutti Group (Valutazione) | F12: na | G12: PN | H12: 00300430931 | I12: 222909 | J12: Plastic | K12: Stampaggio materie plastiche a iniezione | L12: Fabio Messinese | M12: Fabio Messinese | S12: no | T12: 2019 | U12: 79.17 | V12: 6.97 | W12: 0.088038398 | X12: 2.24 | Y12: 40.34 | AA12: Segnalatore | AB12: Neri Andrea | AC12: ASC | AD12: ASC | AE12: PAD | AF12: LUS | AH12: 1 | AI12: =+TODAY()-AM12 -> 1408 | AJ12: =+(IF(AL12="Closed","-",IF(TODAY()-MAX(AN12:BA12)>0,TODAY()-MAX(AN12:BA12),0))) -> - | AK12: Valutazione | AL12: =+IF(BB12="",IF(AZ12="",IF(AY12="",IF(AX12="",COUNTA(AN12:AV12)/9,"On-hold"),"Aborted"),"Closed"),"RIP") -> Closed | AM12: 44256 | AN12: 44270 | AO12: na | AP12: 44294 | AQ12: 44294 | AR12: 44308 | AS12: 44342 | AT12: 44618 | AU12: 44630 | AV12: 44630 | AZ12: 44674 | BC12: |
B13: =IF(D13=$A$516,1,IF(D13=$A$517,2,IF(D13=$A$518,3,IF(D13=$A$519,4,IF(D13=$A$520,5,IF(D13=$A$521,6)))))) -> 1 | D13: =IF(AL13="Closed","cls",IF(AL13=1,"sgn",IF(AL13="On-hold","hld",IF(AL13="Aborted","abt",IF(AL13<1,"wip","RIP"))))) -> cls | E13: SoBeSport | G13: MI | H13: 08430980964 | I13: 829999 | J13: Other services | K13: Comunicazione e marketing sportivo per professionisti | L13: Gianluca Voulaz | M13: Gianluca Voulaz | S13: no | T13: 2019 | U13: 1.43 | V13: 0.3 | W13: 0.20979021 | X13: 0.2 | Y13: -0.32 | AA13: Relazione | AC13: ASC | AD13: ASC | AE13: LUS | AI13: =+TODAY()-AM13 -> 1177 | AJ13: =+(IF(AL13="Closed","-",IF(TODAY()-MAX(AN13:BA13)>0,TODAY()-MAX(AN13:BA13),0))) -> - | AK13: Sell Side | AL13: =+IF(BB13="",IF(AZ13="",IF(AY13="",IF(AX13="",COUNTA(AN13:AV13)/9,"On-hold"),"Aborted"),"Closed"),"RIP") -> Closed | AM13: 44487 | AN13: 44197 | AO13: na | AP13: 44197 | AQ13: 44197 | AR13: 44237 | AS13: 44270 | AT13: 44361 | AU13: 44461 | AV13: 44495 | AZ13: 44686 | BC13: |
B14: =IF(D14=$A$516,1,IF(D14=$A$517,2,IF(D14=$A$518,3,IF(D14=$A$519,4,IF(D14=$A$520,5,IF(D14=$A$521,6)))))) -> 1 | D14: =IF(AL14="Closed","cls",IF(AL14=1,"sgn",IF(AL14="On-hold","hld",IF(AL14="Aborted","abt",IF(AL14<1,"wip","RIP"))))) -> cls | E14: Rossi Navi (Valutazione) | F14: na | G14: LU | H14: 01431670460 | I14: 301000 | J14: Industrial | K14: Costruzione di navi e imbarcazioni | M14: Paride Rossi | N14: Claudio Rossi | S14: no | T14: 2019 | U14: 62.589 | V14: 1.646 | W14: 0.026298551 | X14: 0.17 | Y14: -2.066 | AA14: Relazione | AC14: ASC | AD14: ASC | AE14: PAD | AH14: 1 | AI14: =+TODAY()-AM14 -> 1256 | AJ14: =+(IF(AL14="Closed","-",IF(TODAY()-MAX(AN14:BA14)>0,TODAY()-MAX(AN14:BA14),0))) -> - | AK14: Valutazione | AL14: =+IF(BB14="",IF(AZ14="",IF(AY14="",IF(AX14="",COUNTA(AN14:AV14)/9,"On-hold"),"Aborted"),"Closed"),"RIP") -> Closed | AM14: 44408 | AN14: 44408 | AO14: na | AP14: na | AQ14: 44509 | AR14: na | AS14: 44609 | AT14: 44613 | AU14: 44620 | AV14: 44620 | AZ14: 44769 | BC14: |
B15: =IF(D15=$A$516,1,IF(D15=$A$517,2,IF(D15=$A$518,3,IF(D15=$A$519,4,IF(D15=$A$520,5,IF(D15=$A$521,6)))))) -> 1 | D15: =IF(AL15="Closed","cls",IF(AL15=1,"sgn",IF(AL15="On-hold","hld",IF(AL15="Aborted","abt",IF(AL15<1,"wip","RIP"))))) -> cls | E15: P&B Vispa Teresa | G15: Francia | J15: Education | K15: Gestione di strutture scolastiche | L15: Odile Broglin | AA15: Relazione | AC15: LOM | AD15: LOM | AE15: LUS | AI15: =+TODAY()-AM15 -> 1166 | AJ15: =+(IF(AL15="Closed","-",IF(TODAY()-MAX(AN15:BA15)>0,TODAY()-MAX(AN15:BA15),0))) -> - | AK15: Buy Side | AL15: =+IF(BB15="",IF(AZ15="",IF(AY15="",IF(AX15="",COUNTA(AN15:AV15)/9,"On-hold"),"Aborted"),"Closed"),"RIP") -> Closed | AM15: 44498 | AN15: =+AM15 -> 44498 | AO15: na | AP15: na | AQ15: =+AN15 -> 44498 | AR15: na | AS15: na | AT15: na | AU15: na | AV15: na | AZ15: 44916 | BC15: |
B16: =IF(D16=$A$516,1,IF(D16=$A$517,2,IF(D16=$A$518,3,IF(D16=$A$519,4,IF(D16=$A$520,5,IF(D16=$A$521,6)))))) -> 1 | D16: =IF(AL16="Closed","cls",IF(AL16=1,"sgn",IF(AL16="On-hold","hld",IF(AL16="Aborted","abt",IF(AL16<1,"wip","RIP"))))) -> cls | E16: P&B Canadian Island | G16: Francia | J16: Education | K16: Gestione di strutture scolastiche | L16: Odile Broglin | AA16: Relazione | AC16: LOM | AD16: LOM | AE16: LUS | AI16: =+TODAY()-AM16 -> 1216 | AJ16: =+(IF(AL16="Closed","-",IF(TODAY()-MAX(AN16:BA16)>0,TODAY()-MAX(AN16:BA16),0))) -> - | AK16: Buy Side | AL16: =+IF(BB16="",IF(AZ16="",IF(AY16="",IF(AX16="",COUNTA(AN16:AV16)/9,"On-hold"),"Aborted"),"Closed"),"RIP") -> Closed | AM16: 44448 | AN16: =+AM16 -> 44448 | AO16: na | AP16: na | AQ16: =+AN16 -> 44448 | AR16: na | AS16: na | AT16: na | AU16: na | AV16: na | AZ16: 44916 | BC16: |
B17: =IF(D17=$A$516,1,IF(D17=$A$517,2,IF(D17=$A$518,3,IF(D17=$A$519,4,IF(D17=$A$520,5,IF(D17=$A$521,6)))))) -> 1 | D17: =IF(AL17="Closed","cls",IF(AL17=1,"sgn",IF(AL17="On-hold","hld",IF(AL17="Aborted","abt",IF(AL17<1,"wip","RIP"))))) -> cls | E17: Pladway S.r.l. | G17: MI | H17: 10251710967 | I17: 731102 | J17: Tech | K17: Piattaforma di DOOH | L17: Luca Scelsa | S17: no | T17: 2022 | U17: 3.8 | V17: 0.006 | W17: 0.0015789474 | X17: na | Y17: na | AA17: Relazione | AC17: ASC | AD17: ASC | AE17: LUS | AG17: Intro Fee 10% | AI17: =+TODAY()-AM17 -> 820 | AJ17: =+(IF(AL17="Closed","-",IF(TODAY()-MAX(AN17:BA17)>0,TODAY()-MAX(AN17:BA17),0))) -> - | AK17: Sell Side | AL17: =+IF(BB17="",IF(AZ17="",IF(AY17="",IF(AX17="",COUNTA(AN17:AV17)/9,"On-hold"),"Aborted"),"Closed"),"RIP") -> Closed | AM17: 44844 | AN17: =+AM17 -> 44844 | AO17: na | AP17: 44849 | AQ17: 44849 | AR17: 44851 | AS17: na | AT17: 44852 | AU17: 44855 | AV17: 44858 | AZ17: 44985 | BC17: |
B18: =IF(D18=$A$516,1,IF(D18=$A$517,2,IF(D18=$A$518,3,IF(D18=$A$519,4,IF(D18=$A$520,5,IF(D18=$A$521,6)))))) -> 1 | D18: =IF(AL18="Closed","cls",IF(AL18=1,"sgn",IF(AL18="On-hold","hld",IF(AL18="Aborted","abt",IF(AL18<1,"wip","RIP"))))) -> cls | E18: Becoming Education (buy OIS) | F18: Nido | G18: MI | H18: 11603690964 | I18: 889100 | J18: Education | K18: Gestione di strutture scolastiche | AA18: Relazione | AC18: LOM | AD18: LOM | AE18: LUS | AI18: =+TODAY()-AM18 -> 1023 | AJ18: =+(IF(AL18="Closed","-",IF(TODAY()-MAX(AN18:BA18)>0,TODAY()-MAX(AN18:BA18),0))) -> - | AK18: Buy Side | AL18: =+IF(BB18="",IF(AZ18="",IF(AY18="",IF(AX18="",COUNTA(AN18:AV18)/9,"On-hold"),"Aborted"),"Closed"),"RIP") -> Closed | AM18: 44641 | AN18: 44641 | AO18: na | AP18: na | AQ18: 44651 | AR18: 44662 | AS18: na | AT18: na | AU18: na | AV18: 44677 | AZ18: 44957 | BC18: |
B19: =IF(D19=$A$516,1,IF(D19=$A$517,2,IF(D19=$A$518,3,IF(D19=$A$519,4,IF(D19=$A$520,5,IF(D19=$A$521,6)))))) -> 1 | D19: =IF(AL19="Closed","cls",IF(AL19=1,"sgn",IF(AL19="On-hold","hld",IF(AL19="Aborted","abt",IF(AL19<1,"wip","RIP"))))) -> cls | E19: Rossi Navi (M&A) | F19: Penta | G19: LU | H19: 01431670460 | I19: 301000 | J19: Industrial | K19: Costruzione di navi e imbarcazioni | M19: Paride Rossi | N19: Claudio Rossi | S19: no | T19: 2019 | U19: 62.589 | V19: 1.646 | W19: 0.026298551 | X19: 0.17 | Y19: -2.066 | AA19: Relazione | AC19: ASC | AD19: ASC | AE19: PAD | AF19: GID | AH19: 1 | AI19: =+TODAY()-AM19 -> 891 | AJ19: =+(IF(AL19="Closed","-",IF(TODAY()-MAX(AN19:BA19)>0,TODAY()-MAX(AN19:BA19),0))) -> - | AK19: Valutazione | AL19: =+IF(BB19="",IF(AZ19="",IF(AY19="",IF(AX19="",COUNTA(AN19:AV19)/9,"On-hold"),"Aborted"),"Closed"),"RIP") -> Closed | AM19: 44773 | AN19: 44408 | AO19: na | AP19: na | AQ19: 44896 | AR19: na | AS19: na | AT19: na | AU19: na | AV19: 45029 | AZ19: 45086 | BC19: |
B20: =IF(D20=$A$516,1,IF(D20=$A$517,2,IF(D20=$A$518,3,IF(D20=$A$519,4,IF(D20=$A$520,5,IF(D20=$A$521,6)))))) -> 1 | D20: =IF(AL20="Closed","cls",IF(AL20=1,"sgn",IF(AL20="On-hold","hld",IF(AL20="Aborted","abt",IF(AL20<1,"wip","RIP"))))) -> cls | E20: Seatram (Valutazione) | G20: GE | H20: 02806090102 | I20: 522910 | J20: Logistics | K20: Freight Forwarding | L20: L. Bruzzo | S20: no | T20: 2019 | U20: 29.07 | V20: 2.25 | W20: 0.077399381 | X20: 1.51 | Y20: -0.21 | AA20: Relazione | AC20: ASC | AD20: ASC | AE20: LUS | AF20: GID | AI20: =+TODAY()-AM20 -> 1422 | AJ20: =+(IF(AL20="Closed","-",IF(TODAY()-MAX(AN20:BA20)>0,TODAY()-MAX(AN20:BA20),0))) -> - | AK20: Valutazione | AL20: =+IF(BB20="",IF(AZ20="",IF(AY20="",IF(AX20="",COUNTA(AN20:AV20)/9,"On-hold"),"Aborted"),"Closed"),"RIP") -> Closed | AM20: 44242 | AN20: 44242 | AO20: na | AP20: 44242 | AQ20: 44249 | AR20: 44305 | AS20: 44985 | AT20: 45023 | AU20: na | AV20: 45043 | AZ20: 45174 | BC20: |
B21: =IF(D21=$A$516,1,IF(D21=$A$517,2,IF(D21=$A$518,3,IF(D21=$A$519,4,IF(D21=$A$520,5,IF(D21=$A$521,6)))))) -> 1 | D21: =IF(AL21="Closed","cls",IF(AL21=1,"sgn",IF(AL21="On-hold","hld",IF(AL21="Aborted","abt",IF(AL21<1,"wip","RIP"))))) -> cls | E21: English Gate School (sell side) | F21: Idia | G21: CO | H21: 07055650969 | I21: 889100 | J21: Education | K21: Gestione di strutture scolastiche | L21: Klodia Gaudino | S21: no | T21: 2020 | U21: 1.084 | V21: 0.085 | W21: 0.078413284 | X21: -0.065 | Y21: -0.561 | AA21: Cold Call | AC21: LOM | AD21: LOM | AE21: LUS | AI21: =+TODAY()-AM21 -> 963 | AJ21: =+(IF(AL21="Closed","-",IF(TODAY()-MAX(AN21:BA21)>0,TODAY()-MAX(AN21:BA21),0))) -> - | AK21: Sell Side | AL21: =+IF(BB21="",IF(AZ21="",IF(AY21="",IF(AX21="",COUNTA(AN21:AV21)/9,"On-hold"),"Aborted"),"Closed"),"RIP") -> Closed | AM21: 44701 | AN21: 44701 | AO21: na | AP21: 44704 | AQ21: 44707 | AR21: na | AS21: 44727 | AT21: 44741 | AU21: 44771 | AV21: 44777 | AZ21: 45209 | BC21: |
B22: =IF(D22=$A$516,1,IF(D22=$A$517,2,IF(D22=$A$518,3,IF(D22=$A$519,4,IF(D22=$A$520,5,IF(D22=$A$521,6)))))) -> 1 | D22: =IF(AL22="Closed","cls",IF(AL22=1,"sgn",IF(AL22="On-hold","hld",IF(AL22="Aborted","abt",IF(AL22<1,"wip","RIP"))))) -> cls | E22: YIES School | F22: Cedar | G22: MB | H22: 09365500967 | I22: 852000 | J22: Education | K22: Gestione di strutture scolastiche | L22: Angela Paladino | S22: no | T22: 2021 | U22: 0.846 | V22: 0.083 | W22: 0.098108747 | X22: 0.031 | Y22: -0.246 | AA22: Cold Call | AC22: LOM | AD22: LOM | AE22: LUS | AF22: GID | AI22: =+TODAY()-AM22 -> 963 | AJ22: =+(IF(AL22="Closed","-",IF(TODAY()-MAX(AN22:BA22)>0,TODAY()-MAX(AN22:BA22),0))) -> - | AK22: Sell Side | AL22: =+IF(BB22="",IF(AZ22="",IF(AY22="",IF(AX22="",COUNTA(AN22:AV22)/9,"On-hold"),"Aborted"),"Closed"),"RIP") -> Closed | AM22: 44701 | AN22: 44701 | AO22: na | AP22: 44701 | AQ22: 44707 | AR22: 44819 | AS22: 44851 | AT22: 44853 | AU22: 44963 | AV22: 44992 | AZ22: 45278 | BC22: |
B23: =IF(D23=$A$516,1,IF(D23=$A$517,2,IF(D23=$A$518,3,IF(D23=$A$519,4,IF(D23=$A$520,5,IF(D23=$A$521,6)))))) -> 1 | D23: =IF(AL23="Closed","cls",IF(AL23=1,"sgn",IF(AL23="On-hold","hld",IF(AL23="Aborted","abt",IF(AL23<1,"wip","RIP"))))) -> cls | E23: F.A.S.T. | F23: Race | G23: RA | H23: 01120890395 | J23: Other services | K23: Agenzia di viaggi | L23: Massimo Bertozzi | S23: no | T23: 2020 | U23: 4.844 | V23: 0.693 | W23: 0.14306358 | X23: 0.591 | Y23: n.d. | AA23: Azionista | AB23: Maurizio Bertozzi | AC23: ASC | AD23: ASC | AE23: GID | AI23: =+TODAY()-AM23 -> 810 | AJ23: =+(IF(AL23="Closed","-",IF(TODAY()-MAX(AN23:BA23)>0,TODAY()-MAX(AN23:BA23),0))) -> - | AK23: Sell Side | AL23: =+IF(BB23="",IF(AZ23="",IF(AY23="",IF(AX23="",COUNTA(AN23:AV23)/9,"On-hold"),"Aborted"),"Closed"),"RIP") -> Closed | AM23: 44854 | AN23: 44854 | AO23: na | AP23: 44854 | AQ23: 44854 | AR23: 44861 | AS23: 44867 | AT23: 44881 | AU23: 44897 | AV23: 44938 | AW23: =TODAY() -> 45664 | AZ23: 45260 | BC23: |
B24: =IF(D24=$A$516,1,IF(D24=$A$517,2,IF(D24=$A$518,3,IF(D24=$A$519,4,IF(D24=$A$520,5,IF(D24=$A$521,6)))))) -> 1 | D24: =IF(AL24="Closed","cls",IF(AL24=1,"sgn",IF(AL24="On-hold","hld",IF(AL24="Aborted","abt",IF(AL24<1,"wip","RIP"))))) -> cls | E24: Eurocert SpA | F24: Assure | G24: BO | J24: Servizi Certificazione | K24: Azienda di certificazione tecnica di impianti civili di vario genere | L24: Andrea Ballandi | S24: no | T24: 2022 | U24: 13.298 | V24: 1.76 | W24: =+V24/U24 -> 0.13235073 | X24: 0.945 | Y24: -4.986 | AA24: Segnalatore | AB24: Andrea Lenzi | AC24: FCA | AD24: FCA | AI24: =+TODAY()-AM24 -> 606 | AJ24: =+(IF(AL24="Closed","-",IF(TODAY()-MAX(AN24:BA24)>0,TODAY()-MAX(AN24:BA24),0))) -> - | AK24: Buy Side | AL24: =+IF(BB24="",IF(AZ24="",IF(AY24="",IF(AX24="",COUNTA(AN24:AV24)/9,"On-hold"),"Aborted"),"Closed"),"RIP") -> Closed | AM24: 45058 | AN24: 45058 | AO24: na | AP24: 45058 | AQ24: 45058 | AR24: 45077 | AS24: na | AT24: na | AU24: na | AV24: 45117 | AW24: =TODAY() -> 45664 | AZ24: 45327 | BC24: |
B25: =IF(D25=$A$516,1,IF(D25=$A$517,2,IF(D25=$A$518,3,IF(D25=$A$519,4,IF(D25=$A$520,5,IF(D25=$A$521,6)))))) -> 1 | D25: =IF(AL25="Closed","cls",IF(AL25=1,"sgn",IF(AL25="On-hold","hld",IF(AL25="Aborted","abt",IF(AL25<1,"wip","RIP"))))) -> cls | E25: Fra Diavolo (2° round) | G25: TO | H25: 00767700156 | I25: 642000 | J25: Food | K25: Catena di ristoranti pizzeria | L25: Mauro D'errico | S25: no | T25: 2020 | U25: 2.558 | V25: 0.127 | W25: =+V25/U25 -> 0.049648163 | X25: 0.005 | Y25: 1.739 | AA25: Relazione | AC25: LOM | AD25: LOM | AE25: PAD | AF25: GID | AG25: Buy Alto Partners | AI25: =+TODAY()-AM25 -> 1215 | AJ25: =+(IF(AL25="Closed","-",IF(TODAY()-MAX(AN25:BA25)>0,TODAY()-MAX(AN25:BA25),0))) -> - | AK25: Buy Side | AL25: =+IF(BB25="",IF(AZ25="",IF(AY25="",IF(AX25="",COUNTA(AN25:AV25)/9,"On-hold"),"Aborted"),"Closed"),"RIP") -> Closed | AM25: 44449 | AN25: 44449 | AO25: 44449 | AP25: 44449 | AQ25: 44449 | AR25: na | AS25: 45236 | AT25: 45245 | AU25: 45320 | AV25: 45320 | AW25: =TODAY() -> 45664 | AZ25: 45433 | BC25: |
B26: =IF(D26=$A$516,1,IF(D26=$A$517,2,IF(D26=$A$518,3,IF(D26=$A$519,4,IF(D26=$A$520,5,IF(D26=$A$521,6)))))) -> 1 | D26: =IF(AL26="Closed","cls",IF(AL26=1,"sgn",IF(AL26="On-hold","hld",IF(AL26="Aborted","abt",IF(AL26<1,"wip","RIP"))))) -> cls | E26: Ferrari - Contratto di Sviluppo (CdS) | F26: e-Building | G26: MO | H26: 00159560366 | J26: Automotive | K26: Produzione auto sportive | L26: Alessandro Tedesco | M26: Ferrari N.V | O26: John Philip Elkann | P26: Benedetto Vigna | Q26: Ignazio Carbone | S26: no | T26: 2023 | U26: 5650 | V26: 1792.321 | W26: =+V26/U26 -> 0.31722496 | X26: 1275 | Y26: -0.841 | AA26: Segnalatore | AB26: Aimo + Consulman | AC26: FCA | AD26: FCA | AE26: MMO | AF26: GSE | AI26: =+TODAY()-AM26 -> 1651 | AJ26: =+(IF(AL26="Closed","-",IF(TODAY()-MAX(AN26:BA26)>0,TODAY()-MAX(AN26:BA26),0))) -> - | AK26: Agevolato | AL26: =+IF(BB26="",IF(AZ26="",IF(AY26="",IF(AX26="",COUNTA(AN26:AV26)/9,"On-hold"),"Aborted"),"Closed"),"RIP") -> Closed | AM26: 44013 | AN26: 44013 | AO26: na | AP26: 44075 | AQ26: 44075 | AR26: 44103 | AS26: 44105 | AT26: 44105 | AU26: na | AV26: 44159 | AW26: =TODAY() -> 45664 | AZ26: 45502 | BC26: |
B27: =IF(D27=$A$516,1,IF(D27=$A$517,2,IF(D27=$A$518,3,IF(D27=$A$519,4,IF(D27=$A$520,5,IF(D27=$A$521,6)))))) -> 1 | D27: =IF(AL27="Closed","cls",IF(AL27=1,"sgn",IF(AL27="On-hold","hld",IF(AL27="Aborted","abt",IF(AL27<1,"wip","RIP"))))) -> cls | E27: International School Brescia (sell side) | F27: Garda | G27: BS | H27: 03915470987 | I27: 852000 | J27: Education | K27: Scuola internazionale k-12 | L27: Omar Bonomelli | M27: Sunderland Srl | N27: Barbara Filippini | P27: Omar Bonomelli | S27: no | T27: 2023 | U27: 2.685 | V27: 0.585 | W27: =+V27/U27 -> 0.21787709 | X27: 0 | Y27: 0 | AA27: Cold Call | AC27: LOM | AD27: LOM | AE27: LUS | AF27: GID | AI27: =+TODAY()-AM27 -> 770 | AJ27: =+(IF(AL27="Closed","-",IF(TODAY()-MAX(AN27:BA27)>0,TODAY()-MAX(AN27:BA27),0))) -> - | AK27: Sell Side | AL27: =+IF(BB27="",IF(AZ27="",IF(AY27="",IF(AX27="",COUNTA(AN27:AV27)/9,"On-hold"),"Aborted"),"Closed"),"RIP") -> Closed | AM27: 44894 | AN27: 44894 | AO27: na | AP27: 44895 | AQ27: 44951 | AR27: 45014 | AS27: 45084 | AT27: 45131 | AU27: 45139 | AV27: 45147 | AW27: =TODAY() -> 45664 | AZ27: 45477 | BC27: |
B28: =IF(D28=$A$516,1,IF(D28=$A$517,2,IF(D28=$A$518,3,IF(D28=$A$519,4,IF(D28=$A$520,5,IF(D28=$A$521,6)))))) -> 1 | D28: =IF(AL28="Closed","cls",IF(AL28=1,"sgn",IF(AL28="On-hold","hld",IF(AL28="Aborted","abt",IF(AL28<1,"wip","RIP"))))) -> cls | E28: Maschio Gaspardo - Simest | F28: Internaz. | G28: PD | H28: 03272800289 | I28: 283090 | J28: Industrial | K28: Produzione attrezzature agricole | L28: Pierantonio Prevarin | M28: Maschio Holding Spa | N28: Self owned | O28: Mirco Maschio | P28: Luigi De Puppi | Q28: Pietro Del Fabbro | S28: no | T28: 2023 | U28: 425.13 | V28: 64.202 | W28: =+V28/U28 -> 0.15101734 | X28: 25.631 | Y28: 116.723 | AA28: Segnalatore | AB28: Mise | AC28: FCA | AD28: FCA | AE28: MMO | AF28: GSE | AI28: =+TODAY()-AM28 -> 556 | AJ28: =+(IF(AL28="Closed","-",IF(TODAY()-MAX(AN28:BA28)>0,TODAY()-MAX(AN28:BA28),0))) -> - | AK28: Agevolato | AL28: =+IF(BB28="",IF(AZ28="",IF(AY28="",IF(AX28="",COUNTA(AN28:AV28)/9,"On-hold"),"Aborted"),"Closed"),"RIP") -> Closed | AM28: 45108 | AN28: =+AM28 -> 45108 | AO28: na | AP28: na | AQ28: =+AN28 -> 45108 | AR28: na | AS28: na | AT28: na | AU28: na | AV28: 44859 | AW28: =TODAY() -> 45664 | AZ28: 45614 | BC28: |
B29: =IF(D29=$A$516,1,IF(D29=$A$517,2,IF(D29=$A$518,3,IF(D29=$A$519,4,IF(D29=$A$520,5,IF(D29=$A$521,6)))))) -> 2 | C29: =+COUNTIF(D:D,"sgn") -> 7 | D29: =IF(AL29="Closed","cls",IF(AL29=1,"sgn",IF(AL29="On-hold","hld",IF(AL29="Aborted","abt",IF(AL29<1,"wip","RIP"))))) -> sgn | E29: ISL Nardi | F29: Edvige | G29: MI | H29: 11878560157 | I29: 522921 | J29: Logistics | K29: Spedizioni internazionali via nave | M29: Andrea Gay | N29: Stefano Guazzaroni | O29: Andrea Gay | Q29: Emanuele Borgonovo | S29: si | T29: 2022 | U29: 87.778 | V29: 2.848 | W29: =+V29/U29 -> 0.032445487 | X29: 1.921 | Y29: -6.213 | AA29: Relazione | AC29: ASC | AD29: ASC | AE29: RIM | AF29: LUS | AI29: =+TODAY()-AM29 -> 1166 | AJ29: =+(IF(AL29="Closed","-",IF(TODAY()-MAX(AN29:BA29)>0,TODAY()-MAX(AN29:BA29),0))) -> 0 | AK29: Sell Side | AL29: =+IF(BB29="",IF(AZ29="",IF(AY29="",IF(AX29="",COUNTA(AN29:AV29)/9,"On-hold"),"Aborted"),"Closed"),"RIP") -> 1 | AM29: 44498 | AN29: 44498 | AO29: na | AP29: 44498 | AQ29: 44510 | AR29: 44524 | AS29: na | AT29: 44540 | AU29: 44588 | AV29: 44588 | AW29: =TODAY() -> 45664 | BC29: |
B30: =IF(D30=$A$516,1,IF(D30=$A$517,2,IF(D30=$A$518,3,IF(D30=$A$519,4,IF(D30=$A$520,5,IF(D30=$A$521,6)))))) -> 2 | D30: =IF(AL30="Closed","cls",IF(AL30=1,"sgn",IF(AL30="On-hold","hld",IF(AL30="Aborted","abt",IF(AL30<1,"wip","RIP"))))) -> sgn | E30: Fischer & Rechsteiner (buy) | G30: LC | H30: 00210750139 | I30: 522910 | J30: Logistics | K30: Spedizioni internazionali via nave | L30: Riccardo Riva | M30: Inter Freight | P30: Riccardo Riva | Q30: Luigi Frizzi | S30: no | T30: 2023 | U30: 27.284 | V30: 0.452 | W30: =+V30/U30 -> 0.016566486 | X30: 0.266 | Y30: 2.223 | AA30: Segnalatore | AB30: Ermanno Restano | AC30: ASC | AD30: ASC | AE30: RIM | AF30: GID | AI30: =+TODAY()-AM30 -> 522 | AJ30: =+(IF(AL30="Closed","-",IF(TODAY()-MAX(AN30:BA30)>0,TODAY()-MAX(AN30:BA30),0))) -> 0 | AK30: Buy Side | AL30: =+IF(BB30="",IF(AZ30="",IF(AY30="",IF(AX30="",COUNTA(AN30:AV30)/9,"On-hold"),"Aborted"),"Closed"),"RIP") -> 1 | AM30: 45142 | AN30: 45142 | AO30: 45142 | AP30: 45142 | AQ30: =+AN30 -> 45142 | AR30: na | AS30: 45181 | AT30: 45217 | AU30: na | AV30: 45229 | AW30: =TODAY() -> 45664 | BC30: |
B31: =IF(D31=$A$516,1,IF(D31=$A$517,2,IF(D31=$A$518,3,IF(D31=$A$519,4,IF(D31=$A$520,5,IF(D31=$A$521,6)))))) -> 2 | D31: =IF(AL31="Closed","cls",IF(AL31=1,"sgn",IF(AL31="On-hold","hld",IF(AL31="Aborted","abt",IF(AL31<1,"wip","RIP"))))) -> sgn | E31: Haier/Candy - Contratto di Sviluppo (CdS) | F31: Digit+Sost | G31: MB | H31: 00786860965 | J31: Industrial | K31: Produzione elettrodomestici | L31: Daniele Frigerio | M31: Haier | O31: Neil Tunstall | P31: Neill Tunstall | S31: no | T31: 2022 | U31: 1192 | V31: -15.08 | W31: =+V31/U31 -> -0.012651007 | X31: -163 | Y31: 289.797 | AA31: Segnalatore | AB31: Consulman | AC31: FCA | AD31: FCA | AE31: MMO | AF31: GSE | AI31: =+TODAY()-AM31 -> 1286 | AJ31: =+(IF(AL31="Closed","-",IF(TODAY()-MAX(AN31:BA31)>0,TODAY()-MAX(AN31:BA31),0))) -> 0 | AK31: Agevolato | AL31: =+IF(BB31="",IF(AZ31="",IF(AY31="",IF(AX31="",COUNTA(AN31:AV31)/9,"On-hold"),"Aborted"),"Closed"),"RIP") -> 1 | AM31: 44378 | AN31: =+AM31 -> 44378 | AO31: na | AP31: na | AQ31: =+AN31 -> 44378 | AR31: na | AS31: na | AT31: na | AU31: na | AV31: 44644 | AW31: =TODAY() -> 45664 | BC31: |
B32: =IF(D32=$A$516,1,IF(D32=$A$517,2,IF(D32=$A$518,3,IF(D32=$A$519,4,IF(D32=$A$520,5,IF(D32=$A$521,6)))))) -> 2 | D32: =IF(AL32="Closed","cls",IF(AL32=1,"sgn",IF(AL32="On-hold","hld",IF(AL32="Aborted","abt",IF(AL32<1,"wip","RIP"))))) -> sgn | E32: Ferrari - CdS - Management & Reporting | F32: e-Building | G32: MO | H32: 00159560366 | J32: Automotive | K32: Produzione auto sportive | L32: Alessandro Tedesco | M32: Ferrari N.V | O32: John Philip Elkann | P32: Benedetto Vigna | Q32: Ignazio Carbone | S32: no | T32: 2023 | U32: 5650 | V32: 1792.3 | W32: =+V32/U32 -> 0.31722124 | X32: 1275 | Y32: -0.8 | AA32: Segnalatore | AB32: Aimo + Consulman | AC32: FCA | AD32: FCA | AE32: GSE | AF32: MMO | AI32: =+TODAY()-AM32 -> 859 | AJ32: =+(IF(AL32="Closed","-",IF(TODAY()-MAX(AN32:BA32)>0,TODAY()-MAX(AN32:BA32),0))) -> 0 | AK32: Agevolato | AL32: =+IF(BB32="",IF(AZ32="",IF(AY32="",IF(AX32="",COUNTA(AN32:AV32)/9,"On-hold"),"Aborted"),"Closed"),"RIP") -> 1 | AM32: 44805 | AN32: =+AM32 -> 44805 | AO32: na | AP32: na | AQ32: =+AN32 -> 44805 | AR32: na | AS32: na | AT32: na | AU32: na | AV32: 44872 | AW32: =TODAY() -> 45664 | BC32: |
B33: =IF(D33=$A$516,1,IF(D33=$A$517,2,IF(D33=$A$518,3,IF(D33=$A$519,4,IF(D33=$A$520,5,IF(D33=$A$521,6)))))) -> 2 | D33: =IF(AL33="Closed","cls",IF(AL33=1,"sgn",IF(AL33="On-hold","hld",IF(AL33="Aborted","abt",IF(AL33<1,"wip","RIP"))))) -> sgn | E33: Myes School (sellside) | F33: Anfield | G33: FI | H33: 07096960484 | J33: Education | K33: Corsi di lingua | M33: Myes Firenze Srl | P33: Luigi Sguerri | S33: no | T33: 2023 | U33: 5.035 | V33: 0.226 | W33: =+V33/U33 -> 0.044885799 | X33: 0.103 | Y33: -0.014 | AA33: Cold Call | AC33: LOM | AD33: LOM | AE33: LUS | AF33: GID | AI33: =+TODAY()-AM33 -> 749 | AJ33: =+(IF(AL33="Closed","-",IF(TODAY()-MAX(AN33:BA33)>0,TODAY()-MAX(AN33:BA33),0))) -> 0 | AK33: Sell Side | AL33: =+IF(BB33="",IF(AZ33="",IF(AY33="",IF(AX33="",COUNTA(AN33:AV33)/9,"On-hold"),"Aborted"),"Closed"),"RIP") -> 1 | AM33: 44915 | AN33: 45013 | AO33: na | AP33: 45062 | AQ33: 45069 | AR33: 45113 | AS33: 45124 | AT33: 45344 | AU33: na | AV33: 45350 | AW33: =TODAY() -> 45664 | BA33: =+IF(AY33="","",COUNTA(AN33:AV33)/(COUNTA(AN33:AV33)+COUNTBLANK(AN33:AV33))) | BC33: |
B34: =IF(D34=$A$516,1,IF(D34=$A$517,2,IF(D34=$A$518,3,IF(D34=$A$519,4,IF(D34=$A$520,5,IF(D34=$A$521,6)))))) -> 2 | D34: =IF(AL34="Closed","cls",IF(AL34=1,"sgn",IF(AL34="On-hold","hld",IF(AL34="Aborted","abt",IF(AL34<1,"wip","RIP"))))) -> sgn | E34: Kilometro Verde | F34: Mars | G34: BS | H34: 04267900985 | J34: Food | K34: Vertical farms | L34: Battagliola | P34: Sabrina De Filippis | S34: no | T34: 2023 | U34: 0.06 | V34: -1.421 | W34: =+V34/U34 -> -23.683333 | X34: -2.347 | Y34: 13.203 | AA34: Azionista | AB34: Dario Micheli | AC34: ROS | AD34: ROS | AE34: PAD | AF34: GID | AH34: 1 | AI34: =+TODAY()-AM34 -> 235 | AJ34: =+(IF(AL34="Closed","-",IF(TODAY()-MAX(AN34:BA34)>0,TODAY()-MAX(AN34:BA34),0))) -> 0 | AK34: Fundraising | AL34: =+IF(BB34="",IF(AZ34="",IF(AY34="",IF(AX34="",COUNTA(AN34:AV34)/9,"On-hold"),"Aborted"),"Closed"),"RIP") -> 1 | AM34: 45429 | AN34: 45429 | AO34: 45429 | AP34: 45429 | AQ34: 45429 | AR34: 45436 | AS34: 45436 | AT34: 45439 | AU34: 45441 | AV34: 45441 | AW34: =TODAY() -> 45664 | BC34: |
B35: =IF(D35=$A$516,1,IF(D35=$A$517,2,IF(D35=$A$518,3,IF(D35=$A$519,4,IF(D35=$A$520,5,IF(D35=$A$521,6)))))) -> 2 | D35: =IF(AL35="Closed","cls",IF(AL35=1,"sgn",IF(AL35="On-hold","hld",IF(AL35="Aborted","abt",IF(AL35<1,"wip","RIP"))))) -> sgn | E35: Formazione Giuridica | F35: Edera | G35: BO | H35: 03266791205 | J35: Education | K35: Corsi di preparazione a esami di avvocatura, magistratura, notariato | L35: Marco Zincani | S35: no | T35: 2022 | U35: 1.84 | V35: 0.883 | W35: =+V35/U35 -> 0.4798913 | X35: 0.507 | Y35: n.d. | AA35: Cold Call | AC35: LUS | AD35: LOM | AE35: LUS | AF35: GID | AI35: =+TODAY()-AM35 -> 195 | AJ35: =+(IF(AL35="Closed","-",IF(TODAY()-MAX(AN35:BA35)>0,TODAY()-MAX(AN35:BA35),0))) -> 0 | AK35: Sell Side | AL35: =+IF(BB35="",IF(AZ35="",IF(AY35="",IF(AX35="",COUNTA(AN35:AV35)/9,"On-hold"),"Aborted"),"Closed"),"RIP") -> 1 | AM35: 45469 | AN35: 45470 | AO35: na | AP35: 45470 | AQ35: 45476 | AR35: na | AS35: 45481 | AT35: 45489 | AU35: 45498 | AV35: 45499 | AW35: =+TODAY() -> 45664 | BC35: |
B36: =IF(D36=$A$516,1,IF(D36=$A$517,2,IF(D36=$A$518,3,IF(D36=$A$519,4,IF(D36=$A$520,5,IF(D36=$A$521,6)))))) -> 3 | D36: =IF(AL36="Closed","cls",IF(AL36=1,"sgn",IF(AL36="On-hold","hld",IF(AL36="Aborted","abt",IF(AL36<1,"wip","RIP"))))) -> wip | E36: Distilleria F.lli Caffo (Buy-side_2025) | G36: VV | H36: 08575640969 | I36: 110100 | J36: Food: Spirits | K36: Distilleria - Amaro del Capo | L36: Sabastiano Caffo | M36: Fam. Caffo | N36: Giuseppe Giovanni Caffo | P36: Sebastiano Giovanni Caffo | Q36: Lorenzo Pagliuca | S36: sì | T36: 2022 | U36: 93 | V36: 22 | W36: =+V36/U36 -> 0.23655914 | X36: 11.8 | Y36: -13 | AA36: Relazione | AC36: ASC | AD36: ASC | AE36: RIM | AF36: LUS | AI36: =+TODAY()-AM36 -> 1528 | AJ36: =+(IF(AL36="Closed","-",IF(TODAY()-MAX(AN36:BA36)>0,TODAY()-MAX(AN36:BA36),0))) -> 18 | AK36: Buy Side | AL36: =+IF(BB36="",IF(AZ36="",IF(AY36="",IF(AX36="",COUNTA(AN36:AV36)/9,"On-hold"),"Aborted"),"Closed"),"RIP") -> 0.88888889 | AM36: 44136 | AN36: 44136 | AO36: na | AP36: 44136 | AQ36: 45631 | AR36: na | AS36: na | AT36: 45636 | AU36: 45646 | AW36: 45646 | BC36: |
B37: =IF(D37=$A$516,1,IF(D37=$A$517,2,IF(D37=$A$518,3,IF(D37=$A$519,4,IF(D37=$A$520,5,IF(D37=$A$521,6)))))) -> 3 | D37: =IF(AL37="Closed","cls",IF(AL37=1,"sgn",IF(AL37="On-hold","hld",IF(AL37="Aborted","abt",IF(AL37<1,"wip","RIP"))))) -> wip | E37: Fagioli PFW | G37: RE | H37: 00674300355 | J37: Logistics | K37: Project Cargo - freight forwarding | M37: Quattro R | S37: no | T37: 2022 | U37: 32 | V37: 4.503 | W37: =+V37/U37 -> 0.14071875 | X37: 2.26 | Y37: 46.553 | AA37: Relazione | AC37: ASC | AD37: ASC | AE37: RIM | AF37: SEB | AI37: =+TODAY()-AM37 -> 242 | AJ37: =+(IF(AL37="Closed","-",IF(TODAY()-MAX(AN37:BA37)>0,TODAY()-MAX(AN37:BA37),0))) -> 36 | AK37: Sell Side | AL37: =+IF(BB37="",IF(AZ37="",IF(AY37="",IF(AX37="",COUNTA(AN37:AV37)/9,"On-hold"),"Aborted"),"Closed"),"RIP") -> 0.66666667 | AM37: 45422 | AN37: 45422 | AO37: 45422 | AP37: 45422 | AQ37: 45432 | AR37: 45471 | AS37: 45628 | AW37: 45628 | BC37: |
B38: =IF(D38=$A$516,1,IF(D38=$A$517,2,IF(D38=$A$518,3,IF(D38=$A$519,4,IF(D38=$A$520,5,IF(D38=$A$521,6)))))) -> 3 | D38: =IF(AL38="Closed","cls",IF(AL38=1,"sgn",IF(AL38="On-hold","hld",IF(AL38="Aborted","abt",IF(AL38<1,"wip","RIP"))))) -> wip | E38: Gemarmed | F38: Apollo | G38: MO | J38: Pharma | K38: Consulenza nella certificazione di medical devices | L38: Mario Gennari | S38: no | AA38: Segnalatore | AB38: GMAP | AC38: ASC | AD38: ASC | AE38: PAD | AH38: 1 | AI38: =+TODAY()-AM38 -> 333 | AJ38: =+(IF(AL38="Closed","-",IF(TODAY()-MAX(AN38:BA38)>0,TODAY()-MAX(AN38:BA38),0))) -> 288 | AK38: Buy Side | AL38: =+IF(BB38="",IF(AZ38="",IF(AY38="",IF(AX38="",COUNTA(AN38:AV38)/9,"On-hold"),"Aborted"),"Closed"),"RIP") -> 0.55555556 | AM38: 45331 | AN38: 45331 | AO38: na | AP38: 45335 | AQ38: 45335 | AR38: 45376 | BC38: |
B39: =IF(D39=$A$516,1,IF(D39=$A$517,2,IF(D39=$A$518,3,IF(D39=$A$519,4,IF(D39=$A$520,5,IF(D39=$A$521,6)))))) -> 3 | D39: =IF(AL39="Closed","cls",IF(AL39=1,"sgn",IF(AL39="On-hold","hld",IF(AL39="Aborted","abt",IF(AL39<1,"wip","RIP"))))) -> wip | E39: Weerts Logistics Parks (WLP) | G39: Belgio | J39: Logistics | K39: Sviluppo e gestione di immobili logistici di alto livello in Europa | L39: Othmane Sabere | P39: Christophe Weerts | S39: no | T39: 2023 | W39: =+V39/U39 -> #DIV/0! | AA39: Segnalatore | AB39: Ivano Pelassa | AC39: FCA | AD39: FCA | AE39: MMO | AG39: ZES unica Sud-Bari | AI39: =+TODAY()-AM39 -> 57 | AJ39: =+(IF(AL39="Closed","-",IF(TODAY()-MAX(AN39:BA39)>0,TODAY()-MAX(AN39:BA39),0))) -> 57 | AK39: Agevolato | AL39: =+IF(BB39="",IF(AZ39="",IF(AY39="",IF(AX39="",COUNTA(AN39:AV39)/9,"On-hold"),"Aborted"),"Closed"),"RIP") -> 0.44444444 | AM39: 45607 | AN39: 45607 | AO39: na | AP39: 45607 | AQ39: 45607 | AW39: 45607 | BC39: |
B40: =IF(D40=$A$516,1,IF(D40=$A$517,2,IF(D40=$A$518,3,IF(D40=$A$519,4,IF(D40=$A$520,5,IF(D40=$A$521,6)))))) -> 3 | D40: =IF(AL40="Closed","cls",IF(AL40=1,"sgn",IF(AL40="On-hold","hld",IF(AL40="Aborted","abt",IF(AL40<1,"wip","RIP"))))) -> wip | E40: EUROSPITAL SpA | G40: TS | H40: 00047510326 | J40: Medical Equipment | K40: Produzione equipment e consumables per laboratori analisi | L40: Massimiliano Kropf | M40: Michele Kropf | N40: Massimiliano Kropf | P40: Massimiliano Kropf | S40: no | T40: 2023 | U40: 38.3 | V40: 3.7 | W40: =+V40/U40 -> 0.096605744 | X40: 1.5 | Y40: 0.5 | AA40: Relazione | AC40: FCA | AD40: FCA | AG40: Meet MEDICA 2024 | AI40: =+TODAY()-AM40 -> 55 | AJ40: =+(IF(AL40="Closed","-",IF(TODAY()-MAX(AN40:BA40)>0,TODAY()-MAX(AN40:BA40),0))) -> 55 | AK40: Sell Side | AL40: =+IF(BB40="",IF(AZ40="",IF(AY40="",IF(AX40="",COUNTA(AN40:AV40)/9,"On-hold"),"Aborted"),"Closed"),"RIP") -> 0.44444444 | AM40: 45609 | AN40: 45609 | AO40: na | AP40: 45609 | AQ40: 45609 | AW40: 45609 | BC40: |
B41: =IF(D41=$A$516,1,IF(D41=$A$517,2,IF(D41=$A$518,3,IF(D41=$A$519,4,IF(D41=$A$520,5,IF(D41=$A$521,6)))))) -> 3 | D41: =IF(AL41="Closed","cls",IF(AL41=1,"sgn",IF(AL41="On-hold","hld",IF(AL41="Aborted","abt",IF(AL41<1,"wip","RIP"))))) -> wip | E41: BORGHI SpA | G41: MO | H41: 03575150366 | J41: Machinery | K41: Produzione di macchine per l'industria delle spazzole | L41: Andrea Del Carlo | M41: Marco Solato | N41: Fabrizio Biagi | P41: Giampaolo Roversi | S41: no | T41: 2023 | U41: 33 | V41: 1.4 | W41: =+V41/U41 -> 0.042424242 | X41: 0.6 | Y41: 3.6 | AA41: Fiera | AC41: FCA | AD41: FCA | AG41: Meet MEDICA 2024 | AI41: =+TODAY()-AM41 -> 55 | AJ41: =+(IF(AL41="Closed","-",IF(TODAY()-MAX(AN41:BA41)>0,TODAY()-MAX(AN41:BA41),0))) -> 55 | AK41: Agevolato | AL41: =+IF(BB41="",IF(AZ41="",IF(AY41="",IF(AX41="",COUNTA(AN41:AV41)/9,"On-hold"),"Aborted"),"Closed"),"RIP") -> 0.44444444 | AM41: 45609 | AN41: 45609 | AO41: na | AP41: 45609 | AQ41: 45609 | AW41: 45609 | BC41: |
B42: =IF(D42=$A$516,1,IF(D42=$A$517,2,IF(D42=$A$518,3,IF(D42=$A$519,4,IF(D42=$A$520,5,IF(D42=$A$521,6)))))) -> 3 | D42: =IF(AL42="Closed","cls",IF(AL42=1,"sgn",IF(AL42="On-hold","hld",IF(AL42="Aborted","abt",IF(AL42<1,"wip","RIP"))))) -> wip | E42: M.D.L. Srl | G42: SO | H42: 00656810140 | J42: Medical Disposables | K42: Produzione aghi speciali per biopsie e chirurgia | L42: Simone Dell'Oca | M42: Marcello Dell'Oca | S42: no | T42: 2023 | U42: 8.2 | V42: 2 | W42: =+V42/U42 -> 0.24390244 | X42: 1.1 | Y42: -1.1 | AA42: Fiera | AC42: FCA | AD42: FCA | AG42: Meet MEDICA 2024 | AI42: =+TODAY()-AM42 -> 55 | AJ42: =+(IF(AL42="Closed","-",IF(TODAY()-MAX(AN42:BA42)>0,TODAY()-MAX(AN42:BA42),0))) -> 55 | AK42: Sell Side | AL42: =+IF(BB42="",IF(AZ42="",IF(AY42="",IF(AX42="",COUNTA(AN42:AV42)/9,"On-hold"),"Aborted"),"Closed"),"RIP") -> 0.44444444 | AM42: 45609 | AN42: 45609 | AO42: na | AP42: 45609 | AQ42: 45609 | AW42: 45609 | BC42: |
B43: =IF(D43=$A$516,1,IF(D43=$A$517,2,IF(D43=$A$518,3,IF(D43=$A$519,4,IF(D43=$A$520,5,IF(D43=$A$521,6)))))) -> 3 | D43: =IF(AL43="Closed","cls",IF(AL43=1,"sgn",IF(AL43="On-hold","hld",IF(AL43="Aborted","abt",IF(AL43<1,"wip","RIP"))))) -> wip | E43: APTACA SpA | G43: AS | H43: 00862050960 | J43: Medical Disposables | K43: Dispositivi monouso e riutilizzabili per Laboratori Analisi, Ospedali, Istituti di Ricerca e per l’Industria Chimica e Farmaceutica. | L43: Duilio Buono | M43: Simone Buono | N43: Duilio Buono | P43: Simone Buono | S43: no | T43: 2023 | U43: 16.5 | V43: 1.2 | W43: =+V43/U43 -> 0.072727273 | X43: 0.3 | Y43: 3 | AA43: Fiera | AC43: FCA | AD43: FCA | AG43: Meet MEDICA 2024 | AI43: =+TODAY()-AM43 -> 55 | AJ43: =+(IF(AL43="Closed","-",IF(TODAY()-MAX(AN43:BA43)>0,TODAY()-MAX(AN43:BA43),0))) -> 55 | AL43: =+IF(BB43="",IF(AZ43="",IF(AY43="",IF(AX43="",COUNTA(AN43:AV43)/9,"On-hold"),"Aborted"),"Closed"),"RIP") -> 0.44444444 | AM43: 45609 | AN43: 45609 | AO43: na | AP43: 45609 | AQ43: 45609 | AW43: 45609 | BC43: |
B44: =IF(D44=$A$516,1,IF(D44=$A$517,2,IF(D44=$A$518,3,IF(D44=$A$519,4,IF(D44=$A$520,5,IF(D44=$A$521,6)))))) -> 3 | D44: =IF(AL44="Closed","cls",IF(AL44=1,"sgn",IF(AL44="On-hold","hld",IF(AL44="Aborted","abt",IF(AL44<1,"wip","RIP"))))) -> wip | E44: Frau Pharma | G44: MB | H44: 03758850162 | J44: Pharma | K44: Produzione di APIs | L44: Francesco Autuori | M44: Francesco Autuori | S44: no | T44: 2023 | U44: 5.9 | V44: 2 | W44: =+V44/U44 -> 0.33898305 | X44: 0.894 | Y44: -3.149 | AA44: Relazione | AC44: ASC | AD44: ASC | AH44: 1 | AI44: =+TODAY()-AM44 -> 36 | AJ44: =+(IF(AL44="Closed","-",IF(TODAY()-MAX(AN44:BA44)>0,TODAY()-MAX(AN44:BA44),0))) -> 36 | AK44: Buy Side | AL44: =+IF(BB44="",IF(AZ44="",IF(AY44="",IF(AX44="",COUNTA(AN44:AV44)/9,"On-hold"),"Aborted"),"Closed"),"RIP") -> 0.11111111 | AM44: 45628 | AN44: 45628 | BC44: |
B45: =IF(D45=$A$516,1,IF(D45=$A$517,2,IF(D45=$A$518,3,IF(D45=$A$519,4,IF(D45=$A$520,5,IF(D45=$A$521,6)))))) -> 3 | D45: =IF(AL45="Closed","cls",IF(AL45=1,"sgn",IF(AL45="On-hold","hld",IF(AL45="Aborted","abt",IF(AL45<1,"wip","RIP"))))) -> wip | E45: Ivas Industria Vernici SpA | G45: FC | H45: 00124120403 | J45: Chemicals | K45: Vernici e altri materiali a base chimica per l'edilizia | M45: Filippo Colonna | N45: Federico Colonna | O45: Filippo Colonna | P45: Filippo Colonna | S45: si | T45: 2023 | U45: 83.98 | V45: 15.402 | W45: =+V45/U45 -> 0.18340081 | X45: 8.96 | Y45: 8.55 | AA45: Cold Call | AC45: ASC | AD45: ASC | AE45: GIM | AI45: =+TODAY()-AM45 -> 54 | AJ45: =+(IF(AL45="Closed","-",IF(TODAY()-MAX(AN45:BA45)>0,TODAY()-MAX(AN45:BA45),0))) -> 54 | AK45: Sell Side | AL45: =+IF(BB45="",IF(AZ45="",IF(AY45="",IF(AX45="",COUNTA(AN45:AV45)/9,"On-hold"),"Aborted"),"Closed"),"RIP") -> 0 | AM45: 45610 | AW45: 45610 | BC45: |
B46: =IF(D46=$A$516,1,IF(D46=$A$517,2,IF(D46=$A$518,3,IF(D46=$A$519,4,IF(D46=$A$520,5,IF(D46=$A$521,6)))))) -> 4 | D46: =IF(AL46="Closed","cls",IF(AL46=1,"sgn",IF(AL46="On-hold","hld",IF(AL46="Aborted","abt",IF(AL46<1,"wip","RIP"))))) -> hld | E46: Tampieri | G46: RA | H46: 02075400396 | I46: 104120 | J46: Food | K46: Produzione olio | S46: no | T46: 2023 | U46: 382.493 | V46: 19 | W46: =+V46/U46 -> 0.049674112 | X46: 14 | Y46: 13.2 | AA46: Relazione | AC46: ASC/FCA | AD46: ASC/FCA | AE46: PAD | AF46: ASP | AH46: 1 | AI46: =+TODAY()-AM46 -> 603 | AJ46: =+(IF(AL46="Closed","-",IF(TODAY()-MAX(AN46:BA46)>0,TODAY()-MAX(AN46:BA46),0))) -> 245 | AK46: Sell Side | AL46: =+IF(BB46="",IF(AZ46="",IF(AY46="",IF(AX46="",COUNTA(AN46:AV46)/9,"On-hold"),"Aborted"),"Closed"),"RIP") -> On-hold | AM46: 45061 | AN46: 45061 | AO46: na | AP46: 45061 | AQ46: 45061 | AR46: 45108 | AS46: 45177 | AT46: 45224 | AU46: na | AV46: 45224 | AW46: 45419 | AX46: 45419 | BA46: =+IF(AY46="","",COUNTA(AN46:AV46)/(COUNTA(AN46:AV46)+COUNTBLANK(AN46:AV46))) | BC46: |
B47: =IF(D47=$A$516,1,IF(D47=$A$517,2,IF(D47=$A$518,3,IF(D47=$A$519,4,IF(D47=$A$520,5,IF(D47=$A$521,6)))))) -> 4 | D47: =IF(AL47="Closed","cls",IF(AL47=1,"sgn",IF(AL47="On-hold","hld",IF(AL47="Aborted","abt",IF(AL47<1,"wip","RIP"))))) -> hld | E47: Edra SpA | G47: PI | H47: 00670710508 | J47: Design | K47: Arredamento di lusso | S47: no | T47: 2022 | U47: 57.875 | V47: 20.706 | W47: =+V47/U47 -> 0.35777106 | X47: 14.236 | Y47: -29.947 | AA47: Relazione | AC47: ROS | AD47: ROS | AI47: =+TODAY()-AM47 -> 281 | AJ47: =+(IF(AL47="Closed","-",IF(TODAY()-MAX(AN47:BA47)>0,TODAY()-MAX(AN47:BA47),0))) -> 245 | AK47: Sell Side | AL47: =+IF(BB47="",IF(AZ47="",IF(AY47="",IF(AX47="",COUNTA(AN47:AV47)/9,"On-hold"),"Aborted"),"Closed"),"RIP") -> On-hold | AM47: 45383 | AN47: 45383 | AO47: na | AP47: 44846 | AQ47: 45399 | AW47: 45399 | AX47: 45419 | BA47: =+IF(AY47="","",COUNTA(AN47:AV47)/(COUNTA(AN47:AV47)+COUNTBLANK(AN47:AV47))) | BC47: |
B48: =IF(D48=$A$516,1,IF(D48=$A$517,2,IF(D48=$A$518,3,IF(D48=$A$519,4,IF(D48=$A$520,5,IF(D48=$A$521,6)))))) -> 4 | D48: =IF(AL48="Closed","cls",IF(AL48=1,"sgn",IF(AL48="On-hold","hld",IF(AL48="Aborted","abt",IF(AL48<1,"wip","RIP"))))) -> hld | E48: Anthilia | G48: MI | J48: FONDO_PD | K48: Generalista | L48: Tobia Dian | S48: no | AA48: Relazione | AC48: RIM | AI48: =+TODAY()-AM48 -> 260 | AJ48: =+(IF(AL48="Closed","-",IF(TODAY()-MAX(AN48:BA48)>0,TODAY()-MAX(AN48:BA48),0))) -> 260 | AK48: Fondo | AL48: =+IF(BB48="",IF(AZ48="",IF(AY48="",IF(AX48="",COUNTA(AN48:AV48)/9,"On-hold"),"Aborted"),"Closed"),"RIP") -> On-hold | AM48: 45404 | AN48: 45404 | AO48: 45404 | AP48: 45404 | AQ48: 45404 | AW48: 45404 | AX48: 45404 | BA48: =+IF(AY48="","",COUNTA(AN48:AV48)/(COUNTA(AN48:AV48)+COUNTBLANK(AN48:AV48))) | BC48: |
B49: =IF(D49=$A$516,1,IF(D49=$A$517,2,IF(D49=$A$518,3,IF(D49=$A$519,4,IF(D49=$A$520,5,IF(D49=$A$521,6)))))) -> 4 | D49: =IF(AL49="Closed","cls",IF(AL49=1,"sgn",IF(AL49="On-hold","hld",IF(AL49="Aborted","abt",IF(AL49<1,"wip","RIP"))))) -> hld | E49: Azimut Libera Impresa | G49: MI | J49: FONDO_PE | K49: Generalista | L49: Giacomo Nava | S49: no | AA49: Relazione | AC49: RIM | AI49: =+TODAY()-AM49 -> 252 | AJ49: =+(IF(AL49="Closed","-",IF(TODAY()-MAX(AN49:BA49)>0,TODAY()-MAX(AN49:BA49),0))) -> 252 | AK49: Fondo | AL49: =+IF(BB49="",IF(AZ49="",IF(AY49="",IF(AX49="",COUNTA(AN49:AV49)/9,"On-hold"),"Aborted"),"Closed"),"RIP") -> On-hold | AM49: 45412 | AN49: 45412 | AO49: 45412 | AP49: 45412 | AQ49: 45412 | AW49: 45412 | AX49: 45412 | BA49: =+IF(AY49="","",COUNTA(AN49:AV49)/(COUNTA(AN49:AV49)+COUNTBLANK(AN49:AV49))) | BC49: |
B50: =IF(D50=$A$516,1,IF(D50=$A$517,2,IF(D50=$A$518,3,IF(D50=$A$519,4,IF(D50=$A$520,5,IF(D50=$A$521,6)))))) -> 4 | D50: =IF(AL50="Closed","cls",IF(AL50=1,"sgn",IF(AL50="On-hold","hld",IF(AL50="Aborted","abt",IF(AL50<1,"wip","RIP"))))) -> hld | E50: Pricoa | G50: MI | J50: FONDO_PD | K50: Generalista | L50: Giacomo Barone | S50: no | AA50: Relazione | AC50: RIM | AI50: =+TODAY()-AM50 -> 260 | AJ50: =+(IF(AL50="Closed","-",IF(TODAY()-MAX(AN50:BA50)>0,TODAY()-MAX(AN50:BA50),0))) -> 260 | AK50: Fondo | AL50: =+IF(BB50="",IF(AZ50="",IF(AY50="",IF(AX50="",COUNTA(AN50:AV50)/9,"On-hold"),"Aborted"),"Closed"),"RIP") -> On-hold | AM50: 45404 | AN50: 45404 | AO50: 45404 | AP50: 45404 | AQ50: 45404 | AW50: 45404 | AX50: 45404 | BA50: =+IF(AY50="","",COUNTA(AN50:AV50)/(COUNTA(AN50:AV50)+COUNTBLANK(AN50:AV50))) | BC50: |
B51: =IF(D51=$A$516,1,IF(D51=$A$517,2,IF(D51=$A$518,3,IF(D51=$A$519,4,IF(D51=$A$520,5,IF(D51=$A$521,6)))))) -> 4 | D51: =IF(AL51="Closed","cls",IF(AL51=1,"sgn",IF(AL51="On-hold","hld",IF(AL51="Aborted","abt",IF(AL51<1,"wip","RIP"))))) -> hld | E51: Clessidra PD | G51: MI | J51: FONDO_PD | K51: Generalista | L51: Roberto Ippolito | S51: no | AA51: Relazione | AC51: ASC | AD51: ASC | AE51: RIM | AI51: =+TODAY()-AM51 -> 260 | AJ51: =+(IF(AL51="Closed","-",IF(TODAY()-MAX(AN51:BA51)>0,TODAY()-MAX(AN51:BA51),0))) -> 260 | AK51: Fondo | AL51: =+IF(BB51="",IF(AZ51="",IF(AY51="",IF(AX51="",COUNTA(AN51:AV51)/9,"On-hold"),"Aborted"),"Closed"),"RIP") -> On-hold | AM51: 45404 | AN51: 45404 | AO51: 45404 | AP51: 45404 | AQ51: 45404 | AW51: 45404 | AX51: 45404 | BC51: |
B52: =IF(D52=$A$516,1,IF(D52=$A$517,2,IF(D52=$A$518,3,IF(D52=$A$519,4,IF(D52=$A$520,5,IF(D52=$A$521,6)))))) -> 4 | D52: =IF(AL52="Closed","cls",IF(AL52=1,"sgn",IF(AL52="On-hold","hld",IF(AL52="Aborted","abt",IF(AL52<1,"wip","RIP"))))) -> hld | E52: Solbian spa | G52: TO | H52: 10201500013 | J52: Energia | K52: Produzione di panelli solari per nautica | L52: Enrique Garcia | S52: no | T52: 2023 | U52: 6.245 | V52: 0.977 | W52: =+V52/U52 -> 0.15644516 | X52: 0.335 | Y52: 1.507 | AA52: Relazione | AC52: ROS | AD52: ROS | AI52: =+TODAY()-AM52 -> 281 | AJ52: =+(IF(AL52="Closed","-",IF(TODAY()-MAX(AN52:BA52)>0,TODAY()-MAX(AN52:BA52),0))) -> 252 | AK52: Sell Side | AL52: =+IF(BB52="",IF(AZ52="",IF(AY52="",IF(AX52="",COUNTA(AN52:AV52)/9,"On-hold"),"Aborted"),"Closed"),"RIP") -> On-hold | AM52: 45383 | AN52: 45383 | AO52: na | AP52: 44846 | AQ52: 45399 | AW52: 45399 | AX52: 45412 | BA52: =+IF(AY52="","",COUNTA(AN52:AV52)/(COUNTA(AN52:AV52)+COUNTBLANK(AN52:AV52))) | BC52: |
B53: =IF(D53=$A$516,1,IF(D53=$A$517,2,IF(D53=$A$518,3,IF(D53=$A$519,4,IF(D53=$A$520,5,IF(D53=$A$521,6)))))) -> 4 | D53: =IF(AL53="Closed","cls",IF(AL53=1,"sgn",IF(AL53="On-hold","hld",IF(AL53="Aborted","abt",IF(AL53<1,"wip","RIP"))))) -> hld | E53: Tersan | G53: BA | H53: 00475590725 | J53: Energia | K53: Energia / Smaltimento rifiuti | S53: no | T53: 2022 | U53: 22.1 | V53: 9.5 | W53: =+V53/U53 -> 0.42986425 | X53: 4.5 | Y53: 0.4 | AA53: Relazione | AC53: ROS | AD53: ROS | AI53: =+TODAY()-AM53 -> 267 | AJ53: =+(IF(AL53="Closed","-",IF(TODAY()-MAX(AN53:BA53)>0,TODAY()-MAX(AN53:BA53),0))) -> 265 | AK53: Sell Side | AL53: =+IF(BB53="",IF(AZ53="",IF(AY53="",IF(AX53="",COUNTA(AN53:AV53)/9,"On-hold"),"Aborted"),"Closed"),"RIP") -> On-hold | AM53: 45397 | AN53: 45397 | AO53: 45397 | AP53: 45397 | AQ53: 45399 | AW53: 45399 | AX53: 45399 | BA53: =+IF(AY53="","",COUNTA(AN53:AV53)/(COUNTA(AN53:AV53)+COUNTBLANK(AN53:AV53))) | BC53: |
B54: =IF(D54=$A$516,1,IF(D54=$A$517,2,IF(D54=$A$518,3,IF(D54=$A$519,4,IF(D54=$A$520,5,IF(D54=$A$521,6)))))) -> 4 | D54: =IF(AL54="Closed","cls",IF(AL54=1,"sgn",IF(AL54="On-hold","hld",IF(AL54="Aborted","abt",IF(AL54<1,"wip","RIP"))))) -> hld | E54: Edilkamin | G54: MI | H54: 00192220192 | I54: 236100 | J54: Industrial | K54: Produzione caminetti e stufe a pellet e legna | L54: Fam. Borsatti | S54: no | T54: 2022 | U54: 88.2 | V54: 5.133 | W54: =+V54/U54 -> 0.058197279 | X54: 2.526 | Y54: -2.157 | AA54: Segnalatore | AB54: Mauro Radaelli | AC54: ASC | AD54: ASC | AE54: RIM | AI54: =+TODAY()-AM54 -> 274 | AJ54: =+(IF(AL54="Closed","-",IF(TODAY()-MAX(AN54:BA54)>0,TODAY()-MAX(AN54:BA54),0))) -> 253 | AK54: Sell Side | AL54: =+IF(BB54="",IF(AZ54="",IF(AY54="",IF(AX54="",COUNTA(AN54:AV54)/9,"On-hold"),"Aborted"),"Closed"),"RIP") -> On-hold | AM54: 45390 | AN54: 45390 | AO54: 45390 | AP54: 45390 | AW54: 45390 | AX54: 45411 | BC54: |
B55: =IF(D55=$A$516,1,IF(D55=$A$517,2,IF(D55=$A$518,3,IF(D55=$A$519,4,IF(D55=$A$520,5,IF(D55=$A$521,6)))))) -> 4 | D55: =IF(AL55="Closed","cls",IF(AL55=1,"sgn",IF(AL55="On-hold","hld",IF(AL55="Aborted","abt",IF(AL55<1,"wip","RIP"))))) -> hld | E55: LAURETANA | G55: BI | H55: 00166260026 | I55: 110700 | J55: Food: Beverage | K55: INDUSTRIA DELLE BIBITE ANALCOLICHE, DELLE ACQUE MINERALI E DI ALTR ACQUE IN BOTTIGLIA | L55: Giovanni Vietti Michelina | M55: Giovanni Vietti Michelina | N55: Anna Rina Vietti Michelina | O55: Giovanni Vietti Michelina | P55: Antonio Pola | Q55: Alberto Murialdo | S55: no | T55: 2023 | U55: 55.084 | V55: 19 | W55: =+V55/U55 -> 0.34492775 | X55: 12.129 | Y55: -24.2 | AA55: Relazione | AC55: ASC | AD55: ASC | AI55: =+TODAY()-AM55 -> 1351 | AJ55: =+(IF(AL55="Closed","-",IF(TODAY()-MAX(AN55:BA55)>0,TODAY()-MAX(AN55:BA55),0))) -> 28 | AK55: Sell Side | AL55: =+IF(BB55="",IF(AZ55="",IF(AY55="",IF(AX55="",COUNTA(AN55:AV55)/9,"On-hold"),"Aborted"),"Closed"),"RIP") -> On-hold | AM55: 44313 | AN55: 44313 | AO55: na | AP55: 44313 | AQ55: 44375 | AW55: 45636 | AX55: 45291 | BA55: =+IF(AY55="","",COUNTA(AN55:AV55)/(COUNTA(AN55:AV55)+COUNTBLANK(AN55:AV55))) | BC55: |
B56: =IF(D56=$A$516,1,IF(D56=$A$517,2,IF(D56=$A$518,3,IF(D56=$A$519,4,IF(D56=$A$520,5,IF(D56=$A$521,6)))))) -> 4 | D56: =IF(AL56="Closed","cls",IF(AL56=1,"sgn",IF(AL56="On-hold","hld",IF(AL56="Aborted","abt",IF(AL56<1,"wip","RIP"))))) -> hld | E56: Gefran | G56: BS | H56: 03032420170 | I56: 265129 | J56: Industrial | K56: Sensori | L56: Fam. Franceschetti | M56: Fingefran Srl | N56: Lazard Frères Banque Sa | O56: Maria Chiara Franceschetti | P56: Marcello Perini | S56: si | T56: 2022 | U56: 132.491 | V56: 25 | W56: =+V56/U56 -> 0.18869206 | X56: 10 | Y56: -24 | AA56: Segnalatore | AB56: Piccolo Daniele | AC56: ASC | AD56: ASC | AE56: RIM | AI56: =+TODAY()-AM56 -> 1267 | AJ56: =+(IF(AL56="Closed","-",IF(TODAY()-MAX(AN56:BA56)>0,TODAY()-MAX(AN56:BA56),0))) -> 259 | AK56: Buy Side | AL56: =+IF(BB56="",IF(AZ56="",IF(AY56="",IF(AX56="",COUNTA(AN56:AV56)/9,"On-hold"),"Aborted"),"Closed"),"RIP") -> On-hold | AM56: 44397 | AN56: 44397 | AO56: na | AP56: 44446 | AQ56: 45366 | AR56: 45398 | AW56: 45398 | AX56: 45405 | BA56: =+IF(AY56="","",COUNTA(AN56:AV56)/(COUNTA(AN56:AV56)+COUNTBLANK(AN56:AV56))) | BC56: |
B57: =IF(D57=$A$516,1,IF(D57=$A$517,2,IF(D57=$A$518,3,IF(D57=$A$519,4,IF(D57=$A$520,5,IF(D57=$A$521,6)))))) -> 4 | D57: =IF(AL57="Closed","cls",IF(AL57=1,"sgn",IF(AL57="On-hold","hld",IF(AL57="Aborted","abt",IF(AL57<1,"wip","RIP"))))) -> hld | E57: Paragon Partners | G57: Germania | J57: FONDO_PE | K57: Generalista | L57: Stefano Tatarella | AA57: Relazione | AC57: ASC | AD57: ASC | AE57: RIM | AF57: PAD | AH57: 1 | AI57: =+TODAY()-AM57 -> 294 | AJ57: =+(IF(AL57="Closed","-",IF(TODAY()-MAX(AN57:BA57)>0,TODAY()-MAX(AN57:BA57),0))) -> 260 | AK57: Fondo | AL57: =+IF(BB57="",IF(AZ57="",IF(AY57="",IF(AX57="",COUNTA(AN57:AV57)/9,"On-hold"),"Aborted"),"Closed"),"RIP") -> On-hold | AM57: 45370 | AN57: 45370 | AO57: na | AP57: 45370 | AQ57: 45370 | AR57: 45386 | AW57: 45386 | AX57: 45404 | BC57: |
B58: =IF(D58=$A$516,1,IF(D58=$A$517,2,IF(D58=$A$518,3,IF(D58=$A$519,4,IF(D58=$A$520,5,IF(D58=$A$521,6)))))) -> 4 | D58: =IF(AL58="Closed","cls",IF(AL58=1,"sgn",IF(AL58="On-hold","hld",IF(AL58="Aborted","abt",IF(AL58<1,"wip","RIP"))))) -> hld | E58: MASMEC - S.P.A. | G58: BA | H58: 03805970724 | J58: Tech | K58: Robotica | L58: Dott. Vinci | M58: fam. Vinci | S58: no | T58: 2022 | U58: 39.109 | V58: 5.676 | W58: =+V58/U58 -> 0.14513283 | X58: 0.893 | Y58: 20 | AA58: Cold Call | AC58: FCA | AD58: FCA | AE58: ASP | AI58: =+TODAY()-AM58 -> 351 | AJ58: =+(IF(AL58="Closed","-",IF(TODAY()-MAX(AN58:BA58)>0,TODAY()-MAX(AN58:BA58),0))) -> 259 | AK58: Sell Side | AL58: =+IF(BB58="",IF(AZ58="",IF(AY58="",IF(AX58="",COUNTA(AN58:AV58)/9,"On-hold"),"Aborted"),"Closed"),"RIP") -> On-hold | AM58: 45313 | AN58: 45316 | AO58: na | AP58: 45317 | AQ58: 45324 | AW58: 45324 | AX58: 45405 | BC58: |
B59: =IF(D59=$A$516,1,IF(D59=$A$517,2,IF(D59=$A$518,3,IF(D59=$A$519,4,IF(D59=$A$520,5,IF(D59=$A$521,6)))))) -> 4 | D59: =IF(AL59="Closed","cls",IF(AL59=1,"sgn",IF(AL59="On-hold","hld",IF(AL59="Aborted","abt",IF(AL59<1,"wip","RIP"))))) -> hld | E59: Tecnosytemi | G59: TV | H59: 02535780247 | J59: HVAC | K59: Componenti per HVAC | L59: Anna Munari | S59: no | T59: 2022 | U59: 50.055008 | V59: 11.616713 | W59: =+V59/U59 -> 0.23207894 | X59: 6 | Y59: 4 | AA59: Fiera | AC59: ASC | AD59: ASC | AE59: PAD | AH59: 1 | AI59: =+TODAY()-AM59 -> 300 | AJ59: =+(IF(AL59="Closed","-",IF(TODAY()-MAX(AN59:BA59)>0,TODAY()-MAX(AN59:BA59),0))) -> 259 | AK59: Sell Side | AL59: =+IF(BB59="",IF(AZ59="",IF(AY59="",IF(AX59="",COUNTA(AN59:AV59)/9,"On-hold"),"Aborted"),"Closed"),"RIP") -> On-hold | AM59: 45364 | AN59: 45364 | AO59: 45364 | AP59: 45364 | AQ59: 45364 | AR59: 45380 | AS59: 45391 | AX59: 45405 | BC59: |
B60: =IF(D60=$A$516,1,IF(D60=$A$517,2,IF(D60=$A$518,3,IF(D60=$A$519,4,IF(D60=$A$520,5,IF(D60=$A$521,6)))))) -> 4 | D60: =IF(AL60="Closed","cls",IF(AL60=1,"sgn",IF(AL60="On-hold","hld",IF(AL60="Aborted","abt",IF(AL60<1,"wip","RIP"))))) -> hld | E60: Speroni Water Pumps | G60: RE | H60: 00133990358 | J60: HVAC | K60: Pompe acqua | L60: Giuseppe Speroni | S60: no | T60: 2022 | U60: 54.591 | V60: 5.039 | W60: =+V60/U60 -> 0.092304592 | X60: 2 | Y60: 12 | AA60: Fiera | AC60: ASC | AD60: ASC | AE60: PAD | AH60: 1 | AI60: =+TODAY()-AM60 -> 300 | AJ60: =+(IF(AL60="Closed","-",IF(TODAY()-MAX(AN60:BA60)>0,TODAY()-MAX(AN60:BA60),0))) -> 259 | AK60: Sell Side | AL60: =+IF(BB60="",IF(AZ60="",IF(AY60="",IF(AX60="",COUNTA(AN60:AV60)/9,"On-hold"),"Aborted"),"Closed"),"RIP") -> On-hold | AM60: 45364 | AN60: 45364 | AO60: 45364 | AP60: 45364 | AQ60: 45364 | AX60: 45405 | BC60: |
B61: =IF(D61=$A$516,1,IF(D61=$A$517,2,IF(D61=$A$518,3,IF(D61=$A$519,4,IF(D61=$A$520,5,IF(D61=$A$521,6)))))) -> 4 | D61: =IF(AL61="Closed","cls",IF(AL61=1,"sgn",IF(AL61="On-hold","hld",IF(AL61="Aborted","abt",IF(AL61<1,"wip","RIP"))))) -> hld | E61: Arneg Spa | G61: PD | H61: 00220200281 | I61: 282500 | J61: Industrial | K61: Banchi frigo | L61: Daniele Marzaro | S61: si | T61: 2022 | U61: 320 | V61: 28 | W61: =+V61/U61 -> 0.0875 | X61: 20 | Y61: 4.233 | AA61: Cold Call | AC61: ASC | AD61: ASC | AE61: GID | AI61: =+TODAY()-AM61 -> 277 | AJ61: =+(IF(AL61="Closed","-",IF(TODAY()-MAX(AN61:BA61)>0,TODAY()-MAX(AN61:BA61),0))) -> 273 | AK61: Controparte | AL61: =+IF(BB61="",IF(AZ61="",IF(AY61="",IF(AX61="",COUNTA(AN61:AV61)/9,"On-hold"),"Aborted"),"Closed"),"RIP") -> On-hold | AM61: 45387 | AN61: 45387 | AO61: na | AP61: 45391 | AW61: 45391 | AX61: 45391 | BC61: |
B62: =IF(D62=$A$516,1,IF(D62=$A$517,2,IF(D62=$A$518,3,IF(D62=$A$519,4,IF(D62=$A$520,5,IF(D62=$A$521,6)))))) -> 4 | D62: =IF(AL62="Closed","cls",IF(AL62=1,"sgn",IF(AL62="On-hold","hld",IF(AL62="Aborted","abt",IF(AL62<1,"wip","RIP"))))) -> hld | E62: La Coque de Nacre | G62: Francia | J62: Fashion | K62: Gioielli - designer e rivenditori | S62: no | T62: 2022 | U62: 40 | W62: =+V62/U62 -> 0 | AA62: GMAP | AC62: LOM | AD62: LOM | AE62: GID | AI62: =+TODAY()-AM62 -> 648 | AJ62: =+(IF(AL62="Closed","-",IF(TODAY()-MAX(AN62:BA62)>0,TODAY()-MAX(AN62:BA62),0))) -> 271 | AK62: Buy Side | AL62: =+IF(BB62="",IF(AZ62="",IF(AY62="",IF(AX62="",COUNTA(AN62:AV62)/9,"On-hold"),"Aborted"),"Closed"),"RIP") -> On-hold | AM62: 45016 | AN62: 45016 | AO62: na | AP62: na | AQ62: =+AN62 -> 45016 | AR62: na | AS62: na | AT62: 45219 | AU62: na | AV62: 45236 | AX62: 45393 | BA62: =+IF(AY62="","",COUNTA(AN62:AV62)/(COUNTA(AN62:AV62)+COUNTBLANK(AN62:AV62))) | BC62: |
B63: =IF(D63=$A$516,1,IF(D63=$A$517,2,IF(D63=$A$518,3,IF(D63=$A$519,4,IF(D63=$A$520,5,IF(D63=$A$521,6)))))) -> 4 | D63: =IF(AL63="Closed","cls",IF(AL63=1,"sgn",IF(AL63="On-hold","hld",IF(AL63="Aborted","abt",IF(AL63<1,"wip","RIP"))))) -> hld | E63: J.A.S. JET AIR Service | G63: MI | H63: 01921910152 | J63: Logistic | K63: Spedizioni internazionali via mare e aereo | L63: Biagio Bruni | S63: no | T63: 2023 | U63: 595 | V63: 17 | W63: =+V63/U63 -> 0.028571429 | X63: 13 | Y63: -26 | AA63: Relazione | AC63: ASC | AD63: ASC | AE63: GID | AI63: =+TODAY()-AM63 -> 354 | AJ63: =+(IF(AL63="Closed","-",IF(TODAY()-MAX(AN63:BA63)>0,TODAY()-MAX(AN63:BA63),0))) -> 15 | AK63: Buy Side | AL63: =+IF(BB63="",IF(AZ63="",IF(AY63="",IF(AX63="",COUNTA(AN63:AV63)/9,"On-hold"),"Aborted"),"Closed"),"RIP") -> On-hold | AM63: 45310 | AN63: 45310 | AO63: na | AP63: 45310 | AQ63: 45355 | AR63: 45364 | AW63: 45390 | AX63: 45649 | BA63: =+IF(AY63="","",COUNTA(AN63:AV63)/(COUNTA(AN63:AV63)+COUNTBLANK(AN63:AV63))) | BC63: |
B64: =IF(D64=$A$516,1,IF(D64=$A$517,2,IF(D64=$A$518,3,IF(D64=$A$519,4,IF(D64=$A$520,5,IF(D64=$A$521,6)))))) -> 4 | D64: =IF(AL64="Closed","cls",IF(AL64=1,"sgn",IF(AL64="On-hold","hld",IF(AL64="Aborted","abt",IF(AL64<1,"wip","RIP"))))) -> hld | E64: CGS Swiss | G64: CH | J64: FONDO_PE | K64: Fondo_PE | N64: Thierry Biggoer | S64: no | AA64: Private Equity | AC64: ASC | AD64: ASC | AE64: RIM | AF64: PAD | AH64: 1 | AI64: =+TODAY()-AM64 -> 390 | AJ64: =+(IF(AL64="Closed","-",IF(TODAY()-MAX(AN64:BA64)>0,TODAY()-MAX(AN64:BA64),0))) -> 273 | AK64: Fondo | AL64: =+IF(BB64="",IF(AZ64="",IF(AY64="",IF(AX64="",COUNTA(AN64:AV64)/9,"On-hold"),"Aborted"),"Closed"),"RIP") -> On-hold | AM64: 45274 | AN64: 45274 | AO64: na | AP64: 45274 | AQ64: 45327 | AR64: 45329 | AS64: 45378 | AW64: 45384 | AX64: 45391 | BC64: |
B65: =IF(D65=$A$516,1,IF(D65=$A$517,2,IF(D65=$A$518,3,IF(D65=$A$519,4,IF(D65=$A$520,5,IF(D65=$A$521,6)))))) -> 4 | D65: =IF(AL65="Closed","cls",IF(AL65=1,"sgn",IF(AL65="On-hold","hld",IF(AL65="Aborted","abt",IF(AL65<1,"wip","RIP"))))) -> hld | E65: Industrie Chimiche Forestali | G65: MI | H65: 04918930969 | J65: Chemicals | K65: Produzione di adesivi e tessuti per automotive e calzature | L65: Guido Cami | M65: V.F. Adhesives Srl | N65: Amundi Sgr SpA | O65: Guido Cami | Q65: Paolo Basile | S65: no | T65: 2022 | U65: 88 | V65: 8 | W65: =+V65/U65 -> 0.090909091 | X65: 3.2 | Y65: 8.2 | AA65: Relazione | AC65: ASC | AD65: ASC | AE65: RIM | AI65: =+TODAY()-AM65 -> 348 | AJ65: =+(IF(AL65="Closed","-",IF(TODAY()-MAX(AN65:BA65)>0,TODAY()-MAX(AN65:BA65),0))) -> 273 | AK65: Buy Side | AL65: =+IF(BB65="",IF(AZ65="",IF(AY65="",IF(AX65="",COUNTA(AN65:AV65)/9,"On-hold"),"Aborted"),"Closed"),"RIP") -> On-hold | AM65: 45316 | AN65: =+AM65 -> 45316 | AO65: na | AP65: 45344 | AQ65: 45344 | AR65: 45365 | AW65: 45386 | AX65: 45391 | BA65: =+IF(AY65="","",COUNTA(AN65:AV65)/(COUNTA(AN65:AV65)+COUNTBLANK(AN65:AV65))) | BC65: |
B66: =IF(D66=$A$516,1,IF(D66=$A$517,2,IF(D66=$A$518,3,IF(D66=$A$519,4,IF(D66=$A$520,5,IF(D66=$A$521,6)))))) -> 4 | D66: =IF(AL66="Closed","cls",IF(AL66=1,"sgn",IF(AL66="On-hold","hld",IF(AL66="Aborted","abt",IF(AL66<1,"wip","RIP"))))) -> hld | E66: Diploma | G66: UK | J66: Distribution | K66: Distributore a valore aggiunto di cavi, fasteners, altri componenti meccanici. Attivo anche nel settore healthcare | L66: Steve Sargeant | S66: si | T66: 2023 | U66: 1200 | V66: 240 | W66: =+V66/U66 -> 0.2 | AA66: Relazione | AC66: ASC | AD66: ASC | AE66: PAD | AH66: 1 | AI66: =+TODAY()-AM66 -> 287 | AJ66: =+(IF(AL66="Closed","-",IF(TODAY()-MAX(AN66:BA66)>0,TODAY()-MAX(AN66:BA66),0))) -> 273 | AK66: Sell Side | AL66: =+IF(BB66="",IF(AZ66="",IF(AY66="",IF(AX66="",COUNTA(AN66:AV66)/9,"On-hold"),"Aborted"),"Closed"),"RIP") -> On-hold | AM66: 45377 | AN66: 45370 | AO66: 45370 | AP66: 45370 | AQ66: 45370 | AR66: 45377 | AX66: 45391 | BC66: |
B67: =IF(D67=$A$516,1,IF(D67=$A$517,2,IF(D67=$A$518,3,IF(D67=$A$519,4,IF(D67=$A$520,5,IF(D67=$A$521,6)))))) -> 4 | D67: =IF(AL67="Closed","cls",IF(AL67=1,"sgn",IF(AL67="On-hold","hld",IF(AL67="Aborted","abt",IF(AL67<1,"wip","RIP"))))) -> hld | E67: OF.RA. Officine Ravenna Srl | G67: RA | H67: 02014050393 | J67: Industrial | K67: Costruzione e manutenzione impianti oil & gas | L67: Davide Brusa | S67: no | T67: 2022 | U67: 16.5 | V67: 1.16 | W67: =+V67/U67 -> 0.07030303 | X67: 0.301 | Y67: 4 | AA67: Relazione | AB67: Davide Brusa | AC67: FCA | AD67: FCA | AE67: ASP | AI67: =+TODAY()-AM67 -> 319 | AJ67: =+(IF(AL67="Closed","-",IF(TODAY()-MAX(AN67:BA67)>0,TODAY()-MAX(AN67:BA67),0))) -> 273 | AK67: Sell Side | AL67: =+IF(BB67="",IF(AZ67="",IF(AY67="",IF(AX67="",COUNTA(AN67:AV67)/9,"On-hold"),"Aborted"),"Closed"),"RIP") -> On-hold | AM67: 45345 | AN67: 45345 | AO67: na | AP67: 45345 | AQ67: 45345 | AW67: 45359 | AX67: 45391 | BC67: |
B68: =IF(D68=$A$516,1,IF(D68=$A$517,2,IF(D68=$A$518,3,IF(D68=$A$519,4,IF(D68=$A$520,5,IF(D68=$A$521,6)))))) -> 4 | D68: =IF(AL68="Closed","cls",IF(AL68=1,"sgn",IF(AL68="On-hold","hld",IF(AL68="Aborted","abt",IF(AL68<1,"wip","RIP"))))) -> hld | E68: Archimed | G68: Francia | J68: FONDO_PE | K68: Healthcare | L68: Igor Petricca | S68: no | AA68: Relazione | AC68: FCA | AD68: FCA | AE68: ASP | AI68: =+TODAY()-AM68 -> 335 | AJ68: =+(IF(AL68="Closed","-",IF(TODAY()-MAX(AN68:BA68)>0,TODAY()-MAX(AN68:BA68),0))) -> 274 | AK68: Buy Side | AL68: =+IF(BB68="",IF(AZ68="",IF(AY68="",IF(AX68="",COUNTA(AN68:AV68)/9,"On-hold"),"Aborted"),"Closed"),"RIP") -> On-hold | AM68: 45329 | AN68: 45329 | AO68: na | AP68: 45329 | AQ68: 45342 | AW68: 45359 | AX68: 45390 | BC68: |
B69: =IF(D69=$A$516,1,IF(D69=$A$517,2,IF(D69=$A$518,3,IF(D69=$A$519,4,IF(D69=$A$520,5,IF(D69=$A$521,6)))))) -> 4 | D69: =IF(AL69="Closed","cls",IF(AL69=1,"sgn",IF(AL69="On-hold","hld",IF(AL69="Aborted","abt",IF(AL69<1,"wip","RIP"))))) -> hld | E69: Quadrivio | G69: Italia | J69: FONDO_PE | K69: Healthcare, Industry, Made in Italy | L69: Dario Di Iorio | S69: no | T69: 2022 | U69: 2.8 | V69: 0.171 | W69: =+V69/U69 -> 0.061071429 | X69: 0.075 | Y69: -0.044 | AA69: Relazione | AC69: FCA | AD69: FCA | AE69: ASP | AI69: =+TODAY()-AM69 -> 335 | AJ69: =+(IF(AL69="Closed","-",IF(TODAY()-MAX(AN69:BA69)>0,TODAY()-MAX(AN69:BA69),0))) -> 274 | AK69: Fondo | AL69: =+IF(BB69="",IF(AZ69="",IF(AY69="",IF(AX69="",COUNTA(AN69:AV69)/9,"On-hold"),"Aborted"),"Closed"),"RIP") -> On-hold | AM69: 45329 | AN69: 45329 | AO69: na | AP69: 45329 | AQ69: 45344 | AW69: 45344 | AX69: 45390 | BC69: |
B70: =IF(D70=$A$516,1,IF(D70=$A$517,2,IF(D70=$A$518,3,IF(D70=$A$519,4,IF(D70=$A$520,5,IF(D70=$A$521,6)))))) -> 4 | D70: =IF(AL70="Closed","cls",IF(AL70=1,"sgn",IF(AL70="On-hold","hld",IF(AL70="Aborted","abt",IF(AL70<1,"wip","RIP"))))) -> hld | E70: Unigrains | G70: Francia | J70: FONDO_PE | K70: Agrifood | AA70: Relazione | AC70: FCA | AD70: FCA | AI70: =+TODAY()-AM70 -> 294 | AJ70: =+(IF(AL70="Closed","-",IF(TODAY()-MAX(AN70:BA70)>0,TODAY()-MAX(AN70:BA70),0))) -> 274 | AK70: Fondo | AL70: =+IF(BB70="",IF(AZ70="",IF(AY70="",IF(AX70="",COUNTA(AN70:AV70)/9,"On-hold"),"Aborted"),"Closed"),"RIP") -> On-hold | AM70: 45370 | AN70: 45370 | AO70: na | AP70: 45370 | AQ70: 45370 | AW70: 45370 | AX70: 45390 | BC70: |
B71: =IF(D71=$A$516,1,IF(D71=$A$517,2,IF(D71=$A$518,3,IF(D71=$A$519,4,IF(D71=$A$520,5,IF(D71=$A$521,6)))))) -> 4 | D71: =IF(AL71="Closed","cls",IF(AL71=1,"sgn",IF(AL71="On-hold","hld",IF(AL71="Aborted","abt",IF(AL71<1,"wip","RIP"))))) -> hld | E71: Orienta Partners | G71: FC | J71: FONDO_PE | K71: Generalista | L71: Augusto Balestra | S71: no | T71: 2022 | U71: 1.5 | V71: 0.519 | W71: =+V71/U71 -> 0.346 | X71: 0.619 | Y71: -0.592 | AA71: Relazione | AC71: FCA | AD71: FCA | AE71: ASP | AI71: =+TODAY()-AM71 -> 335 | AJ71: =+(IF(AL71="Closed","-",IF(TODAY()-MAX(AN71:BA71)>0,TODAY()-MAX(AN71:BA71),0))) -> 274 | AK71: Fondo | AL71: =+IF(BB71="",IF(AZ71="",IF(AY71="",IF(AX71="",COUNTA(AN71:AV71)/9,"On-hold"),"Aborted"),"Closed"),"RIP") -> On-hold | AM71: 45329 | AN71: 45329 | AO71: na | AP71: 45329 | AW71: 45352 | AX71: 45390 | BC71: |
B72: =IF(D72=$A$516,1,IF(D72=$A$517,2,IF(D72=$A$518,3,IF(D72=$A$519,4,IF(D72=$A$520,5,IF(D72=$A$521,6)))))) -> 4 | D72: =IF(AL72="Closed","cls",IF(AL72=1,"sgn",IF(AL72="On-hold","hld",IF(AL72="Aborted","abt",IF(AL72<1,"wip","RIP"))))) -> hld | E72: PIAM Farmaceutici | G72: GE | J72: Pharma | K72: Produzione medicinali | L72: Augusto Bruschettini | M72: Fam. Bruschettini | S72: no | T72: 2022 | U72: 61.219 | V72: 12.473 | W72: =+V72/U72 -> 0.20374394 | X72: 7.348 | Y72: 21.254 | AA72: Relazione | AC72: ASC | AD72: ASC | AG72: FCA conosce l'AD | AI72: =+TODAY()-AM72 -> 363 | AJ72: =+(IF(AL72="Closed","-",IF(TODAY()-MAX(AN72:BA72)>0,TODAY()-MAX(AN72:BA72),0))) -> 280 | AK72: Controparte | AL72: =+IF(BB72="",IF(AZ72="",IF(AY72="",IF(AX72="",COUNTA(AN72:AV72)/9,"On-hold"),"Aborted"),"Closed"),"RIP") -> On-hold | AM72: 45301 | AN72: 45301 | AO72: na | AP72: 45307 | AQ72: 45307 | AR72: 45370 | AW72: 45316 | AX72: 45384 | BA72: =+IF(AY72="","",COUNTA(AN72:AV72)/(COUNTA(AN72:AV72)+COUNTBLANK(AN72:AV72))) | BC72: |
B73: =IF(D73=$A$516,1,IF(D73=$A$517,2,IF(D73=$A$518,3,IF(D73=$A$519,4,IF(D73=$A$520,5,IF(D73=$A$521,6)))))) -> 4 | D73: =IF(AL73="Closed","cls",IF(AL73=1,"sgn",IF(AL73="On-hold","hld",IF(AL73="Aborted","abt",IF(AL73<1,"wip","RIP"))))) -> hld | E73: Oltre Capital | G73: MI | J73: FONDO_PE | K73: Generalista | S73: no | AA73: Relazione | AC73: LOM | AD73: LOM | AE73: LUS | AI73: =+TODAY()-AM73 -> 309 | AJ73: =+(IF(AL73="Closed","-",IF(TODAY()-MAX(AN73:BA73)>0,TODAY()-MAX(AN73:BA73),0))) -> 309 | AK73: Fondo | AL73: =+IF(BB73="",IF(AZ73="",IF(AY73="",IF(AX73="",COUNTA(AN73:AV73)/9,"On-hold"),"Aborted"),"Closed"),"RIP") -> On-hold | AM73: 45355 | AN73: 45355 | AO73: na | AP73: 45355 | AQ73: 45355 | AW73: 44640 | AX73: 44640 | BA73: =+IF(AY73="","",COUNTA(AN73:AV73)/(COUNTA(AN73:AV73)+COUNTBLANK(AN73:AV73))) | BC73: |
B74: =IF(D74=$A$516,1,IF(D74=$A$517,2,IF(D74=$A$518,3,IF(D74=$A$519,4,IF(D74=$A$520,5,IF(D74=$A$521,6)))))) -> 4 | D74: =IF(AL74="Closed","cls",IF(AL74=1,"sgn",IF(AL74="On-hold","hld",IF(AL74="Aborted","abt",IF(AL74<1,"wip","RIP"))))) -> hld | E74: ICI Caldaie SpA | G74: VR | H74: 00227490232 | J74: Industrial | K74: Produzione di caldaie a gas industriali o per condomini | L74: Emanuela Lucchini | M74: Emanuela Lucchini | S74: no | T74: 2023 | U74: 30.24 | V74: 2.037 | W74: =+V74/U74 -> 0.067361111 | X74: 0.505 | Y74: 4.663 | AA74: Cold Call | AC74: FCA | AD74: FCA | AE74: ASP | AG74: Contatti fiera Hydrogen | AI74: =+TODAY()-AM74 -> 477 | AJ74: =+(IF(AL74="Closed","-",IF(TODAY()-MAX(AN74:BA74)>0,TODAY()-MAX(AN74:BA74),0))) -> 287 | AK74: Buy Side | AL74: =+IF(BB74="",IF(AZ74="",IF(AY74="",IF(AX74="",COUNTA(AN74:AV74)/9,"On-hold"),"Aborted"),"Closed"),"RIP") -> On-hold | AM74: 45187 | AN74: 45187 | AO74: na | AP74: 45187 | AQ74: 45195 | AR74: 45267 | AW74: 45350 | AX74: 45377 | BC74: |
B75: =IF(D75=$A$516,1,IF(D75=$A$517,2,IF(D75=$A$518,3,IF(D75=$A$519,4,IF(D75=$A$520,5,IF(D75=$A$521,6)))))) -> 4 | D75: =IF(AL75="Closed","cls",IF(AL75=1,"sgn",IF(AL75="On-hold","hld",IF(AL75="Aborted","abt",IF(AL75<1,"wip","RIP"))))) -> hld | E75: Meta System | G75: RE | H75: 00271730350 | J75: Automotive | K75: Produzione disistemi di ricarica e altro per EV | M75: Deren Investment Holding S.à.r.l | N75: Sichuan Gangrong Investment | O75: Yang Qiu | P75: Angel Legarda | Q75: Hermann Steiner | S75: si | T75: 2022 | U75: 263.69 | V75: 0.5 | W75: =+V75/U75 -> 0.001896166 | X75: -12 | Y75: 2.14 | AA75: Segnalatore | AB75: Mattia Patti | AC75: LOM | AD75: LOM | AE75: PAD | AH75: 1 | AI75: =+TODAY()-AM75 -> 329 | AJ75: =+(IF(AL75="Closed","-",IF(TODAY()-MAX(AN75:BA75)>0,TODAY()-MAX(AN75:BA75),0))) -> 287 | AK75: Buy Side | AL75: =+IF(BB75="",IF(AZ75="",IF(AY75="",IF(AX75="",COUNTA(AN75:AV75)/9,"On-hold"),"Aborted"),"Closed"),"RIP") -> On-hold | AM75: 45335 | AN75: 45335 | AO75: na | AP75: 45335 | AQ75: 45335 | AX75: 45377 | BA75: =+IF(AY75="","",COUNTA(AN75:AV75)/(COUNTA(AN75:AV75)+COUNTBLANK(AN75:AV75))) | BC75: |
B76: =IF(D76=$A$516,1,IF(D76=$A$517,2,IF(D76=$A$518,3,IF(D76=$A$519,4,IF(D76=$A$520,5,IF(D76=$A$521,6)))))) -> 4 | D76: =IF(AL76="Closed","cls",IF(AL76=1,"sgn",IF(AL76="On-hold","hld",IF(AL76="Aborted","abt",IF(AL76<1,"wip","RIP"))))) -> hld | E76: Indeco Ind. SpA | G76: BA | H76: 05949910722 | J76: Industrial | K76: Produzione di componenti per macchine demolizione e movimento terra | L76: Diego Rufini | M76: Vitulano | N76: Vitulano Susanna | S76: si | T76: 2022 | U76: 42.745 | V76: 9 | W76: =+V76/U76 -> 0.21055094 | X76: 15 | Y76: -5.563 | AA76: Segnalatore | AB76: Diego Rufini | AC76: FCA | AD76: FCA | AE76: ASP | AI76: =+TODAY()-AM76 -> 302 | AJ76: =+(IF(AL76="Closed","-",IF(TODAY()-MAX(AN76:BA76)>0,TODAY()-MAX(AN76:BA76),0))) -> 287 | AK76: Sell Side | AL76: =+IF(BB76="",IF(AZ76="",IF(AY76="",IF(AX76="",COUNTA(AN76:AV76)/9,"On-hold"),"Aborted"),"Closed"),"RIP") -> On-hold | AM76: 45362 | AN76: 45362 | AO76: na | AP76: 45362 | AW76: 45362 | AX76: 45377 | BC76: |
B77: =IF(D77=$A$516,1,IF(D77=$A$517,2,IF(D77=$A$518,3,IF(D77=$A$519,4,IF(D77=$A$520,5,IF(D77=$A$521,6)))))) -> 4 | D77: =IF(AL77="Closed","cls",IF(AL77=1,"sgn",IF(AL77="On-hold","hld",IF(AL77="Aborted","abt",IF(AL77<1,"wip","RIP"))))) -> hld | E77: Metrika | G77: MI | H77: 10693910969 | J77: FONDO_PE | K77: Generalista | L77: Giuseppini | AA77: Relazione | AC77: ASC | AD77: ASC | AE77: RIM | AI77: =+TODAY()-AM77 -> 292 | AJ77: =+(IF(AL77="Closed","-",IF(TODAY()-MAX(AN77:BA77)>0,TODAY()-MAX(AN77:BA77),0))) -> 292 | AK77: Fondo | AL77: =+IF(BB77="",IF(AZ77="",IF(AY77="",IF(AX77="",COUNTA(AN77:AV77)/9,"On-hold"),"Aborted"),"Closed"),"RIP") -> On-hold | AM77: 45372 | AN77: 45372 | AO77: 45372 | AP77: 45372 | AQ77: 45372 | AR77: 45372 | AW77: 45372 | AX77: 45372 | BC77: |
B78: =IF(D78=$A$516,1,IF(D78=$A$517,2,IF(D78=$A$518,3,IF(D78=$A$519,4,IF(D78=$A$520,5,IF(D78=$A$521,6)))))) -> 4 | D78: =IF(AL78="Closed","cls",IF(AL78=1,"sgn",IF(AL78="On-hold","hld",IF(AL78="Aborted","abt",IF(AL78<1,"wip","RIP"))))) -> hld | E78: Wise | G78: MI | J78: FONDO_PE | K78: Generalista | AA78: Relazione | AC78: ASC | AD78: ASC | AE78: RIM | AF78: SEB | AI78: =+TODAY()-AM78 -> 300 | AJ78: =+(IF(AL78="Closed","-",IF(TODAY()-MAX(AN78:BA78)>0,TODAY()-MAX(AN78:BA78),0))) -> 300 | AK78: Fondo | AL78: =+IF(BB78="",IF(AZ78="",IF(AY78="",IF(AX78="",COUNTA(AN78:AV78)/9,"On-hold"),"Aborted"),"Closed"),"RIP") -> On-hold | AM78: 45364 | AN78: 45364 | AO78: 45364 | AP78: 45364 | AQ78: 45364 | AW78: 44640 | AX78: 44640 | BA78: =+IF(AY78="","",COUNTA(AN78:AV78)/(COUNTA(AN78:AV78)+COUNTBLANK(AN78:AV78))) | BC78: |
B79: =IF(D79=$A$516,1,IF(D79=$A$517,2,IF(D79=$A$518,3,IF(D79=$A$519,4,IF(D79=$A$520,5,IF(D79=$A$521,6)))))) -> 4 | D79: =IF(AL79="Closed","cls",IF(AL79=1,"sgn",IF(AL79="On-hold","hld",IF(AL79="Aborted","abt",IF(AL79<1,"wip","RIP"))))) -> hld | E79: KPS | G79: US | J79: FONDO_PE | K79: Generalista | L79: Lilly Green | S79: no | AA79: Relazione | AC79: ASC | AD79: ASC | AE79: RIM | AG79: Add-on per Princess + Special Flanges | AI79: =+TODAY()-AM79 -> 341 | AJ79: =+(IF(AL79="Closed","-",IF(TODAY()-MAX(AN79:BA79)>0,TODAY()-MAX(AN79:BA79),0))) -> 229 | AK79: Fondo | AL79: =+IF(BB79="",IF(AZ79="",IF(AY79="",IF(AX79="",COUNTA(AN79:AV79)/9,"On-hold"),"Aborted"),"Closed"),"RIP") -> On-hold | AM79: 45323 | AN79: 45323 | AO79: na | AP79: 45323 | AQ79: 45335 | AR79: 45355 | AW79: 45435 | AX79: 45363 | BC79: |
B80: =IF(D80=$A$516,1,IF(D80=$A$517,2,IF(D80=$A$518,3,IF(D80=$A$519,4,IF(D80=$A$520,5,IF(D80=$A$521,6)))))) -> 4 | D80: =IF(AL80="Closed","cls",IF(AL80=1,"sgn",IF(AL80="On-hold","hld",IF(AL80="Aborted","abt",IF(AL80<1,"wip","RIP"))))) -> hld | E80: C&P Group | G80: TO | H80: 06955340010 | I80: 812202 | J80: Other services | K80: Attività di pulizia specializzata per il settore alimentare e manutenzione impianti industriali | L80: Ettore Franco | M80: Ettore Franco | O80: Ettore Franco | S80: no | T80: 2022 | U80: 16 | V80: 0.6 | W80: =+V80/U80 -> 0.0375 | X80: 0.217 | Y80: 0.609 | AA80: Relazione | AB80: Fabrizio Torchio | AC80: FCA | AD80: FCA | AE80: GSE | AF80: MMO | AI80: =+TODAY()-AM80 -> 350 | AJ80: =+(IF(AL80="Closed","-",IF(TODAY()-MAX(AN80:BA80)>0,TODAY()-MAX(AN80:BA80),0))) -> 294 | AK80: Fundraising | AL80: =+IF(BB80="",IF(AZ80="",IF(AY80="",IF(AX80="",COUNTA(AN80:AV80)/9,"On-hold"),"Aborted"),"Closed"),"RIP") -> On-hold | AM80: 45314 | AN80: 45314 | AO80: na | AP80: 45314 | AQ80: 45315 | AW80: 45316 | AX80: 45370 | BA80: =+IF(AY80="","",COUNTA(AN80:AV80)/(COUNTA(AN80:AV80)+COUNTBLANK(AN80:AV80))) | BC80: |
B81: =IF(D81=$A$516,1,IF(D81=$A$517,2,IF(D81=$A$518,3,IF(D81=$A$519,4,IF(D81=$A$520,5,IF(D81=$A$521,6)))))) -> 4 | D81: =IF(AL81="Closed","cls",IF(AL81=1,"sgn",IF(AL81="On-hold","hld",IF(AL81="Aborted","abt",IF(AL81<1,"wip","RIP"))))) -> hld | E81: ABC | G81: RM | H81: 00877161000 | I81: 463100 | J81: Food: Agrifood | K81: Commercio all'ingrosso di frutta e ortaggi | L81: A. Pagni | S81: no | T81: 2022 | U81: 61 | V81: -0.128 | W81: =+V81/U81 -> -0.0020983607 | X81: 0.073 | Y81: 0.367 | AA81: Relazione | AC81: LOM | AD81: LOM | AE81: RIM | AF81: GID | AI81: =+TODAY()-AM81 -> 554 | AJ81: =+(IF(AL81="Closed","-",IF(TODAY()-MAX(AN81:BA81)>0,TODAY()-MAX(AN81:BA81),0))) -> 301 | AK81: Buy Side | AL81: =+IF(BB81="",IF(AZ81="",IF(AY81="",IF(AX81="",COUNTA(AN81:AV81)/9,"On-hold"),"Aborted"),"Closed"),"RIP") -> On-hold | AM81: 45110 | AN81: =+AM81 -> 45110 | AO81: na | AP81: na | AQ81: =+AN81 -> 45110 | AR81: 45114 | AW81: 45342 | AX81: 45363 | BA81: =+IF(AY81="","",COUNTA(AN81:AV81)/(COUNTA(AN81:AV81)+COUNTBLANK(AN81:AV81))) | BC81: |
B82: =IF(D82=$A$516,1,IF(D82=$A$517,2,IF(D82=$A$518,3,IF(D82=$A$519,4,IF(D82=$A$520,5,IF(D82=$A$521,6)))))) -> 4 | D82: =IF(AL82="Closed","cls",IF(AL82=1,"sgn",IF(AL82="On-hold","hld",IF(AL82="Aborted","abt",IF(AL82<1,"wip","RIP"))))) -> hld | E82: Casa di Cura Villa Montallegro | G82: GE | H82: 00967100108 | J82: Medical | K82: Casa di cura | S82: no | T82: 2022 | U82: 19 | V82: 2.2 | W82: =+V82/U82 -> 0.11578947 | X82: 0.5 | Y82: 1.2 | AA82: Segnalatore | AB82: Strufaldi Sarah | AC82: ASC | AD82: ASC | AI82: =+TODAY()-AM82 -> 348 | AJ82: =+(IF(AL82="Closed","-",IF(TODAY()-MAX(AN82:BA82)>0,TODAY()-MAX(AN82:BA82),0))) -> 301 | AK82: Buy Side | AL82: =+IF(BB82="",IF(AZ82="",IF(AY82="",IF(AX82="",COUNTA(AN82:AV82)/9,"On-hold"),"Aborted"),"Closed"),"RIP") -> On-hold | AM82: 45316 | AN82: =+AM82 -> 45316 | AO82: na | AP82: 45344 | AQ82: 45344 | AX82: 45363 | BA82: =+IF(AY82="","",COUNTA(AN82:AV82)/(COUNTA(AN82:AV82)+COUNTBLANK(AN82:AV82))) | BC82: |
B83: =IF(D83=$A$516,1,IF(D83=$A$517,2,IF(D83=$A$518,3,IF(D83=$A$519,4,IF(D83=$A$520,5,IF(D83=$A$521,6)))))) -> 4 | D83: =IF(AL83="Closed","cls",IF(AL83=1,"sgn",IF(AL83="On-hold","hld",IF(AL83="Aborted","abt",IF(AL83<1,"wip","RIP"))))) -> hld | E83: Tages Capital SGR | G83: MI | H83: 07118810964 | J83: FONDO_Debt | K83: Generalista - Ticket 10M€ | L83: Eleonora Astori | M83: Tages SpA | N83: Quarto Srl | O83: Elisabetta Gualandri | Q83: Giuseppe Alessandro Galeano | S83: no | T83: 2022 | U83: 13.58 | V83: 0 | W83: =+V83/U83 -> 0 | X83: 1.72 | Y83: 0 | AA83: Relazione | AC83: ASC | AD83: ASC | AI83: =+TODAY()-AM83 -> 320 | AJ83: =+(IF(AL83="Closed","-",IF(TODAY()-MAX(AN83:BA83)>0,TODAY()-MAX(AN83:BA83),0))) -> 301 | AK83: Buy Side | AL83: =+IF(BB83="",IF(AZ83="",IF(AY83="",IF(AX83="",COUNTA(AN83:AV83)/9,"On-hold"),"Aborted"),"Closed"),"RIP") -> On-hold | AM83: 45344 | AN83: 45344 | AO83: na | AP83: 45344 | AQ83: 45355 | AX83: 45363 | BC83: |
B84: =IF(D84=$A$516,1,IF(D84=$A$517,2,IF(D84=$A$518,3,IF(D84=$A$519,4,IF(D84=$A$520,5,IF(D84=$A$521,6)))))) -> 4 | D84: =IF(AL84="Closed","cls",IF(AL84=1,"sgn",IF(AL84="On-hold","hld",IF(AL84="Aborted","abt",IF(AL84<1,"wip","RIP"))))) -> hld | E84: Guglielmo S.p.A. | G84: CZ | H84: 00050720796 | J84: Food | K84: Produzione e commercializzazione di caffè | M84: Silvana Papaleo | N84: Gabriella Papaleo | O84: Roberto Volpi | Q84: Mario Antonini | S84: no | T84: 2022 | U84: 12.3 | V84: 1.4 | W84: =+V84/U84 -> 0.11382114 | X84: 0.272 | Y84: 1.7 | AA84: Segnalatore | AB84: Caffo Sebastiano | AC84: ASC | AD84: ASC | AI84: =+TODAY()-AM84 -> 340 | AJ84: =+(IF(AL84="Closed","-",IF(TODAY()-MAX(AN84:BA84)>0,TODAY()-MAX(AN84:BA84),0))) -> 301 | AK84: Buy Side | AL84: =+IF(BB84="",IF(AZ84="",IF(AY84="",IF(AX84="",COUNTA(AN84:AV84)/9,"On-hold"),"Aborted"),"Closed"),"RIP") -> On-hold | AM84: 45324 | AN84: 45324 | AO84: na | AP84: 45352 | AX84: 45363 | BC84: |
B85: =IF(D85=$A$516,1,IF(D85=$A$517,2,IF(D85=$A$518,3,IF(D85=$A$519,4,IF(D85=$A$520,5,IF(D85=$A$521,6)))))) -> 4 | D85: =IF(AL85="Closed","cls",IF(AL85=1,"sgn",IF(AL85="On-hold","hld",IF(AL85="Aborted","abt",IF(AL85<1,"wip","RIP"))))) -> hld | E85: DBAG Italia | G85: MI | H85: 118 546 609 63 | J85: FONDO_PE | K85: Generalista | L85: Giovanni Revoltella | S85: no | T85: 2023 | U85: 2.618 | V85: 0.237 | W85: =+V85/U85 -> 0.09052712 | X85: 0.117 | Y85: -0.576 | AA85: Relazione | AC85: ASC | AD85: ASC | AE85: RIM | AF85: PAD | AH85: 1 | AI85: =+TODAY()-AM85 -> 306 | AJ85: =+(IF(AL85="Closed","-",IF(TODAY()-MAX(AN85:BA85)>0,TODAY()-MAX(AN85:BA85),0))) -> 302 | AK85: Fondo | AL85: =+IF(BB85="",IF(AZ85="",IF(AY85="",IF(AX85="",COUNTA(AN85:AV85)/9,"On-hold"),"Aborted"),"Closed"),"RIP") -> On-hold | AM85: 45358 | AN85: 45358 | AO85: na | AP85: 45358 | AQ85: 45358 | AX85: 45362 | BA85: =+IF(AY85="","",COUNTA(AN85:AV85)/(COUNTA(AN85:AV85)+COUNTBLANK(AN85:AV85))) | BC85: |
B86: =IF(D86=$A$516,1,IF(D86=$A$517,2,IF(D86=$A$518,3,IF(D86=$A$519,4,IF(D86=$A$520,5,IF(D86=$A$521,6)))))) -> 4 | D86: =IF(AL86="Closed","cls",IF(AL86=1,"sgn",IF(AL86="On-hold","hld",IF(AL86="Aborted","abt",IF(AL86<1,"wip","RIP"))))) -> hld | E86: SBS | F86: Lake | G86: NO | H86: 01888310032 | I86: 465201 | J86: Industrial | K86: Dispositivi elettronici e accessori smartphone | L86: Mattia Marchesa | M86: Sbs Holding Srl | O86: Alessandro Storti | Q86: Massimo Gaboardi | S86: no | T86: 2023 | U86: 83 | V86: 15 | W86: =+V86/U86 -> 0.18072289 | X86: 9 | Y86: 13.264 | AA86: Relazione | AC86: RIM | AD86: ASC | AE86: RIM | AF86: GID | AI86: =+TODAY()-AM86 -> 858 | AJ86: =+(IF(AL86="Closed","-",IF(TODAY()-MAX(AN86:BA86)>0,TODAY()-MAX(AN86:BA86),0))) -> 313 | AK86: Buy Side | AL86: =+IF(BB86="",IF(AZ86="",IF(AY86="",IF(AX86="",COUNTA(AN86:AV86)/9,"On-hold"),"Aborted"),"Closed"),"RIP") -> On-hold | AM86: 44806 | AN86: 44806 | AO86: na | AP86: 44806 | AQ86: 44858 | AR86: 28/11/22 | AS86: 44960 | AW86: 45330 | AX86: 45351 | BA86: =+IF(AY86="","",COUNTA(AN86:AV86)/(COUNTA(AN86:AV86)+COUNTBLANK(AN86:AV86))) | BC86: |
B87: =IF(D87=$A$516,1,IF(D87=$A$517,2,IF(D87=$A$518,3,IF(D87=$A$519,4,IF(D87=$A$520,5,IF(D87=$A$521,6)))))) -> 4 | D87: =IF(AL87="Closed","cls",IF(AL87=1,"sgn",IF(AL87="On-hold","hld",IF(AL87="Aborted","abt",IF(AL87<1,"wip","RIP"))))) -> hld | E87: Italwatt Srl (Iveco Defence Vehicles) | G87: TO | H87: 08890680013 | I87: 293100 | J87: Industrial - Automotive | K87: Progettazione e produzione di apparecchiature elettroniche per veicoli militari | L87: Alessandro Morando | M87: Gruppo Iveco | O87: John Elkann | P87: Giandomenico Demartini | S87: no | T87: 2023 | U87: 10.4 | V87: 3.5 | W87: =+V87/U87 -> 0.33653846 | X87: 2.4 | Y87: -5.5 | AA87: Cold call | AC87: MMO | AD87: MMO | AE87: GSE | AI87: =+TODAY()-AM87 -> 399 | AJ87: =+(IF(AL87="Closed","-",IF(TODAY()-MAX(AN87:BA87)>0,TODAY()-MAX(AN87:BA87),0))) -> 302 | AK87: Agevolato | AL87: =+IF(BB87="",IF(AZ87="",IF(AY87="",IF(AX87="",COUNTA(AN87:AV87)/9,"On-hold"),"Aborted"),"Closed"),"RIP") -> On-hold | AM87: 45265 | AN87: 45265 | AO87: na | AP87: 45265 | AQ87: 45271 | AR87: 45314 | AX87: 45362 | BA87: =+IF(AY87="","",COUNTA(AN87:AV87)/(COUNTA(AN87:AV87)+COUNTBLANK(AN87:AV87))) | BC87: |
B88: =IF(D88=$A$516,1,IF(D88=$A$517,2,IF(D88=$A$518,3,IF(D88=$A$519,4,IF(D88=$A$520,5,IF(D88=$A$521,6)))))) -> 4 | D88: =IF(AL88="Closed","cls",IF(AL88=1,"sgn",IF(AL88="On-hold","hld",IF(AL88="Aborted","abt",IF(AL88<1,"wip","RIP"))))) -> hld | E88: St. Stephen's School (buy side) | G88: RM | J88: Education | K88: Scuola internazionale 14-18 | L88: Jill Muti | S88: no | AA88: Relazione | AC88: LOM | AD88: LOM | AE88: LUS | AI88: =+TODAY()-AM88 -> 337 | AJ88: =+(IF(AL88="Closed","-",IF(TODAY()-MAX(AN88:BA88)>0,TODAY()-MAX(AN88:BA88),0))) -> 308 | AK88: Buy Side | AL88: =+IF(BB88="",IF(AZ88="",IF(AY88="",IF(AX88="",COUNTA(AN88:AV88)/9,"On-hold"),"Aborted"),"Closed"),"RIP") -> On-hold | AM88: 45327 | AN88: 45327 | AO88: na | AP88: 45327 | AQ88: 45352 | AW88: 45352 | AX88: 45356 | BA88: =+IF(AY88="","",COUNTA(AN88:AV88)/(COUNTA(AN88:AV88)+COUNTBLANK(AN88:AV88))) | BC88: |
B89: =IF(D89=$A$516,1,IF(D89=$A$517,2,IF(D89=$A$518,3,IF(D89=$A$519,4,IF(D89=$A$520,5,IF(D89=$A$521,6)))))) -> 4 | D89: =IF(AL89="Closed","cls",IF(AL89=1,"sgn",IF(AL89="On-hold","hld",IF(AL89="Aborted","abt",IF(AL89<1,"wip","RIP"))))) -> hld | E89: Cargo Compass | G89: Sud Africa | J89: Logistic | K89: Servizi di logistica internazionale | S89: no | AA89: GMAP | AC89: ASC | AD89: ASC | AE89: GID | AI89: =+TODAY()-AM89 -> 333 | AJ89: =+(IF(AL89="Closed","-",IF(TODAY()-MAX(AN89:BA89)>0,TODAY()-MAX(AN89:BA89),0))) -> 314 | AK89: Controparte | AL89: =+IF(BB89="",IF(AZ89="",IF(AY89="",IF(AX89="",COUNTA(AN89:AV89)/9,"On-hold"),"Aborted"),"Closed"),"RIP") -> On-hold | AM89: 45331 | AN89: =+AM89 -> 45331 | AO89: na | AP89: 45331 | AW89: 45331 | AX89: 45350 | BC89: |
B90: =IF(D90=$A$516,1,IF(D90=$A$517,2,IF(D90=$A$518,3,IF(D90=$A$519,4,IF(D90=$A$520,5,IF(D90=$A$521,6)))))) -> 4 | D90: =IF(AL90="Closed","cls",IF(AL90=1,"sgn",IF(AL90="On-hold","hld",IF(AL90="Aborted","abt",IF(AL90<1,"wip","RIP"))))) -> hld | E90: Ldue Capital | G90: MI | H90: 13253780962 | J90: Search Fund | K90: Generalista | L90: Andrea Taurelli Salimbeni | S90: no | AA90: Relazione | AC90: ASC | AD90: ASC | AE90: PAD | AF90: GID | AH90: 1 | AI90: =+TODAY()-AM90 -> 327 | AJ90: =+(IF(AL90="Closed","-",IF(TODAY()-MAX(AN90:BA90)>0,TODAY()-MAX(AN90:BA90),0))) -> 225 | AK90: Fondo | AL90: =+IF(BB90="",IF(AZ90="",IF(AY90="",IF(AX90="",COUNTA(AN90:AV90)/9,"On-hold"),"Aborted"),"Closed"),"RIP") -> On-hold | AM90: 45337 | AN90: 45337 | AO90: na | AP90: 45337 | AQ90: 45351 | AR90: 45439 | AW90: 45436 | AX90: 45436 | BC90: |
B91: =IF(D91=$A$516,1,IF(D91=$A$517,2,IF(D91=$A$518,3,IF(D91=$A$519,4,IF(D91=$A$520,5,IF(D91=$A$521,6)))))) -> 4 | D91: =IF(AL91="Closed","cls",IF(AL91=1,"sgn",IF(AL91="On-hold","hld",IF(AL91="Aborted","abt",IF(AL91<1,"wip","RIP"))))) -> hld | E91: Bioindustria LIM | G91: AL | H91: 01679130060 | J91: Pharma | K91: Produzione di farmaci e API | M91: Biofin Farma Srl | N91: Fabrizio Caraccia | O91: Fabrizio Caraccia | Q91: Paolo Fasce | S91: no | T91: 2023 | U91: 26 | V91: 5 | W91: =+V91/U91 -> 0.19230769 | X91: 2.4 | Y91: -10 | AA91: Segnalatore | AB91: Strufaldi Sarah | AC91: ASC | AD91: ASC | AI91: =+TODAY()-AM91 -> 341 | AJ91: =+(IF(AL91="Closed","-",IF(TODAY()-MAX(AN91:BA91)>0,TODAY()-MAX(AN91:BA91),0))) -> 321 | AK91: Buy Side | AL91: =+IF(BB91="",IF(AZ91="",IF(AY91="",IF(AX91="",COUNTA(AN91:AV91)/9,"On-hold"),"Aborted"),"Closed"),"RIP") -> On-hold | AM91: 45323 | AN91: 45323 | AO91: na | AX91: 45343 | BC91: |
B92: =IF(D92=$A$516,1,IF(D92=$A$517,2,IF(D92=$A$518,3,IF(D92=$A$519,4,IF(D92=$A$520,5,IF(D92=$A$521,6)))))) -> 4 | D92: =IF(AL92="Closed","cls",IF(AL92=1,"sgn",IF(AL92="On-hold","hld",IF(AL92="Aborted","abt",IF(AL92<1,"wip","RIP"))))) -> hld | E92: Alba International School (sell side) | G92: CN | H92: 03700250040 | I92: 852000 | J92: Education | K92: Scuola internazionale 6-14 | L92: Silvana Carbone | S92: no | T92: 2023 | U92: 0.74 | V92: 0.2 | W92: =+V92/U92 -> 0.27027027 | X92: 0.92 | Y92: 0 | AA92: Cold Call | AC92: LOM | AD92: LOM | AE92: LUS | AF92: GID | AI92: =+TODAY()-AM92 -> 725 | AJ92: =+(IF(AL92="Closed","-",IF(TODAY()-MAX(AN92:BA92)>0,TODAY()-MAX(AN92:BA92),0))) -> 322 | AK92: Sell Side | AL92: =+IF(BB92="",IF(AZ92="",IF(AY92="",IF(AX92="",COUNTA(AN92:AV92)/9,"On-hold"),"Aborted"),"Closed"),"RIP") -> On-hold | AM92: 44939 | AN92: =+AM92 -> 44939 | AO92: na | AP92: 44946 | AQ92: 44946 | AR92: 44970 | AS92: 45021 | AT92: 45320 | AW92: 45320 | AX92: 45342 | BC92: |
B93: =IF(D93=$A$516,1,IF(D93=$A$517,2,IF(D93=$A$518,3,IF(D93=$A$519,4,IF(D93=$A$520,5,IF(D93=$A$521,6)))))) -> 4 | D93: =IF(AL93="Closed","cls",IF(AL93=1,"sgn",IF(AL93="On-hold","hld",IF(AL93="Aborted","abt",IF(AL93<1,"wip","RIP"))))) -> hld | E93: Side Asset Management | G93: RM | H93: 15515591004 | J93: Education RE | K93: Piattaforma di investimento nel settore RE Education | L93: Alessandro Masi | AA93: Relazione | AC93: LUS | AD93: LOM | AE93: LUS | AI93: =+TODAY()-AM93 -> 350 | AJ93: =+(IF(AL93="Closed","-",IF(TODAY()-MAX(AN93:BA93)>0,TODAY()-MAX(AN93:BA93),0))) -> 322 | AK93: Fundraising | AL93: =+IF(BB93="",IF(AZ93="",IF(AY93="",IF(AX93="",COUNTA(AN93:AV93)/9,"On-hold"),"Aborted"),"Closed"),"RIP") -> On-hold | AM93: 45314 | AN93: 45315 | AO93: na | AP93: 45315 | AQ93: 45316 | AR93: 45336 | AW93: 45338 | AX93: 45342 | BA93: =+IF(AY93="","",COUNTA(AN93:AV93)/(COUNTA(AN93:AV93)+COUNTBLANK(AN93:AV93))) | BC93: |
B94: =IF(D94=$A$516,1,IF(D94=$A$517,2,IF(D94=$A$518,3,IF(D94=$A$519,4,IF(D94=$A$520,5,IF(D94=$A$521,6)))))) -> 4 | D94: =IF(AL94="Closed","cls",IF(AL94=1,"sgn",IF(AL94="On-hold","hld",IF(AL94="Aborted","abt",IF(AL94<1,"wip","RIP"))))) -> hld | E94: H.I.G. | G94: MI | J94: FONDO_PE | K94: Generalista | L94: Giovanni Guglielmi | AA94: Relazione | AC94: LOM | AD94: LOM | AE94: PAD | AH94: 1 | AI94: =+TODAY()-AM94 -> 350 | AJ94: =+(IF(AL94="Closed","-",IF(TODAY()-MAX(AN94:BA94)>0,TODAY()-MAX(AN94:BA94),0))) -> 321 | AK94: Fondo | AL94: =+IF(BB94="",IF(AZ94="",IF(AY94="",IF(AX94="",COUNTA(AN94:AV94)/9,"On-hold"),"Aborted"),"Closed"),"RIP") -> On-hold | AM94: 45314 | AN94: 45314 | AO94: na | AP94: 45316 | AQ94: 45316 | AW94: 45327 | AX94: 45343 | BA94: =+IF(AY94="","",COUNTA(AN94:AV94)/(COUNTA(AN94:AV94)+COUNTBLANK(AN94:AV94))) | BC94: |
B95: =IF(D95=$A$516,1,IF(D95=$A$517,2,IF(D95=$A$518,3,IF(D95=$A$519,4,IF(D95=$A$520,5,IF(D95=$A$521,6)))))) -> 4 | D95: =IF(AL95="Closed","cls",IF(AL95=1,"sgn",IF(AL95="On-hold","hld",IF(AL95="Aborted","abt",IF(AL95<1,"wip","RIP"))))) -> hld | E95: JAB Holding | G95: Olanda | J95: Holding di investimento | K95: Holding di investimento proprietaria di numerosi brand nel food&beverage e fashion | L95: Joachim Creus (CEO) | S95: no | AA95: Cold Call | AC95: ASC | AD95: ASC | AE95: GID | AI95: =+TODAY()-AM95 -> 341 | AJ95: =+(IF(AL95="Closed","-",IF(TODAY()-MAX(AN95:BA95)>0,TODAY()-MAX(AN95:BA95),0))) -> 329 | AK95: Controparte | AL95: =+IF(BB95="",IF(AZ95="",IF(AY95="",IF(AX95="",COUNTA(AN95:AV95)/9,"On-hold"),"Aborted"),"Closed"),"RIP") -> On-hold | AM95: 45323 | AN95: 45330 | AO95: na | AP95: 45335 | AW95: 45335 | AX95: 45335 | BC95: |
B96: =IF(D96=$A$516,1,IF(D96=$A$517,2,IF(D96=$A$518,3,IF(D96=$A$519,4,IF(D96=$A$520,5,IF(D96=$A$521,6)))))) -> 4 | D96: =IF(AL96="Closed","cls",IF(AL96=1,"sgn",IF(AL96="On-hold","hld",IF(AL96="Aborted","abt",IF(AL96<1,"wip","RIP"))))) -> hld | E96: White Bridge Investments | G96: MI | H96: 08304650966 | J96: FONDO_PE | K96: Investimenti in aziende media dimensione | L96: Riccardo Catalano | M96: Dolomiti 3 Sàrl | N96: Synergetic Srl | O96: Marco Pinciroli | P96: Stefano Devescovi | Q96: Ruggero Roberto Capone | S96: no | AA96: Private Equity | AC96: LOM | AD96: LOM | AE96: LUS | AI96: =+TODAY()-AM96 -> 370 | AJ96: =+(IF(AL96="Closed","-",IF(TODAY()-MAX(AN96:BA96)>0,TODAY()-MAX(AN96:BA96),0))) -> 326 | AK96: Buy Side | AL96: =+IF(BB96="",IF(AZ96="",IF(AY96="",IF(AX96="",COUNTA(AN96:AV96)/9,"On-hold"),"Aborted"),"Closed"),"RIP") -> On-hold | AM96: 45294 | AN96: 45294 | AO96: na | AP96: 45294 | AQ96: 45321 | AW96: 45321 | AX96: 45338 | BC96: |
B97: =IF(D97=$A$516,1,IF(D97=$A$517,2,IF(D97=$A$518,3,IF(D97=$A$519,4,IF(D97=$A$520,5,IF(D97=$A$521,6)))))) -> 4 | D97: =IF(AL97="Closed","cls",IF(AL97=1,"sgn",IF(AL97="On-hold","hld",IF(AL97="Aborted","abt",IF(AL97<1,"wip","RIP"))))) -> hld | E97: Metallurgica Pessina | G97: MI | H97: 00634080121 | I97: 243200 | J97: Industrial | K97: Produzione nastri in acciaio | M97: Giovannantonio Greppi | S97: no | T97: 2022 | U97: 26.566755 | V97: 5.084395 | W97: =+V97/U97 -> 0.19138186 | X97: 2.507227 | Y97: 1.764842 | AA97: Segnalatore | AB97: Marco Dal Molin | AC97: ASC | AD97: ASC | AE97: RIM | AI97: =+TODAY()-AM97 -> 392 | AJ97: =+(IF(AL97="Closed","-",IF(TODAY()-MAX(AN97:BA97)>0,TODAY()-MAX(AN97:BA97),0))) -> 326 | AK97: Sell Side | AL97: =+IF(BB97="",IF(AZ97="",IF(AY97="",IF(AX97="",COUNTA(AN97:AV97)/9,"On-hold"),"Aborted"),"Closed"),"RIP") -> On-hold | AM97: 45272 | AN97: =+AM97 -> 45272 | AO97: na | AP97: na | AQ97: 45316 | AW97: 45323 | AX97: 45338 | BC97: |
B98: =IF(D98=$A$516,1,IF(D98=$A$517,2,IF(D98=$A$518,3,IF(D98=$A$519,4,IF(D98=$A$520,5,IF(D98=$A$521,6)))))) -> 4 | D98: =IF(AL98="Closed","cls",IF(AL98=1,"sgn",IF(AL98="On-hold","hld",IF(AL98="Aborted","abt",IF(AL98<1,"wip","RIP"))))) -> hld | E98: Cellularline | G98: RE | H98: 09800730963 | I98: 465201 | J98: Industrial | K98: Dispositivi elettronici e accessori smartphone | S98: si | T98: 2022 | U98: 137.6 | V98: 11.97 | W98: =+V98/U98 -> 0.086991279 | X98: -75.2 | Y98: 40.45 | AA98: Segnalatore | AB98: Marco Fumagalli | AC98: ASC | AD98: ASC | AE98: RIM | AI98: =+TODAY()-AM98 -> 355 | AJ98: =+(IF(AL98="Closed","-",IF(TODAY()-MAX(AN98:BA98)>0,TODAY()-MAX(AN98:BA98),0))) -> 326 | AK98: Buy Side | AL98: =+IF(BB98="",IF(AZ98="",IF(AY98="",IF(AX98="",COUNTA(AN98:AV98)/9,"On-hold"),"Aborted"),"Closed"),"RIP") -> On-hold | AM98: 45309 | AN98: 45314 | AO98: na | AP98: 45314 | AQ98: 45315 | AW98: 45315 | AX98: 45338 | BA98: =+IF(AY98="","",COUNTA(AN98:AV98)/(COUNTA(AN98:AV98)+COUNTBLANK(AN98:AV98))) | BC98: |
B99: =IF(D99=$A$516,1,IF(D99=$A$517,2,IF(D99=$A$518,3,IF(D99=$A$519,4,IF(D99=$A$520,5,IF(D99=$A$521,6)))))) -> 4 | D99: =IF(AL99="Closed","cls",IF(AL99=1,"sgn",IF(AL99="On-hold","hld",IF(AL99="Aborted","abt",IF(AL99<1,"wip","RIP"))))) -> hld | E99: Ethica Investments | G99: MI | H99: 06706910962 | J99: FONDO_PE | K99: Generalista | L99: Nicola De Biase | S99: no | T99: 2022 | U99: 125 | V99: 21 | W99: =+V99/U99 -> 0.168 | X99: 0.333 | Y99: 44.3 | AA99: Relazione | AC99: ASC | AD99: ASC | AG99: Per LEVICO | AI99: =+TODAY()-AM99 -> 348 | AJ99: =+(IF(AL99="Closed","-",IF(TODAY()-MAX(AN99:BA99)>0,TODAY()-MAX(AN99:BA99),0))) -> 326 | AK99: Fondo | AL99: =+IF(BB99="",IF(AZ99="",IF(AY99="",IF(AX99="",COUNTA(AN99:AV99)/9,"On-hold"),"Aborted"),"Closed"),"RIP") -> On-hold | AM99: 45316 | AN99: =+AM99 -> 45316 | AO99: na | AP99: 45323 | AQ99: 45324 | AW99: 45329 | AX99: 45338 | BC99: |
B100: =IF(D100=$A$516,1,IF(D100=$A$517,2,IF(D100=$A$518,3,IF(D100=$A$519,4,IF(D100=$A$520,5,IF(D100=$A$521,6)))))) -> 4 | D100: =IF(AL100="Closed","cls",IF(AL100=1,"sgn",IF(AL100="On-hold","hld",IF(AL100="Aborted","abt",IF(AL100<1,"wip","RIP"))))) -> hld | E100: PM Partners | G100: MI | J100: FONDO_PE | K100: Generalista | AA100: Relazione | AC100: LOM | AD100: LOM | AE100: PAD | AH100: 1 | AI100: =+TODAY()-AM100 -> 659 | AJ100: =+(IF(AL100="Closed","-",IF(TODAY()-MAX(AN100:BA100)>0,TODAY()-MAX(AN100:BA100),0))) -> 322 | AK100: Fondo | AL100: =+IF(BB100="",IF(AZ100="",IF(AY100="",IF(AX100="",COUNTA(AN100:AV100)/9,"On-hold"),"Aborted"),"Closed"),"RIP") -> On-hold | AM100: 45005 | AN100: 45301 | AO100: na | AP100: na | AQ100: 45300 | AW100: 45336 | AX100: 45342 | BA100: =+IF(AY100="","",COUNTA(AN100:AV100)/(COUNTA(AN100:AV100)+COUNTBLANK(AN100:AV100))) | BC100: |
B101: =IF(D101=$A$516,1,IF(D101=$A$517,2,IF(D101=$A$518,3,IF(D101=$A$519,4,IF(D101=$A$520,5,IF(D101=$A$521,6)))))) -> 4 | D101: =IF(AL101="Closed","cls",IF(AL101=1,"sgn",IF(AL101="On-hold","hld",IF(AL101="Aborted","abt",IF(AL101<1,"wip","RIP"))))) -> hld | E101: Ludovico Martelli (buy su Haan) | G101: FI | H101: 04514880485 | I101: 204200 | J101: Consumer: Beauty | K101: Produzione di prodotti per la cura dell'uomo (rasatura, igiene orale, dermocosmesi) | M101: Martelli e Figli Srl | N101: N.U.O. Partners Srl | O101: Stefania Martelli | P101: Giovanni Galeotti | Q101: Carlo Delladio | S101: no | T101: 2023 | U101: 92.63 | V101: 16.84 | W101: =+V101/U101 -> 0.18179855 | X101: 8.74 | Y101: -14.38 | AA101: Relazione | AC101: LOM | AD101: LOM | AE101: RIM | AI101: =+TODAY()-AM101 -> 968 | AJ101: =+(IF(AL101="Closed","-",IF(TODAY()-MAX(AN101:BA101)>0,TODAY()-MAX(AN101:BA101),0))) -> 329 | AK101: Buy Side | AL101: =+IF(BB101="",IF(AZ101="",IF(AY101="",IF(AX101="",COUNTA(AN101:AV101)/9,"On-hold"),"Aborted"),"Closed"),"RIP") -> On-hold | AM101: 44696 | AN101: 44698 | AO101: na | AP101: na | AQ101: 44701 | AR101: 44736 | AS101: 44747 | AT101: 45169 | AW101: 45313 | AX101: 45335 | BA101: =+IF(AY101="","",COUNTA(AN101:AV101)/(COUNTA(AN101:AV101)+COUNTBLANK(AN101:AV101))) | BC101: |
...

Sheet Int'l
E1: =+Tracking!$E$2 -> 2 | F1: NON MODIFICARE CELLE CONTENTENTI FORMULE | V1: Tracking | W1: =+COUNTIF($B:$B,1) -> 9 | Y1: WIP | Z1: =+COUNTIF($B:$B,2) -> 2 | AB1: Aborted | AC1: =+COUNTIF($B:$B,3) -> 181
AA2: |
C3: Status | D3: Flow | E3: Nome | F3: Int'l Partner | G3: Country | H3: Type of mandate | J3: Sector | K3: Description | L3: Partner’s Notes | N3: Relationship @BCA | O3: In Charge @BCA | Q3: Notes | S3: Days since idea | T3: Days since latest progress | V3: Idea | W3: First Contact | X3: Latest Progress | Y3: Status | AA3: |
AA4: |
B5: {=+_xlfn.IFS(C5="Tracking",2,C5="WIP",1,C5="Aborted",3)} -> 1 | C5: =+Y5 -> WIP | D5: Inbound | E5: Food packaging (pitch) | F5: JBR - GMAP | G5: Netherlands | H5: Sell | J5: Industrial | K5: Packaging (food and tobacco) | N5: ASC | S5: =+TODAY()-V5 -> 30 | T5: =+TODAY()-X5 -> 30 | V5: 45634 | W5: 45634 | X5: 45634 | Y5: WIP
B6: {=+_xlfn.IFS(C6="Tracking",2,C6="WIP",1,C6="Aborted",3)} -> 1 | C6: =+Y6 -> WIP | D6: Inbound | E6: Payment app (pitch) | F6: Saga Corporate Finance - GMAP | G6: Norway | H6: Sell | J6: Technology | K6: Payment app group (for bus ticketing, boat docking payments, doctor appointments etc) | N6: ASC | O6: LUS | S6: =+TODAY()-V6 -> 30 | T6: =+TODAY()-X6 -> 29 | V6: 45634 | W6: 45634 | X6: 45635 | Y6: WIP
B7: {=+_xlfn.IFS(C7="Tracking",2,C7="WIP",1,C7="Aborted",3)} -> 1 | C7: =+Y7 -> WIP | D7: Inbound | E7: Injection molding (automotive supplier) | F7: Invescom Corporate Finance - GMAP | G7: Romania | H7: Sell | J7: Industrial | K7: Plastic injection molding supplier in Romania | L7: Ricavi: €27M, EBITDA €5.4M | N7: LUS | O7: FCA | S7: =+TODAY()-V7 -> 36 | T7: =+TODAY()-X7 -> 29 | V7: 45628 | W7: 45628 | X7: 45635 | Y7: WIP
B8: {=+_xlfn.IFS(C8="Tracking",2,C8="WIP",1,C8="Aborted",3)} -> 1 | C8: =+Y8 -> WIP | D8: Inbound | E8: Fine foods (pitch) | F8: Financière de Courcelles - REACH | G8: France | H8: Sell | J8: Food | K8: Branded sea foods products | L8: EBITDA €5M | O8: LUS | S8: =+TODAY()-V8 -> 36 | T8: =+TODAY()-X8 -> 36 | V8: 45628 | W8: 45628 | X8: 45628 | Y8: WIP
B9: {=+_xlfn.IFS(C9="Tracking",2,C9="WIP",1,C9="Aborted",3)} -> 1 | C9: =+Y9 -> WIP | D9: Inbound | E9: Pj Fleming (pitch) | F9: Zeus Capital - REACH | G9: UK | H9: Sell | J9: Consumer | K9: Cleaning products | L9: Ricavi: £60M, EBITDA £16M | O9: LUS | S9: =+TODAY()-V9 -> 49 | T9: =+TODAY()-X9 -> 36 | V9: 45615 | W9: 45615 | X9: 45628 | Y9: WIP
B10: {=+_xlfn.IFS(C10="Tracking",2,C10="WIP",1,C10="Aborted",3)} -> 1 | C10: =+Y10 -> WIP | D10: Inbound | E10: Pj JACKHAMMER | F10: IOM - GMAP | G10: Germany | H10: Sell | J10: Industrial | K10: Demolition and building material recycling business | L10: Ricavi: €55M, EBITDA €7.5M | N10: ASC | O10: LUS | S10: =+TODAY()-V10 -> 78 | T10: =+TODAY()-X10 -> 68 | V10: 45586 | W10: 45586 | X10: 45596 | Y10: WIP
B11: {=+_xlfn.IFS(C11="Tracking",2,C11="WIP",1,C11="Aborted",3)} -> 1 | C11: =+Y11 -> WIP | D11: Outbound | E11: Add-on Almac (Wise) | F11: IOM - GMAP | G11: Germany | H11: Buy | J11: Industrial | K11: Lift platforms | N11: LOM | O11: PAD | S11: =+TODAY()-V11 -> 41 | T11: =+TODAY()-X11 -> 41 | V11: 45623 | W11: 45623 | X11: 45623 | Y11: WIP
B12: {=+_xlfn.IFS(C12="Tracking",2,C12="WIP",1,C12="Aborted",3)} -> 1 | C12: =+Y12 -> WIP | D12: Outbound | E12: Add-on Greenexta (Wise) | F12: Anquor - GMAP | G12: Spain | H12: Buy | J12: Agro | K12: Biostimolanti | N12: LOM | O12: PAD | S12: =+TODAY()-V12 -> 41 | T12: =+TODAY()-X12 -> 41 | V12: 45623 | W12: 45623 | X12: 45623 | Y12: WIP
B13: {=+_xlfn.IFS(C13="Tracking",2,C13="WIP",1,C13="Aborted",3)} -> 1 | C13: =+Y13 -> WIP | D13: Outbound | E13: Brembo | F13: Meridian Capital, Brown/Gibbson/Lang, Crosbie - REACH | G13: Italy | H13: Buy | J13: Automotive | K13: Braking and suspension systems | N13: FCA | O13: ASP | S13: =+TODAY()-V13 -> 98 | T13: =+TODAY()-X13 -> 41 | V13: 45566 | W13: 45602 | X13: 45623 | Y13: WIP
B14: {=+_xlfn.IFS(C14="Tracking",2,C14="WIP",1,C14="Aborted",3)} -> 2 | C14: =+Y14 -> Tracking | D14: Inbound | E14: Lone Rider | F14: Nash Advisory | G14: Australia | H14: Sell | J14: Consumer | K14: Premium Adventure Motorbike accessories | L14: Rev: $11M; Ebitda $3M | N14: FCA | O14: LUS | S14: =+TODAY()-V14 -> 106 | T14: =+TODAY()-X14 -> 106 | V14: 45558 | W14: 45558 | X14: 45558 | Y14: Tracking
B15: {=+_xlfn.IFS(C15="Tracking",2,C15="WIP",1,C15="Aborted",3)} -> 2 | C15: =+Y15 -> Tracking | D15: Outbound | E15: Fagioli PFW | G15: Italy | H15: Sell | J15: Logistics | K15: Project Forwarding | N15: ASC | O15: RIM | S15: =+TODAY()-V15 -> 64 | T15: =+TODAY()-X15 -> 64 | V15: 45600 | W15: 45600 | X15: 45600 | Y15: Tracking
B16: {=+_xlfn.IFS(C16="Tracking",2,C16="WIP",1,C16="Aborted",3)} -> 3 | C16: =+Y16 -> Aborted | D16: Inbound | E16: Pj Despatch | F16: Cooper Parry - REACH | G16: UK | H16: Sell | J16: Logistics | N16: ASC | O16: LUS | S16: =+TODAY()-V16 -> 76 | T16: =+TODAY()-X16 -> 28 | V16: 45588 | W16: 45588 | X16: 45636 | Y16: Aborted
B17: {=+_xlfn.IFS(C17="Tracking",2,C17="WIP",1,C17="Aborted",3)} -> 3 | C17: =+Y17 -> Aborted | D17: Outbound | E17: Pj Roar (Consilium) | F17: Zeus Capital, IOM, Anquor - REACH | G17: USA, Germany, Spain | H17: Buy | J17: Industrial | K17: Macchnari per lavorazione metalli | N17: ROS | O17: GIM | S17: =+TODAY()-V17 -> 79 | T17: =+TODAY()-X17 -> 42 | V17: 45585 | W17: 45585 | X17: 45622 | Y17: Aborted
B18: {=+_xlfn.IFS(C18="Tracking",2,C18="WIP",1,C18="Aborted",3)} -> 3 | C18: =+Y18 -> Aborted | D18: Inbound | E18: Bonatti (pitch) | F18: RIòN - GMAP | G18: Mexico | H18: Sell | J18: Energy | K18: General contractor Energy, Oli&Gas | N18: ASC | S18: =+TODAY()-V18 -> 151 | T18: =+TODAY()-X18 -> 134 | V18: 45513 | W18: 45528 | X18: 45530 | Y18: Aborted
B19: {=+_xlfn.IFS(C19="Tracking",2,C19="WIP",1,C19="Aborted",3)} -> 3 | C19: =+Y19 -> Aborted | D19: Inbound | E19: Pj MOLDANO | F19: Condere - GMAP | G19: Brasil | H19: Sell | J19: Industrial | K19: Mold maker | L19: Rev: c. $8M | N19: ASC | O19: GIM | Q19: Inviato a OMS Besser Group, non interessati | S19: =+TODAY()-V19 -> 286 | T19: =+TODAY()-X19 -> 119 | V19: 45378 | W19: 45383 | X19: 45545 | Y19: Aborted
B20: {=+_xlfn.IFS(C20="Tracking",2,C20="WIP",1,C20="Aborted",3)} -> 3 | C20: =+Y20 -> Aborted | D20: Inbound | E20: Pj CHASE | F20: IOM - GMAP | G20: Germany | H20: Sell | J20: Consumer | K20: Termocamere ad uso privato (caccia) e militare | L20: Ricavi: €10M, EBITDA €1M | N20: ASC | O20: LUS | S20: =+TODAY()-V20 -> 151 | T20: =+TODAY()-X20 -> 105 | V20: 45513 | W20: 45513 | X20: 45559 | Y20: Aborted
B21: {=+_xlfn.IFS(C21="Tracking",2,C21="WIP",1,C21="Aborted",3)} -> 3 | C21: =+Y21 -> Aborted | D21: Inbound | E21: Pj LABEL | F21: Total Finans - GMAP | G21: Turkey | H21: Sell | J21: Industrial | K21: Self adhesive labels | L21: Rev: $25M; Ebitda $3M | N21: ASC | O21: LUS | S21: =+TODAY()-V21 -> 196 | T21: =+TODAY()-X21 -> 127 | V21: 45468 | W21: 45468 | X21: 45537 | Y21: Aborted
B22: {=+_xlfn.IFS(C22="Tracking",2,C22="WIP",1,C22="Aborted",3)} -> 3 | C22: =+Y22 -> Aborted | D22: Inbound | E22: Pj COAST | F22: BGLCO - GMAP | G22: US | H22: Sell | J22: Food | K22: Rumiano Cheese (Branded and private label organic retail) cheese and contract processor | L22: Rev: $120M; Ebitda $7M | N22: FCA | O22: LUS | S22: =+TODAY()-V22 -> 224 | T22: =+TODAY()-X22 -> 106 | V22: 45440 | W22: 45440 | X22: 45558 | Y22: Aborted
B23: {=+_xlfn.IFS(C23="Tracking",2,C23="WIP",1,C23="Aborted",3)} -> 3 | C23: =+Y23 -> Aborted | D23: Inbound | E23: Italian Pharma Manufacturers | F23: Invescom Corporate Finance - GMAP | G23: Hungary | H23: Buy | J23: Pharma | K23: Polish company looking for italian pharma targets | L23: Ricavi €20-70M | N23: FCA | S23: =+TODAY()-V23 -> 217 | T23: =+TODAY()-X23 -> 211 | V23: 45447 | W23: 45449 | X23: 45453 | Y23: Aborted
B24: {=+_xlfn.IFS(C24="Tracking",2,C24="WIP",1,C24="Aborted",3)} -> 3 | C24: =+Y24 -> Aborted | D24: Outbound | E24: EFC Acciai | F24: IOM - FDC - TotalFinans | G24: Italy | H24: Sell | J24: Industrial | K24: Tubificio | N24: ASC | O24: RIM | P24: PAD | S24: =+TODAY()-V24 -> 169 | T24: =+TODAY()-X24 -> 169 | V24: 45495 | W24: 45495 | X24: 45495 | Y24: Aborted
B25: {=+_xlfn.IFS(C25="Tracking",2,C25="WIP",1,C25="Aborted",3)} -> 3 | C25: =+Y25 -> Aborted | D25: Outbound | E25: Stewart | F25: IOM - FDC | G25: Italy | H25: Sell | J25: Pharma | K25: R&D di farmaci per pediatria e ginecologia | N25: LOM | O25: RIM | S25: =+TODAY()-V25 -> 165 | T25: =+TODAY()-X25 -> 165 | V25: 45499 | W25: 45499 | X25: 45499 | Y25: Aborted
B26: {=+_xlfn.IFS(C26="Tracking",2,C26="WIP",1,C26="Aborted",3)} -> 3 | C26: =+Y26 -> Aborted | D26: Outbound | E26: CDZ Vini Srl | F26: Anquor Corporate Finance - GMAP | G26: Spain | H26: Sell | J26: Food: Wine | K26: Winery | L26: Ricavi: €28M, EBITDA €4M | N26: ROS | O26: LUS | S26: =+TODAY()-V26 -> 224 | T26: =+TODAY()-X26 -> 224 | V26: 45440 | W26: 45440 | X26: 45440 | Y26: Aborted
B27: {=+_xlfn.IFS(C27="Tracking",2,C27="WIP",1,C27="Aborted",3)} -> 3 | C27: =+Y27 -> Aborted | D27: Outbound | E27: Pj PORPORA (CDZ Vini) | F27: Anquor Corporate Finance - GMAP | G27: Spain | H27: Sell | J27: Food&Beverage | K27: Casa vinicola | L27: Rev: €28M, Ebitda: €4M | N27: ROS | O27: LUS | S27: =+TODAY()-V27 -> 239 | T27: =+TODAY()-X27 -> 237 | V27: 45425 | W27: 45425 | X27: 45427 | Y27: Aborted
B28: {=+_xlfn.IFS(C28="Tracking",2,C28="WIP",1,C28="Aborted",3)} -> 3 | C28: =+Y28 -> Aborted | D28: Inbound | E28: Groupe H4 | F28: Financière de Courcelles - GMAP | G28: France | H28: Sell | J28: Services | K28: Brand (Jaym) di cover e accessori smartphone | L28: Rev: c. €10M | N28: ASC | O28: RIM | S28: =+TODAY()-V28 -> 351 | T28: =+TODAY()-X28 -> 349 | V28: 45313 | W28: 45313 | X28: 45315 | Y28: Aborted
B29: {=+_xlfn.IFS(C29="Tracking",2,C29="WIP",1,C29="Aborted",3)} -> 3 | C29: =+Y29 -> Aborted | D29: Inbound | E29: Haier Smart Home | F29: Condere - GMAP | G29: Brasil | H29: Buy | J29: Technology | K29: Soluzioni IoT per la casa | L29: - | N29: ASC | O29: LUS | S29: =+TODAY()-V29 -> 321 | T29: =+TODAY()-X29 -> 321 | V29: 45343 | W29: 45343 | X29: 45343 | Y29: Aborted | AA29: |
B30: {=+_xlfn.IFS(C30="Tracking",2,C30="WIP",1,C30="Aborted",3)} -> 3 | C30: =+Y30 -> Aborted | D30: Outbound | E30: Industrie Chimiche Forestali | F30: GMAP | G30: Italy | H30: Sell | J30: Industrial | K30: Produzione di colle e riforzanti per diversi settori industriali | L30: Ricavi: €88M, EBITDA €8M | N30: ASC | O30: RIM | S30: =+TODAY()-V30 -> 439 | T30: =+TODAY()-X30 -> 439 | V30: 45225 | W30: 45225 | X30: 45225 | Y30: Aborted
B31: {=+_xlfn.IFS(C31="Tracking",2,C31="WIP",1,C31="Aborted",3)} -> 3 | C31: =+Y31 -> Aborted | D31: Outbound | E31: Spica (Pj. Card) | F31: GMAP | G31: Italy | H31: Sell | J31: Industrial | K31: PVC films manufacturer | N31: ASC | O31: RIM | S31: =+TODAY()-V31 -> 328 | T31: =+TODAY()-X31 -> 328 | V31: 45336 | W31: 45336 | X31: 45336 | Y31: Aborted
B32: {=+_xlfn.IFS(C32="Tracking",2,C32="WIP",1,C32="Aborted",3)} -> 3 | C32: =+Y32 -> Aborted | D32: Inbound | E32: Stoll Trucks | F32: Financière de Courcelles - GMAP | G32: Luxembourg | H32: Buy | J32: Automotive | K32: One-stop-services for commercial vehicles, Heavy trucks and Bus | L32: Revenue: € 70M, EBITDA: € 9-10M | N32: FCA | O32: MMO | Q32: Close proximity to management and the investment fund. We need to work on the buy side | S32: =+TODAY()-V32 -> 336 | T32: =+TODAY()-X32 -> 336 | V32: 45328 | W32: =+V32 -> 45328 | X32: =+W32 -> 45328 | Y32: Aborted
B33: {=+_xlfn.IFS(C33="Tracking",2,C33="WIP",1,C33="Aborted",3)} -> 3 | C33: =+Y33 -> Aborted | D33: Inbound | E33: Groupe LT | F33: Financière de Courcelles - GMAP | G33: France | H33: Buy | J33: Industrial | K33: Worksite equipment rental and service provider | L33: - | N33: LOM | O33: LUS | S33: =+TODAY()-V33 -> 358 | T33: =+TODAY()-X33 -> 358 | V33: 45306 | W33: 45306 | X33: 45306 | Y33: Aborted
B34: {=+_xlfn.IFS(C34="Tracking",2,C34="WIP",1,C34="Aborted",3)} -> 3 | C34: =+Y34 -> Aborted | D34: Outbound | E34: Target ProA (Pergole/Tende) | F34: Financière de Courcelles - GMAP | G34: Italy | H34: Buy | J34: Industrial | K34: Produzione di schermature solari | L34: EBITDA >€3M | N34: LOM | O34: PAD | S34: =+TODAY()-V34 -> 361 | T34: =+TODAY()-X34 -> 358 | V34: 45303 | W34: 45303 | X34: 45306 | Y34: Aborted
B35: {=+_xlfn.IFS(C35="Tracking",2,C35="WIP",1,C35="Aborted",3)} -> 3 | C35: =+Y35 -> Aborted | D35: Outbound | E35: Target ProA (HR) | F35: Financière de Courcelles - GMAP | G35: Italy | H35: Buy | J35: Services | K35: Personale interinale e HR | L35: EBITDA >€3M | N35: LOM | O35: PAD | S35: =+TODAY()-V35 -> 361 | T35: =+TODAY()-X35 -> 358 | V35: 45303 | W35: 45303 | X35: 45306 | Y35: Aborted
B36: {=+_xlfn.IFS(C36="Tracking",2,C36="WIP",1,C36="Aborted",3)} -> 3 | C36: =+Y36 -> Aborted | D36: Outbound | E36: Target Riverside (BioDue) | F36: Anquor Corporate Finance - GMAP | G36: Italy | H36: Buy | J36: Pharma | K36: Produzione di colle e riforzanti per diversi settori industriali | L36: EBITDA >€5M | N36: ASC | S36: =+TODAY()-V36 -> 389 | T36: =+TODAY()-X36 -> 361 | V36: 45275 | W36: 45275 | X36: 45303 | Y36: Aborted
B37: {=+_xlfn.IFS(C37="Tracking",2,C37="WIP",1,C37="Aborted",3)} -> 3 | C37: =+Y37 -> Aborted | D37: Inbound | E37: Nobis | F37: Crossbie | G37: Canada | H37: Sell | J37: Fashion & Luxury | K37: Luxury apparel brand | L37: Rev: $25M | N37: ASC | O37: LUS | S37: =+TODAY()-V37 -> 419 | T37: =+TODAY()-X37 -> 411 | V37: 45245 | W37: 45245 | X37: 45253 | Y37: Aborted
B38: {=+_xlfn.IFS(C38="Tracking",2,C38="WIP",1,C38="Aborted",3)} -> 3 | C38: =+Y38 -> Aborted | D38: Inbound | E38: Pelagos | F38: RIòN - GMAP | G38: Mexico | H38: Sell | J38: Food | K38: Fishing, processing, and commercializing sardines | L38: Rev: $86M; Ebitda $29m | N38: LOM | O38: LUS | S38: =+TODAY()-V38 -> 480 | T38: =+TODAY()-X38 -> 480 | V38: 45184 | W38: 45184 | X38: 45184 | Y38: Aborted
B39: {=+_xlfn.IFS(C39="Tracking",2,C39="WIP",1,C39="Aborted",3)} -> 3 | C39: =+Y39 -> Aborted | D39: Inbound | E39: Epicure | F39: Financière de Courcelles - GMAP | G39: France | H39: Sell | J39: Food | K39: Gourmet food (focus: tartufo) | L39: Ricavi: €30M, EBITDA €4M | N39: LOM | O39: LUS | S39: =+TODAY()-V39 -> 489 | T39: =+TODAY()-X39 -> 489 | V39: 45175 | W39: 45175 | X39: 45175 | Y39: Aborted
B40: {=+_xlfn.IFS(C40="Tracking",2,C40="WIP",1,C40="Aborted",3)} -> 3 | C40: =+Y40 -> Aborted | D40: Outbound | E40: Stam | F40: GMAP | G40: Italy | H40: Sell | J40: Industrial | K40: Produzione di linee di profilatura e di taglio della lamiera | L40: Rev: €30M; Ebitda €5m | N40: ASC | O40: RIM | P40: LUS | S40: =+TODAY()-V40 -> 502 | T40: =+TODAY()-X40 -> 502 | V40: 45162 | W40: 45162 | X40: 45162 | Y40: Aborted
B41: {=+_xlfn.IFS(C41="Tracking",2,C41="WIP",1,C41="Aborted",3)} -> 3 | C41: =+Y41 -> Aborted | D41: Inbound | E41: HICKORY | F41: BGLCO - GMAP | G41: US | H41: Sell | J41: Food&Beverage | K41: Produttore di salse per condimento | L41: Rev: $150M; Ebitda $50m | N41: FCA | S41: =+TODAY()-V41 -> 531 | T41: =+TODAY()-X41 -> 531 | V41: 45133 | W41: 45133 | X41: 45133 | Y41: Aborted
B42: {=+_xlfn.IFS(C42="Tracking",2,C42="WIP",1,C42="Aborted",3)} -> 3 | C42: =+Y42 -> Aborted | D42: Inbound | E42: Pj Trigger | F42: Financière de Courcelles - GMAP | G42: France | H42: Sell | J42: Industrial | K42: High-end sensors | N42: ASC | O42: RIM | S42: =+TODAY()-V42 -> 695 | T42: =+TODAY()-X42 -> 582 | V42: 44969 | W42: 44970 | X42: 45082 | Y42: Aborted | AA42: |
B43: {=+_xlfn.IFS(C43="Tracking",2,C43="WIP",1,C43="Aborted",3)} -> 3 | C43: =+Y43 -> Aborted | D43: Inbound | E43: Pj Tifaani | F43: Financière de Courcelles - GMAP | G43: France | H43: Sell | J43: Industrial | K43: industrial engineering: automated production lines and customized machines | L43: Rev: €50M; Ebitda €7m | N43: FCA | O43: LUS | P43: MAD | S43: =+TODAY()-V43 -> 581 | T43: =+TODAY()-X43 -> 573 | V43: 45083 | W43: 45083 | X43: 45091 | Y43: Aborted | AA43: |
B44: {=+_xlfn.IFS(C44="Tracking",2,C44="WIP",1,C44="Aborted",3)} -> 3 | C44: =+Y44 -> Aborted | D44: Inbound | E44: Hinojosa Group | F44: CS Corporate Advisory | G44: Spain | H44: Buy | J44: Industrial | K44: Corrugated cardboard packaging manufacturer | L44: Rev: €800M | N44: LOM | O44: LUS | P44: MAD | S44: =+TODAY()-V44 -> 596 | T44: =+TODAY()-X44 -> 595 | V44: 45068 | W44: 45064 | X44: 45069 | Y44: Aborted | AA44: |
B45: {=+_xlfn.IFS(C45="Tracking",2,C45="WIP",1,C45="Aborted",3)} -> 3 | C45: =+Y45 -> Aborted | D45: Inbound | E45: Pj Arnold | F45: Invescom Corporate Finance - GMAP | G45: Hungary | H45: Sell | J45: Industrial | K45: Private label manufacturer of nutrition supplements | L45: Rev: €31M; EBITDA: €5.8M | N45: FCA | O45: LUS | S45: =+TODAY()-V45 -> 620 | T45: =+TODAY()-X45 -> 616 | V45: 45044 | W45: 45044 | X45: 45048 | Y45: Aborted | AA45: |
B46: {=+_xlfn.IFS(C46="Tracking",2,C46="WIP",1,C46="Aborted",3)} -> 3 | C46: =+Y46 -> Aborted | D46: Outbound | E46: Flair (Xerjoff) | F46: Meeting Barcellona | G46: Italy | H46: Buy | N46: LOM | O46: GID | P46: MAD | S46: =+TODAY()-V46 -> 596 | T46: =+TODAY()-X46 -> 586 | V46: 45068 | W46: 45068 | X46: 45078 | Y46: Aborted | AA46: |
B47: {=+_xlfn.IFS(C47="Tracking",2,C47="WIP",1,C47="Aborted",3)} -> 3 | C47: =+Y47 -> Aborted | D47: Outbound | E47: Silicon (NextHS) | F47: Meeting Barcellona | G47: Italy | H47: Sell | N47: LOM | O47: RIM | P47: PAD | S47: =+TODAY()-V47 -> 596 | T47: =+TODAY()-X47 -> 582 | V47: 45068 | W47: 45068 | X47: 45082 | Y47: Aborted | AA47: |
B48: {=+_xlfn.IFS(C48="Tracking",2,C48="WIP",1,C48="Aborted",3)} -> 3 | C48: =+Y48 -> Aborted | D48: Outbound | E48: ICT (Intersistemi) | F48: Meeting Barcellona | G48: Italy | H48: Sell | S48: =+TODAY()-V48 -> 596 | T48: =+TODAY()-X48 -> 586 | V48: 45068 | W48: 45068 | X48: 45078 | Y48: Aborted | AA48: |
B49: {=+_xlfn.IFS(C49="Tracking",2,C49="WIP",1,C49="Aborted",3)} -> 3 | C49: =+Y49 -> Aborted | D49: Outbound | E49: Vax (Vismederi) | F49: Meeting Barcellona | G49: Italy | H49: Sell | N49: FCA | S49: =+TODAY()-V49 -> 596 | T49: =+TODAY()-X49 -> 596 | V49: 45068 | W49: 45068 | X49: 45068 | Y49: Aborted | AA49: |
B50: {=+_xlfn.IFS(C50="Tracking",2,C50="WIP",1,C50="Aborted",3)} -> 3 | C50: =+Y50 -> Aborted | D50: Outbound | E50: VegOil (Tampieri) | F50: Meeting Barcellona | G50: Italy | H50: Sell | N50: FCA | O50: PAD | P50: MAD | S50: =+TODAY()-V50 -> 596 | T50: =+TODAY()-X50 -> 586 | V50: 45068 | W50: 45068 | X50: 45078 | Y50: Aborted | AA50: |
B51: {=+_xlfn.IFS(C51="Tracking",2,C51="WIP",1,C51="Aborted",3)} -> 3 | C51: =+Y51 -> Aborted | D51: Outbound | E51: THERAS Group (Medicus) | F51: GMAP | G51: Italy | H51: Sell | J51: Medical | K51: Disposables for diabetes and pain therapy | N51: FCA | O51: FCA | S51: =+TODAY()-V51 -> 622 | T51: =+TODAY()-X51 -> 622 | V51: 45042 | X51: 45042 | Y51: Aborted | AA51: |
B52: {=+_xlfn.IFS(C52="Tracking",2,C52="WIP",1,C52="Aborted",3)} -> 3 | C52: =+Y52 -> Aborted | D52: Inbound | E52: Pj Chariot | F52: IOM - GMAP | G52: Germany | H52: Sell | J52: Logistics | K52: Asset heavy freight forwarder for short haul | L52: Rev: €20M; EBITDA: €1M | N52: ASC | O52: LUS | S52: =+TODAY()-V52 -> 706 | T52: =+TODAY()-X52 -> 678 | V52: 44958 | W52: 44958 | X52: 44986 | Y52: Aborted | AA52: |
B53: {=+_xlfn.IFS(C53="Tracking",2,C53="WIP",1,C53="Aborted",3)} -> 3 | C53: =+Y53 -> Aborted | D53: Outbound | E53: Jakala (buy) | F53: GMAP | G53: Italy | H53: Buy | J53: Consulting | K53: Martech | L53: Rev: €266 M; EBITDA: €20.7M | N53: ASC | O53: LUS | S53: =+TODAY()-V53 -> 768 | T53: =+TODAY()-X53 -> 749 | V53: 44896 | W53: 44896 | X53: 44915 | Y53: Aborted | AA53: |
B54: {=+_xlfn.IFS(C54="Tracking",2,C54="WIP",1,C54="Aborted",3)} -> 3 | C54: =+Y54 -> Aborted | D54: Outbound | E54: Fudex Group SpA | F54: GMAP | G54: Italy | H54: Sell | J54: Food&Beverage | K54: Produzione Snack Salutistici | N54: FCA | O54: LUS | S54: =+TODAY()-V54 -> 712 | T54: =+TODAY()-X54 -> 712 | V54: 44952 | W54: 44952 | X54: 44952 | Y54: Aborted | AA54: |
B55: {=+_xlfn.IFS(C55="Tracking",2,C55="WIP",1,C55="Aborted",3)} -> 3 | C55: =+Y55 -> Aborted | D55: Outbound | E55: G. Mariani & Co. | F55: GMAP | G55: Italy | H55: Sell | J55: Food&Beverage | K55: Producer of aromas and ingredients | N55: ASC | O55: RIM | S55: =+TODAY()-V55 -> 713 | T55: =+TODAY()-X55 -> 708 | V55: 44951 | W55: 44952 | X55: 44956 | Y55: Aborted | AA55: |
B56: {=+_xlfn.IFS(C56="Tracking",2,C56="WIP",1,C56="Aborted",3)} -> 3 | C56: =+Y56 -> Aborted | D56: Inbound | E56: Tessitura Monti (buyside con weba) | F56: Zetra - GMAP | G56: Italy | H56: Buy | J56: Textile | K56: Fashion & Textile | N56: ASC | O56: LUS | S56: =+TODAY()-V56 -> 708 | T56: =+TODAY()-X56 -> 708 | V56: 44956 | W56: 44956 | X56: 44956 | Y56: Aborted | AA56: |
B57: {=+_xlfn.IFS(C57="Tracking",2,C57="WIP",1,C57="Aborted",3)} -> 3 | C57: =+Y57 -> Aborted | D57: Outbound | E57: Distilleria F.lli Caffo (master always live) | F57: GMAP | G57: Italy | H57: Buy | J57: Spirits | N57: ASC | O57: LUS | S57: =+TODAY()-V57 -> 768 | T57: =+TODAY()-X57 -> 0 | V57: 44896 | W57: 44896 | X57: =+TODAY() -> 45664 | Y57: Aborted | AA57: |
B58: {=+_xlfn.IFS(C58="Tracking",2,C58="WIP",1,C58="Aborted",3)} -> 3 | C58: =+Y58 -> Aborted | D58: Outbound | E58: Pezzutti Group - Pj Grecale (sell side) | F58: GMAP | G58: Italy | H58: Sell | J58: Industrial | K58: Stampaggio plastico | N58: ASC | O58: ALP | S58: =+TODAY()-V58 -> 963 | T58: =+TODAY()-X58 -> 0 | V58: 44701 | W58: 44711 | X58: =+TODAY() -> 45664 | Y58: Aborted | AA58: |
B59: {=+_xlfn.IFS(C59="Tracking",2,C59="WIP",1,C59="Aborted",3)} -> 3 | C59: =+Y59 -> Aborted | D59: Outbound | E59: Pj Egg (Caseificio dell'Alta Langa) | F59: REACH | G59: Italy | H59: Sell | J59: Food&Beverage | K59: Produzione di formaggi artigianali di alta qualità | L59: Ricavi: €14M, EBITDA €0,6M | N59: ROS | O59: GID | Q59: Inviato a Anquor, FDC, Zeus, Meridian, BGL | S59: =+TODAY()-V59 -> 228 | T59: =+TODAY()-X59 -> 225 | V59: 45436 | W59: 45439 | X59: 45439 | Y59: Aborted
B60: {=+_xlfn.IFS(C60="Tracking",2,C60="WIP",1,C60="Aborted",3)} -> 3 | C60: =+Y60 -> Aborted | D60: Outbound | E60: Pj Apple (Comavicola) | F60: REACH | G60: Italy | H60: Sell | J60: Food&Beverage | K60: Distributore di prodotti ittici congelati | L60: Ricavi: €137M, EBITDA €7M | N60: ROS | O60: GID | Q60: Inviato a JBR, Saga, Anquor, FDC, Zeus, Meridian, BGL | S60: =+TODAY()-V60 -> 228 | T60: =+TODAY()-X60 -> 225 | V60: 45436 | W60: 45439 | X60: 45439 | Y60: Aborted
B61: {=+_xlfn.IFS(C61="Tracking",2,C61="WIP",1,C61="Aborted",3)} -> 3 | C61: =+Y61 -> Aborted | D61: Inbound | E61: La Coque de Nacre | F61: Financière de Courcelles - GMAP | G61: France | H61: Buy | J61: Affordable jewelery | K61: designer and B2B distributor of silver & gold-plated jewelry | L61: Rev: €40M; EBITDA €8M | N61: LOM | O61: GID | S61: =+TODAY()-V61 -> 648 | T61: =+TODAY()-X61 -> 435 | V61: 45016 | W61: 45016 | X61: 45229 | Y61: Aborted | AA61: |
B62: {=+_xlfn.IFS(C62="Tracking",2,C62="WIP",1,C62="Aborted",3)} -> 3 | C62: =+Y62 -> Aborted | D62: Outbound | E62: Elogy | F62: GMAP | G62: Italy | H62: Sell | J62: Logistics | N62: ASC | S62: =+TODAY()-V62 -> 538 | T62: =+TODAY()-X62 -> 536 | V62: 45126 | W62: 45126 | X62: 45128 | Y62: Aborted
B63: {=+_xlfn.IFS(C63="Tracking",2,C63="WIP",1,C63="Aborted",3)} -> 3 | C63: =+Y63 -> Aborted | D63: Outbound | E63: Montallegro | F63: JBR - GMAP | G63: Italy | H63: Sell | J63: Medical | K63: Clinica privata | L63: Ricavi: 20M, EBITDA 3,6M | N63: ASC | O63: LUS | S63: =+TODAY()-V63 -> 686 | T63: =+TODAY()-X63 -> 685 | V63: 44978 | W63: 44979 | X63: 44979 | Y63: Aborted | AA63: |
B64: {=+_xlfn.IFS(C64="Tracking",2,C64="WIP",1,C64="Aborted",3)} -> 3 | C64: =+Y64 -> Aborted | D64: Outbound | E64: Fiaptech | F64: GMAP | G64: Italy | H64: Sell | J64: Industrial | K64: Produzione di anime/tubi in plastica | L64: Rev: €32 M; EBITDA: €6M | N64: LOM | O64: LUS | S64: =+TODAY()-V64 -> 697 | T64: =+TODAY()-X64 -> 697 | V64: 44967 | W64: 44967 | X64: 44967 | Y64: Aborted | AA64: |
B65: {=+_xlfn.IFS(C65="Tracking",2,C65="WIP",1,C65="Aborted",3)} -> 3 | C65: =+Y65 -> Aborted | D65: Outbound | E65: Istituto Volta | F65: GMAP | G65: Italy | H65: Sell | J65: Education | K65: Corsi di informatica | N65: LOM | O65: LUS | S65: =+TODAY()-V65 -> 701 | T65: =+TODAY()-X65 -> 701 | V65: 44963 | W65: 44963 | X65: 44963 | Y65: Aborted | AA65: |
B66: {=+_xlfn.IFS(C66="Tracking",2,C66="WIP",1,C66="Aborted",3)} -> 3 | C66: =+Y66 -> Aborted | D66: Outbound | E66: Pepino | F66: GMAP | G66: Italy | H66: Sell | J66: Food&Beverage | K66: Produzione B2B gelati | N66: LOM | O66: RIM | S66: =+TODAY()-V66 -> 713 | T66: =+TODAY()-X66 -> 713 | V66: 44951 | W66: 44951 | X66: 44951 | Y66: Aborted | AA66: |
B67: {=+_xlfn.IFS(C67="Tracking",2,C67="WIP",1,C67="Aborted",3)} -> 3 | C67: =+Y67 -> Aborted | D67: Outbound | E67: Aspesi | F67: Palazzari & Turries | G67: Italy | H67: Buy | J67: Fashion | K67: Brand di moda | N67: LOM | S67: =+TODAY()-V67 -> 960 | T67: =+TODAY()-X67 -> 960 | V67: 44704 | W67: 44707 | X67: 44704 | Y67: Aborted | AA67: |
B68: {=+_xlfn.IFS(C68="Tracking",2,C68="WIP",1,C68="Aborted",3)} -> 3 | C68: =+Y68 -> Aborted | D68: Outbound | E68: Astro | F68: IOM - GMAP | G68: Italy | H68: Sell | J68: Beverage | K68: Closures | N68: LOM | O68: ALP | S68: =+TODAY()-V68 -> 1063 | T68: =+TODAY()-X68 -> 1063 | V68: 44601 | W68: 44613 | X68: 44601 | Y68: Aborted | AA68: |
B69: {=+_xlfn.IFS(C69="Tracking",2,C69="WIP",1,C69="Aborted",3)} -> 3 | C69: =+Y69 -> Aborted | D69: Outbound | E69: Alfaparf (Buy-side) | F69: Financière de Courcelles - GMAP | G69: Italy | H69: Buy | J69: Industrial | K69: Prodotti haircare | N69: LOM | O69: LUS | S69: =+TODAY()-V69 -> 1079 | T69: =+TODAY()-X69 -> 1079 | V69: 44585 | W69: 44600 | X69: 44585 | Y69: Aborted | AA69: |
B70: {=+_xlfn.IFS(C70="Tracking",2,C70="WIP",1,C70="Aborted",3)} -> 3 | C70: =+Y70 -> Aborted | D70: Outbound | E70: Techedge (HL) | F70: Houlihan Lockey - Int. | G70: Italy | H70: Buy | J70: Beverage | K70: IT | N70: LOM | O70: ALP | S70: =+TODAY()-V70 -> 982 | T70: =+TODAY()-X70 -> 982 | V70: 44682 | W70: na | X70: 44682 | Y70: Aborted | AA70: |
B71: {=+_xlfn.IFS(C71="Tracking",2,C71="WIP",1,C71="Aborted",3)} -> 3 | C71: =+Y71 -> Aborted | D71: Inbound | E71: Finmasi Group | F71: Financière de Courcelles - GMAP | G71: Italy | H71: Buy | J71: Beverage | K71: PCB | N71: ASC | O71: ALP | S71: =+TODAY()-V71 -> 1015 | T71: =+TODAY()-X71 -> 954 | V71: 44649 | W71: 44649 | X71: 44710 | Y71: Aborted | AA71: |
B72: {=+_xlfn.IFS(C72="Tracking",2,C72="WIP",1,C72="Aborted",3)} -> 3 | C72: =+Y72 -> Aborted | D72: Inbound | E72: Sagiv - Gaon Group | F72: Value Base - GMAP | G72: Israel | H72: Buy | J72: Manufacturing | K72: Componenti in ottone (Valvole, raccordi,ecc) | N72: ASC | O72: ALP | S72: =+TODAY()-V72 -> 945 | T72: =+TODAY()-X72 -> 943 | V72: 44719 | W72: 44719 | X72: 44721 | Y72: Aborted | AA72: |
B73: {=+_xlfn.IFS(C73="Tracking",2,C73="WIP",1,C73="Aborted",3)} -> 3 | C73: =+Y73 -> Aborted | D73: Inbound | E73: Project Lectio | F73: Condere - GMAP | G73: Brasil | H73: Sell | J73: Industrial | K73: tipografia brasiliana | L73: 100% cash out | N73: ASC | O73: ALP | S73: =+TODAY()-V73 -> 1201 | T73: =+TODAY()-X73 -> 938 | V73: 44463 | W73: 44463 | X73: 44726 | Y73: Aborted | AA73: |
B74: {=+_xlfn.IFS(C74="Tracking",2,C74="WIP",1,C74="Aborted",3)} -> 3 | C74: =+Y74 -> Aborted | D74: Inbound | E74: Pj Fine (MPI buy-side su UtilGroup) | F74: BGLCO - GMAP | G74: US | H74: Buy | J74: Industrial | N74: ASC | O74: LUS | S74: =+TODAY()-V74 -> 816 | T74: =+TODAY()-X74 -> 812 | V74: 44848 | W74: 44848 | X74: 44852 | Y74: Aborted | AA74: |
B75: {=+_xlfn.IFS(C75="Tracking",2,C75="WIP",1,C75="Aborted",3)} -> 3 | C75: =+Y75 -> Aborted | D75: Inbound | E75: Pj Pearl | F75: Zeus Capital - GMAP | G75: UK | H75: Sell | J75: Services | K75: Compagnia aerea di private charter | L75: Rev: €133M; EBITDA: €21M | N75: ASC | O75: LUS | P75: GID | S75: =+TODAY()-V75 -> 775 | T75: =+TODAY()-X75 -> 763 | V75: 44889 | W75: 44889 | X75: 44901 | Y75: Aborted | AA75: |
B76: {=+_xlfn.IFS(C76="Tracking",2,C76="WIP",1,C76="Aborted",3)} -> 3 | C76: =+Y76 -> Aborted | D76: Outbound | E76: Pj Neighbourhood (Borello) | F76: Financière de Courcelles - GMAP | G76: Italy | H76: Sell | J76: Retail | K76: Supermarket | N76: LOM | O76: PAD | S76: =+TODAY()-V76 -> 1063 | T76: =+TODAY()-X76 -> 1063 | V76: 44601 | W76: 44613 | X76: 44601 | Y76: Aborted | AA76: |
B77: {=+_xlfn.IFS(C77="Tracking",2,C77="WIP",1,C77="Aborted",3)} -> 3 | C77: =+Y77 -> Aborted | D77: Inbound | E77: Pj Beatrice | F77: Zeus Capital - GMAP | G77: UK | H77: Sell | J77: Manufacturing | K77: Toy / Party / Craft & Play market | L77: Rev: €9.9M; EBITDA: €2M | N77: ASC | O77: LUS | S77: =+TODAY()-V77 -> 840 | T77: =+TODAY()-X77 -> 557 | V77: 44824 | W77: 44824 | X77: 45107 | Y77: Aborted | AA77: |
B78: {=+_xlfn.IFS(C78="Tracking",2,C78="WIP",1,C78="Aborted",3)} -> 3 | C78: =+Y78 -> Aborted | D78: Inbound | E78: Pj AROMA | F78: BGLCO - GMAP | G78: US | H78: Sell | J78: Food | K78: Private label dessert products | L78: Rev: $31M; Ebitda $4M | N78: FCA | O78: LUS | S78: =+TODAY()-V78 -> 88 | T78: =+TODAY()-X78 -> 63 | V78: 45576 | W78: 45576 | X78: 45601 | Y78: Aborted
B79: {=+_xlfn.IFS(C79="Tracking",2,C79="WIP",1,C79="Aborted",3)} -> 3 | C79: =+Y79 -> Aborted | D79: Inbound | E79: Groupe BEL | F79: Financière de Courcelles - GMAP | G79: France | H79: Buy | J79: Food | K79: Dairy and healthy products | O79: LUS | S79: =+TODAY()-V79 -> 96 | T79: =+TODAY()-X79 -> 92 | V79: 45568 | W79: 45568 | X79: 45572 | Y79: Aborted
B80: {=+_xlfn.IFS(C80="Tracking",2,C80="WIP",1,C80="Aborted",3)} -> 3 | C80: =+Y80 -> Aborted | D80: Inbound | E80: Mister Freed | F80: Zeus Capital - GMAP | G80: UK | H80: Sell | J80: Food | K80: Healthy snacks | L80: Rev: $6M | N80: LUS | O80: LUS | S80: =+TODAY()-V80 -> 197 | T80: =+TODAY()-X80 -> 120 | V80: 45467 | W80: 45467 | X80: 45544 | Y80: Aborted
B81: {=+_xlfn.IFS(C81="Tracking",2,C81="WIP",1,C81="Aborted",3)} -> 3 | C81: =+Y81 -> Aborted | D81: Inbound | E81: Pj DAWN | F81: Zeus Capital - GMAP | G81: United Kingdom | H81: Sell | J81: Technology | K81: SaaS technology and equipment supplier | S81: =+TODAY()-V81 -> 92 | T81: =+TODAY()-X81 -> 92 | V81: 45572 | W81: 45572 | X81: 45572 | Y81: Aborted
B82: {=+_xlfn.IFS(C82="Tracking",2,C82="WIP",1,C82="Aborted",3)} -> 3 | C82: =+Y82 -> Aborted | D82: Inbound | E82: Orlay | F82: Zeus Capital - GMAP | G82: United Kingdom | H82: Sell | J82: Fashion & Luxury | K82: Female clothing brand | L82: Rev: €35M | S82: =+TODAY()-V82 -> 99 | T82: =+TODAY()-X82 -> 99 | V82: 45565 | W82: 45565 | X82: 45565 | Y82: Aborted
B83: {=+_xlfn.IFS(C83="Tracking",2,C83="WIP",1,C83="Aborted",3)} -> 3 | C83: =+Y83 -> Aborted | D83: Inbound | E83: Korloff | F83: Financière de Courcelles - GMAP | G83: France | H83: Sell | J83: Luxury | K83: Jewelry brand | S83: =+TODAY()-V83 -> 106 | T83: =+TODAY()-X83 -> 106 | V83: 45558 | W83: 45558 | X83: 45558 | Y83: Aborted
B84: {=+_xlfn.IFS(C84="Tracking",2,C84="WIP",1,C84="Aborted",3)} -> 3 | C84: =+Y84 -> Aborted | D84: Inbound | E84: Beston Global Foods | F84: Nash Advisory | G84: Australia | H84: Sell | J84: Food | K84: Lactoferrin plant acquisition opportunity | N84: ROS | O84: LUS | S84: =+TODAY()-V84 -> 106 | T84: =+TODAY()-X84 -> 106 | V84: 45558 | W84: 45558 | X84: 45558 | Y84: Aborted
B85: {=+_xlfn.IFS(C85="Tracking",2,C85="WIP",1,C85="Aborted",3)} -> 3 | C85: =+Y85 -> Aborted | D85: Inbound | E85: Pj SUNRISE | F85: IOM - GMAP | G85: Germany | H85: Sell | J85: Energy | K85: Pannelli solari | L85: Ricavi: €132M, EBITDA €18M | N85: ASC | S85: =+TODAY()-V85 -> 137 | T85: =+TODAY()-X85 -> 137 | V85: 45527 | W85: 45527 | X85: 45527 | Y85: Aborted
B86: {=+_xlfn.IFS(C86="Tracking",2,C86="WIP",1,C86="Aborted",3)} -> 3 | C86: =+Y86 -> Aborted | D86: Inbound | E86: Pj FUJI | F86: NEXUS | G86: Vietnam | H86: Sell | J86: Industrial | K86: Allevamento avicolo | L86: Ricavi: $96.4M, EBITDA: $5.4M | N86: ASC | Q86: Advisor non REACH | S86: =+TODAY()-V86 -> 133 | T86: =+TODAY()-X86 -> 133 | V86: 45531 | W86: 45531 | X86: 45531 | Y86: Aborted
B87: {=+_xlfn.IFS(C87="Tracking",2,C87="WIP",1,C87="Aborted",3)} -> 3 | C87: =+Y87 -> Aborted | D87: Inbound | E87: Athena | F87: FDC | G87: FR | H87: Sell | J87: Industrial | K87: Rivestimenti sedili automotive | S87: =+TODAY()-V87 -> 197 | T87: =+TODAY()-X87 -> 195 | V87: 45467 | W87: 45467 | X87: 45469 | Y87: Aborted
B88: {=+_xlfn.IFS(C88="Tracking",2,C88="WIP",1,C88="Aborted",3)} -> 3 | C88: =+Y88 -> Aborted | D88: Inbound | E88: Pj SAFETY | F88: Anquor Corporate Finance - GMAP | G88: Spain | H88: Sell | J88: Consumer | K88: Safety shoes producer | L88: Ricavi: €20,4M, EBITDA €3,2M | N88: LUS | O88: LUS | S88: =+TODAY()-V88 -> 224 | T88: =+TODAY()-X88 -> 169 | V88: 45440 | W88: 45440 | X88: 45495 | Y88: Aborted
B89: {=+_xlfn.IFS(C89="Tracking",2,C89="WIP",1,C89="Aborted",3)} -> 3 | C89: =+Y89 -> Aborted | D89: Inbound | E89: Pitch in the PVC/Building products in UK | F89: Zeus Capital - GMAP | G89: UK | H89: Sell | J89: Industrial | K89: Manufacturers and distributors of high quality PVC-U building products (fascias, soffits, gutters and cladding to windows, composite doors, bi-folding doors and sliding doors) | L89: Ricavi: £150M, EBITDA £14M | O89: LUS | S89: =+TODAY()-V89 -> 211 | T89: =+TODAY()-X89 -> 211 | V89: 45453 | W89: 45453 | X89: 45453 | Y89: Aborted
B90: {=+_xlfn.IFS(C90="Tracking",2,C90="WIP",1,C90="Aborted",3)} -> 3 | C90: =+Y90 -> Aborted | D90: Inbound | E90: Pitch in the bakery sector in Brazil | F90: Condere - GMAP | G90: Brasil | H90: Sell | J90: Food | K90: Shelf stable breads, cakes, and other gluten free, lactose free, vegan products | L90: EBITDA $2M | N90: ASC | O90: LUS | S90: =+TODAY()-V90 -> 214 | T90: =+TODAY()-X90 -> 211 | V90: 45450 | W90: 45450 | X90: 45453 | Y90: Aborted
B91: {=+_xlfn.IFS(C91="Tracking",2,C91="WIP",1,C91="Aborted",3)} -> 3 | C91: =+Y91 -> Aborted | D91: Inbound | E91: Pj WORLDWIDE | F91: BGLCO - GMAP | G91: US | H91: Sell | J91: Food | K91: High-quality branded and private label food products | L91: Rev: $145M; Ebitda $12m | S91: =+TODAY()-V91 -> 207 | T91: =+TODAY()-X91 -> 207 | V91: 45457 | W91: 45457 | X91: 45457 | Y91: Aborted
B92: {=+_xlfn.IFS(C92="Tracking",2,C92="WIP",1,C92="Aborted",3)} -> 3 | C92: =+Y92 -> Aborted | D92: Inbound | E92: Pj HELIOS | F92: Cooper Parry - REACH | G92: UK | H92: Sell | J92: Industrial | K92: Warehouse – industrial racking | L92: Ricavi: £20M, EBITDA £3M | N92: FCA | O92: LUS | S92: =+TODAY()-V92 -> 224 | T92: =+TODAY()-X92 -> 224 | V92: 45440 | W92: 45440 | X92: 45440 | Y92: Aborted
B93: {=+_xlfn.IFS(C93="Tracking",2,C93="WIP",1,C93="Aborted",3)} -> 3 | C93: =+Y93 -> Aborted | D93: Inbound | E93: Pitch in the cure and care institute for sleeping disorders in Netherlands | F93: JBR - GMAP | G93: Netherlans | H93: Sell | J93: Healthcare | K93: Dutch cure and care institute for sleeping disorders | L93: EBITDA: €3/4M | O93: LUS | S93: =+TODAY()-V93 -> 210 | T93: =+TODAY()-X93 -> 210 | V93: 45454 | W93: 45454 | X93: 45454 | Y93: Aborted
B94: {=+_xlfn.IFS(C94="Tracking",2,C94="WIP",1,C94="Aborted",3)} -> 3 | C94: =+Y94 -> Aborted | D94: Inbound | E94: Pj POZUELO | F94: Anquor Corporate Finance - GMAP | G94: Spain | H94: Sell | J94: Healthcare | K94: Production and marketing of animal health products | L94: Ricavi: €28M, EBITDA €1,5M | N94: ASC | O94: LUS | S94: =+TODAY()-V94 -> 239 | T94: =+TODAY()-X94 -> 237 | V94: 45425 | W94: 45425 | X94: 45427 | Y94: Aborted
B95: {=+_xlfn.IFS(C95="Tracking",2,C95="WIP",1,C95="Aborted",3)} -> 3 | C95: =+Y95 -> Aborted | D95: Inbound | E95: Pj EDGE | F95: Anquor Corporate Finance - GMAP | G95: Spain | H95: Sell | J95: Industrial | K95: Development and manufacturing of composite Resin Transfer Moulding (RTM) structures for aeronautics sector | L95: Ricavi: €14M, EBITDA €1,7M | N95: FCA | O95: LUS | S95: =+TODAY()-V95 -> 224 | T95: =+TODAY()-X95 -> 224 | V95: 45440 | W95: 45440 | X95: 45440 | Y95: Aborted
B96: {=+_xlfn.IFS(C96="Tracking",2,C96="WIP",1,C96="Aborted",3)} -> 3 | C96: =+Y96 -> Aborted | D96: Inbound | E96: Pj DELIGHT | F96: IOM - GMAP | G96: Germany | H96: Sell | J96: Food | K96: Distributor of confectionaries, snacks, and beverages | L96: Ricavi: €93.6M, EBITDA €9.1M | N96: FCA | O96: LUS | S96: =+TODAY()-V96 -> 265 | T96: =+TODAY()-X96 -> 218 | V96: 45399 | W96: 45399 | X96: 45446 | Y96: Aborted
B97: {=+_xlfn.IFS(C97="Tracking",2,C97="WIP",1,C97="Aborted",3)} -> 3 | C97: =+Y97 -> Aborted | D97: Inbound | E97: Parisot (impianti di produzione truciolato) | F97: Financière de Courcelles - GMAP | G97: France | H97: Sell | J97: Industrial | K97: Impianti di produzione truciolato | L97: Rev: c. €130M | N97: LOM | O97: LUS | S97: =+TODAY()-V97 -> 250 | T97: =+TODAY()-X97 -> 210 | V97: 45414 | W97: 45414 | X97: 45454 | Y97: Aborted
B98: {=+_xlfn.IFS(C98="Tracking",2,C98="WIP",1,C98="Aborted",3)} -> 3 | C98: =+Y98 -> Aborted | D98: Inbound | E98: Sitti Spa | F98: Financière de Courcelles - GMAP | G98: Italy | H98: Sell | J98: IT | K98: Hardware and software services to airports, aimed at managing the airport–aircraft voice communication link | L98: Ricavi: €20,8M, EBITDA €2,9M | N98: ASC | O98: LUS | S98: =+TODAY()-V98 -> 309 | T98: =+TODAY()-X98 -> 300 | V98: 45355 | W98: 45358 | X98: 45364 | Y98: Aborted
B99: {=+_xlfn.IFS(C99="Tracking",2,C99="WIP",1,C99="Aborted",3)} -> 3 | C99: =+Y99 -> Aborted | D99: Inbound | E99: Pitch photonics optronics optics | F99: Financière de Courcelles - GMAP | G99: France | H99: Sell | J99: - | K99: - | L99: - | N99: ASC | S99: =+TODAY()-V99 -> 225 | T99: =+TODAY()-X99 -> 225 | V99: 45439 | W99: 45439 | X99: 45439 | Y99: Aborted
B100: {=+_xlfn.IFS(C100="Tracking",2,C100="WIP",1,C100="Aborted",3)} -> 3 | C100: =+Y100 -> Aborted | D100: Inbound | E100: Darryl Lea Chocolate | F100: Nash Advisory | G100: Australia | H100: Buy | J100: Food | K100: Chocolate/confectionary snacking business | L100: Rev: c. AUD500M | N100: ASC | S100: =+TODAY()-V100 -> 273 | T100: =+TODAY()-X100 -> 273 | V100: 45391 | W100: 45391 | X100: 45391 | Y100: Aborted
...

Sheet Fondi_PE
C1: =+COUNTA(C3:C121)-1 -> 117 | M1: x | W1: =+COUNTA(W3:W121)-1 -> 5 | X1: =+COUNTA(X3:X121)-1 -> 5 | Y1: =+COUNTA(Y3:Y121)-1 -> 12 | Z1: =+COUNTA(Z3:Z121)-1 -> 11 | AA1: =+COUNTA(AA3:AA121)-1 -> 6 | AB1: =+COUNTA(AB3:AB121)-1 -> 4 | AC1: =+COUNTA(AC3:AC121)-1 -> 2 | AD1: =+COUNTA(AD3:AD121)-1 -> 3 | ... BT1: =+COUNTA(BT3:BT121)-1 -> 0 | BY1: |
B2: Cnt | C2: SGR / Società di investimento | D2: Sito WEB | E2: Tipologia | F2: Nome Fondo | G2: Raccolta | H2: Anno Raccolta | I2: Sweet Spot Ticket | J2: Sweet Spot EBITDA | K2: Focus settori | L2: Partner ns riferimento | M2: x | N2: Relazione @BCA | O2: Staff_1 | P2: Staff_2 | Q2: Note | S2: #Eventi | T2: Latest Event | U2: Days since | W2: 45313 | X2: =+W2+7 -> 45320 | Y2: =+X2+7 -> 45327 | Z2: =+Y2+7 -> 45334 | AA2: =+Z2+7 -> 45341 | AB2: =+AA2+7 -> 45348 | AC2: =+AB2+7 -> 45355 | AD2: =+AC2+7 -> 45362 | AE2: =+AD2+7 -> 45369 | ... BW2: =+BV2+7 -> 45677 | BX2: INSERIRE PRIMA DI QUESTA COLONNA | BY2: |
C3: 21 Invest | E3: Fondo PE | G3: 320 | H3: 2023 | I3: 20-50M€ | K3: Generalista | L3: Andrea Mazzuccato | N3: ASC | Q3: Con ROS | S3: =+COUNTA(W3:BX3) -> 6 | T3: 45540 | U3: =IF(T3>0,IF(TODAY()>T3,TODAY()-T3,""),"") -> 124 | Y3: SILFA | Z3: SPICA | AM3: FACE | BC3: Meeting | BG3: GPS, Zaini | BJ3: Call | BY3: |
C4: 21 Invest - Healthcare | E4: Fondo PE | G4: 150 | H4: 2024 | I4: 10 - 15M€ | K4: Healthcare | L4: Fabio Parisi | N4: ASC | O4: PAD | S4: =+COUNTA(W4:BX4) -> 7 | T4: 45630 | U4: =IF(T4>0,IF(TODAY()>T4,TODAY()-T4,""),"") -> 34 | Y4: SILFA | Z4: SPICA | AM4: FACE | BC4: Meeting | BG4: GPS, Zaini | BJ4: Call | BP4: Wimed | BY4: |
C5: 360 Capital | E5: Fondo VC | L5: Cesare Maifredi | N5: ASC | O5: RIM | Q5: Tramite Davide Corrias (Allianz) | S5: =+COUNTA(W5:BX5) -> 1 | T5: 45643 | U5: =IF(T5>0,IF(TODAY()>T5,TODAY()-T5,""),"") -> 21 | BV5: Meeting | BY5: |
A6: A | C6: Accel | E6: Fondo VC | L6: Luca Bocchio | N6: FCA | O6: ASP | S6: =+COUNTA(W6:BX6) -> 1 | T6: 45502 | U6: =IF(T6>0,IF(TODAY()>T6,TODAY()-T6,""),"") -> 162 | AX6: PMC | BY6: |
C7: A-Green | E7: Club Deal | L7: Andrea Rossi | N7: FCA | S7: =+COUNTA(W7:BX7) -> 0 | U7: =IF(T7>0,IF(TODAY()>T7,TODAY()-T7,""),"") | BY7: |
C8: Aksìa | D8: www.aksiagroup.com/it | E8: Fondo PE | F8: Aksia Capital V | G8: 275 | H8: 2022 | I8: 10 - 20M€ | K8: Generalista | L8: Marco Rayneri | M8: x | N8: ASC | O8: PAD | S8: =+COUNTA(W8:BX8) -> 1 | T8: 45432 | U8: =IF(T8>0,IF(TODAY()>T8,TODAY()-T8,""),"") -> 232 | AN8: Myes | BY8: |
C9: Alcedo | E9: Fondo PE | K9: Generalista | L9: Alessandro Zanet | N9: ASC | O9: RIM | Q9: ASC con Nalon | S9: =+COUNTA(W9:BX9) -> 4 | T9: 45436 | U9: =IF(T9>0,IF(TODAY()>T9,TODAY()-T9,""),"") -> 228 | AB9: Fusto | AN9: Sapori Veri; Myes | BF9: Mars | BK9: Call | BY9: |
C10: Algebris | E10: Fondo PE | I10: 10 - 20M€ | L10: Stefano Sostero | M10: x | N10: ASC | S10: =+COUNTA(W10:BX10) -> 3 | T10: 45327 | U10: =IF(T10>0,IF(TODAY()>T10,TODAY()-T10,""),"") -> 337 | Y10: SILFA | Z10: SPICA | BF10: Mars | BY10: |
C11: Alpha Generator Capital | E11: Search Fund | K11: Generalista | L11: Federico Di Benedetto | N11: ASC | O11: GIM | P11: GID | S11: =+COUNTA(W11:BX11) -> 1 | T11: 45614 | U11: =IF(T11>0,IF(TODAY()>T11,TODAY()-T11,""),"") -> 50 | BN11: Call | BY11: |
C12: Alto Partners | E12: Fondo PE | G12: 270 | H12: 2023 | I12: 20-50M€ | K12: Generalista | L12: Gianmarco Gandolfi | N12: LOM | S12: =+COUNTA(W12:BX12) -> 7 | T12: 45432 | U12: =IF(T12>0,IF(TODAY()>T12,TODAY()-T12,""),"") -> 232 | W12: Fra' Diavolo | AL12: Fusto | AN12: Myes | AR12: FUA | AS12: Olimpia | BC12: Meeting | BK12: Target Fra Diavolo Polonia | BY12: |
C13: Ambienta | D13: https://ambientasgr.com/ | E13: Fondo PE | F13: Ambienta SGR | G13: 1550 | H13: 2022 | I13: 10 - 20M€ | K13: Sostenibilità | L13: Gianfranco Beraudo Francesco Lodrini | M13: x | N13: ASC | S13: =+COUNTA(W13:BX13) -> 2 | T13: 45544 | U13: =IF(T13>0,IF(TODAY()>T13,TODAY()-T13,""),"") -> 120 | AD13: meeting | BD13: Kilometro Verde | BY13: |
C14: Amundi SGR | E14: Fondo PE | G14: 100 | H14: 2023 | I14: 5 - 10M€ | K14: Generalista | L14: Viviana Gasparrini | M14: x | N14: ASC | Q14: Minoranze "growth" o in co-investimento su LBOs | S14: =+COUNTA(W14:BX14) -> 5 | T14: 45449 | U14: =IF(T14>0,IF(TODAY()>T14,TODAY()-T14,""),"") -> 215 | AO14: Fusto | AP14: Sapori Veri | BD14: Olimpia | BI14: Mars | BM14: Meeting | BY14: |
C15: ANDERA Capital | E15: Fondo PE | F15: V Fondo Mid-cap | G15: 650 | I15: 20-50M€ | K15: Generalista | L15: Francesco Gonzaga | N15: ASC | Q15: Sia Min sia Magg | S15: =+COUNTA(W15:BX15) -> 1 | T15: 45588 | U15: =IF(T15>0,IF(TODAY()>T15,TODAY()-T15,""),"") -> 76 | BJ15: Forum Mergermarket | BY15: |
C16: Anemos Private Investments (Gruppo Samhita) | D16: https://samhitainvestments.com/about-us-anemos/ | E16: Fondo PE | K16: Generalista | L16: Martina Di Gioia | N16: ASC | O16: GIM | S16: =+COUNTA(W16:BX16) -> 1 | T16: 45590 | U16: =IF(T16>0,IF(TODAY()>T16,TODAY()-T16,""),"") -> 74 | BJ16: Incontro | BY16: |
C17: Anthilia | E17: Private Debt | K17: Generalista | L17: Tobia Dian | O17: RIM | S17: =+COUNTA(W17:BX17) -> 1 | T17: 45356 | U17: =IF(T17>0,IF(TODAY()>T17,TODAY()-T17,""),"") -> 308 | AJ17: Fusto + Sapori Veri | BY17: |
C18: Arcadia | E18: Fondo PE | G18: 100M€ | H18: 2024 | I18: 5 - 20M€ | J18: 4 - 8M€ | K18: Generalista | L18: Giovanni Barbujani | N18: ASC | S18: =+COUNTA(W18:BX18) -> 2 | T18: 45562 | U18: =IF(T18>0,IF(TODAY()>T18,TODAY()-T18,""),"") -> 102 | AU18: Call | BE18: Sapori Veri | BY18: |
C19: Archimed | E19: Fondo PE | F19: Healthcare | L19: Igor Petricca | N19: FCA | S19: =+COUNTA(W19:BX19) -> 2 | T19: 45369 | U19: =IF(T19>0,IF(TODAY()>T19,TODAY()-T19,""),"") -> 295 | AA19: Meeting | AE19: Vismederi + Theras | BY19: |
C20: Argos Wityu | D20: https://argos.wityu.fund/it/ | E20: Fondo PE | F20: Euroknights VII | G20: 650 | H20: 2021 | K20: Generalista | L20: Lucio Ranaudo | M20: xx | N20: ASC | O20: RIM | P20: GID | S20: =+COUNTA(W20:BX20) -> 4 | T20: 45478 | U20: =IF(T20>0,IF(TODAY()>T20,TODAY()-T20,""),"") -> 186 | X20: Elogy | Y20: SILFA | Z20: SPICA | AU20: Meeting | BY20: |
C21: Armira | D21: https://www.armira.de/en/ | E21: Inv Holding | I21: >50M€ | K21: Healthcare&Technology | L21: Leopold Walde | N21: FCA | S21: =+COUNTA(W21:BX21) -> 6 | T21: 45404 | U21: =IF(T21>0,IF(TODAY()>T21,TODAY()-T21,""),"") -> 260 | AD21: Meeting | AI21: Meeting | AJ21: Meeting | AQ21: Elmec Informatica | AT21: Elmec Informatica | BD21: Elmec Informatica - visit | BY21: |
C22: Atlas Partners | E22: Search Fund | L22: Stefano Carpano | N22: ASC | O22: PAD | S22: =+COUNTA(W22:BX22) -> 2 | T22: 45405 | U22: =IF(T22>0,IF(TODAY()>T22,TODAY()-T22,""),"") -> 259 | BH22: Bitta | BJ22: Edera | BY22: |
C23: Auctus | E23: Fondo PE | L23: Marco Bortot | N23: FCA | S23: =+COUNTA(W23:BX23) -> 3 | T23: 45406 | U23: =IF(T23>0,IF(TODAY()>T23,TODAY()-T23,""),"") -> 258 | Y23: Next HS Spica Silfa | Z23: SILFA | BF23: Wave, Maestro, Pixel (meeting) | BY23: |
C24: Augens | E24: Inv Holding | I24: 20-50M€ | K24: Generalista | L24: Massimo Puccio - Marco Mantica | M24: x | N24: ASC | Q24: Cercano cluster come HOFI | S24: =+COUNTA(W24:BX24) -> 2 | T24: 45434 | U24: =IF(T24>0,IF(TODAY()>T24,TODAY()-T24,""),"") -> 230 | W24: Call | AN24: Myes | BY24: |
C25: Aurelius | D25: https://www.aurelius-group.com/ | E25: Inv Holding | G25: 2.000 M€ | I25: >50M€ | J25: n/a | K25: Industrial | L25: Andrea Motori | N25: FCA | Q25: Investimenti in aziende o assets non performanti | S25: =+COUNTA(W25:BX25) -> 3 | T25: 45418 | U25: =IF(T25>0,IF(TODAY()>T25,TODAY()-T25,""),"") -> 246 | AK25: Call | AL25: Gruppo Bedeschi | AP25: Call | BY25: |
C26: Azimut Libera Impresa | E26: Fondo PE | N26: RIM | S26: =+COUNTA(W26:BX26) -> 2 | T26: 45414 | U26: =IF(T26>0,IF(TODAY()>T26,TODAY()-T26,""),"") -> 250 | AK26: Fusto | AT26: Fusto | BY26: |
A27: B | C27: B.group | E27: Inv Holding | L27: Orio Pontiggia | N27: FCA | S27: =+COUNTA(W27:BX27) -> 2 | T27: 45439 | U27: =IF(T27>0,IF(TODAY()>T27,TODAY()-T27,""),"") -> 225 | AO27: Novatech srl | BF27: Mars | BY27: |
C28: BIC | E28: Fondo PE | N28: ASC | S28: =+COUNTA(W28:BX28) -> 1 | T28: 45474 | U28: =IF(T28>0,IF(TODAY()>T28,TODAY()-T28,""),"") -> 190 | AT28: Fusto | BY28: |
C29: BNP Equity Investments | E29: Fondo PE | L29: Langella Lorenzo | N29: RIM | S29: =+COUNTA(W29:BX29) -> 1 | T29: 45560 | U29: =IF(T29>0,IF(TODAY()>T29,TODAY()-T29,""),"") -> 104 | BF29: Meeting | BY29: |
C30: Bravo Capital | E30: Fondo PE | L30: Giovanni Saccaggi | N30: LOM | O30: LUS | P30: GID | S30: =+COUNTA(W30:BX30) -> 1 | T30: 45442 | U30: =IF(T30>0,IF(TODAY()>T30,TODAY()-T30,""),"") -> 222 | AN30: Myes | BY30: |
C31: Bregal | N31: ROS | S31: =+COUNTA(W31:BX31) -> 1 | T31: 45467 | U31: =IF(T31>0,IF(TODAY()>T31,TODAY()-T31,""),"") -> 197 | AS31: Meeting | BY31: |
A32: C | C32: Calibrium | E32: Family Office | N32: FCA | S32: =+COUNTA(W32:BX32) -> 1 | T32: 45455 | U32: =IF(T32>0,IF(TODAY()>T32,TODAY()-T32,""),"") -> 209 | Z32: Italtherm | BY32: |
C33: Capza | E33: Fondo PE | L33: Thibault Chatagnon | N33: LOM | O33: LUS | S33: =+COUNTA(W33:BX33) -> 1 | U33: =IF(T33>0,IF(TODAY()>T33,TODAY()-T33,""),"") | BJ33: Edera | BY33: |
C34: CGS | E34: Fondo PE | K34: Generalista | L34: Thierry Biggoer | N34: ASC | O34: RIM | P34: PAD | S34: =+COUNTA(W34:BX34) -> 2 | T34: 45376 | U34: =IF(T34>0,IF(TODAY()>T34,TODAY()-T34,""),"") -> 288 | Y34: Cavanna Spica | AF34: Fusto | BY34: |
C35: Certina Group | E35: Inv Holding | I35: 10 - 20M€ | K35: Special Situations | L35: Holger Schmidt - Giuseppe Grizzo | N35: FCA | S35: =+COUNTA(W35:BX35) -> 1 | T35: 45630 | U35: =IF(T35>0,IF(TODAY()>T35,TODAY()-T35,""),"") -> 34 | BQ35: Call
C36: Clessidra PE | E36: Fondo PE | I36: 10 - 20M€ | K36: Generalista | L36: Giulio Torregrossa | N36: ASC | S36: =+COUNTA(W36:BX36) -> 1 | T36: 45322 | U36: =IF(T36>0,IF(TODAY()>T36,TODAY()-T36,""),"") -> 342 | Y36: SPICA | BY36: |
C37: Clessidra_Private_Debt | E37: Fondo PE | L37: Roberto Ippolito | N37: FCA | Q37: Ebitda>7M da ultimo bilancio | S37: =+COUNTA(W37:BX37) -> 4 | T37: 45432 | U37: =IF(T37>0,IF(TODAY()>T37,TODAY()-T37,""),"") -> 232 | AI37: Sapori Veri + Fusto | AT37: Call | BE37: Call | BG37: Mars | BY37: |
C38: Consilium | E38: Fondo PE | L38: Roberto De Rossi | S38: =+COUNTA(W38:BX38) -> 2 | T38: 45443 | U38: =IF(T38>0,IF(TODAY()>T38,TODAY()-T38,""),"") -> 221 | AO38: Evento | BI38: Meeting | BY38: |
C39: CRÉDIT MUTUEL EQUITY | E39: Fondo PE | F39: CM-E | I39: 5 - 20M€ | K39: Generalista | L39: Francesco Liistro | N39: ASC | O39: PAD | Q39: Minoranze "growth" o in co-investimento su LBOs | S39: =+COUNTA(W39:BX39) -> 3 | T39: 45635 | U39: =IF(T39>0,IF(TODAY()>T39,TODAY()-T39,""),"") -> 29 | AU39: Meeting | BI39: Meeting | BQ39: Pj Moon Pj Nero | BY39: |
C40: Cronos Capital Partners | E40: Fondo PE | K40: Generalista | N40: ASC | S40: =+COUNTA(W40:BX40) -> 1 | T40: 45635 | U40: =IF(T40>0,IF(TODAY()>T40,TODAY()-T40,""),"") -> 29 | BQ40: Pj Nero - Call | BY40: |
A41: D | C41: DBAG | E41: Fondo PE | K41: Generalista | N41: ASC | O41: RIM | P41: PAD | S41: =+COUNTA(W41:BX41) -> 2 | T41: 45362 | U41: =IF(T41>0,IF(TODAY()>T41,TODAY()-T41,""),"") -> 302 | AA41: SILFA | AD41: Spica | BY41: |
C42: Dea Capital - Taste of Italy 2 | E42: Fondo PE | L42: Stefano Caspani | N42: FCA | S42: =+COUNTA(W42:BX42) -> 1 | U42: =IF(T42>0,IF(TODAY()>T42,TODAY()-T42,""),"") | AN42: Myes | BY42: |
C43: Dea Capital - XXX | E43: Fondo PE | F43: DeA Capital Alternative Funds | L43: Giuliano Palazzo | N43: ASC | S43: =+COUNTA(W43:BX43) -> 3 | U43: =IF(T43>0,IF(TODAY()>T43,TODAY()-T43,""),"") | AJ43: Fusto | BI43: Mars | BK43: Incontro | BY43: |
C44: DUBAG | E44: Fondo PE | K44: Special Situations | L44: Emanuel Cattanei | N44: ASC | O44: RIM | P44: PAD | S44: =+COUNTA(W44:BX44) -> 1 | T44: 45356 | U44: =IF(T44>0,IF(TODAY()>T44,TODAY()-T44,""),"") -> 308 | AA44: Siman | BY44: |
A45: E | C45: Entangled Capital | E45: Fondo PE | N45: LOM | O45: PAD | S45: =+COUNTA(W45:BX45) -> 2 | U45: =IF(T45>0,IF(TODAY()>T45,TODAY()-T45,""),"") | W45: Finestre | BD45: meeting | BY45: |
C46: Eolo Capital | E46: Search Fund | L46: Antonio Garufi | N46: PAD | S46: =+COUNTA(W46:BX46) -> 1 | T46: 45618 | U46: =IF(T46>0,IF(TODAY()>T46,TODAY()-T46,""),"") -> 46 | BO46: Intro | BY46: |
C47: Equilybra Capital Partners | D47: www.equilybrapartners.it | E47: Inv Holding | G47: 80 | H47: n/a | I47: 5 - 10M€ | K47: Generalista | L47: Matteo Gatti | M47: x | N47: ASC | O47: PAD | S47: =+COUNTA(W47:BX47) -> 2 | T47: 45334 | U47: =IF(T47>0,IF(TODAY()>T47,TODAY()-T47,""),"") -> 330 | Z47: Xanitalia | BD47: Kilometro verde | BY47: |
C48: Equinox | E48: Fondo PE | L48: Andrea Bovone | N48: LOM | O48: LUS | S48: =+COUNTA(W48:BX48) -> 1 | T48: 45435 | U48: =IF(T48>0,IF(TODAY()>T48,TODAY()-T48,""),"") -> 229 | AN48: Myes | BY48: |
C49: Equita Smart Capital | E49: Fondo PE | L49: Matteo Morelli | N49: ASC | S49: =+COUNTA(W49:BX49) -> 2 | T49: 45559 | U49: =IF(T49>0,IF(TODAY()>T49,TODAY()-T49,""),"") -> 105 | BF49: Call | BJ49: Forum Mergermarket | BY49: |
C50: Equiter | E50: Fondo PE | N50: LOM | S50: =+COUNTA(W50:BX50) -> 1 | T50: 45323 | U50: =IF(T50>0,IF(TODAY()>T50,TODAY()-T50,""),"") -> 341 | BI50: Primo contatto | BY50: |
C51: Ethica Investments | E51: Club Deal | J51: 4 - 8M€ | K51: Generalista | L51: Nicola Di Biase | N51: ASC | S51: =+COUNTA(W51:BX51) -> 2 | T51: 45323 | U51: =IF(T51>0,IF(TODAY()>T51,TODAY()-T51,""),"") -> 341 | X51: Fava Bibite | Y51: Mariani Aromi | BY51: |
C52: Eulero Capital | E52: Inv Holding | N52: LOM | O52: LUS | S52: =+COUNTA(W52:BX52) -> 1 | T52: 45434 | U52: =IF(T52>0,IF(TODAY()>T52,TODAY()-T52,""),"") -> 230 | AN52: Myes | BY52: |
A53: F | C53: F&P | E53: Fondo PE | K53: Generalista | L53: Maurizio Perroni | N53: ASC | O53: RIM | S53: =+COUNTA(W53:BX53) -> 1 | T53: 45444 | U53: =IF(T53>0,IF(TODAY()>T53,TODAY()-T53,""),"") -> 220 | AL53: Fusto | BY53: |
C54: Fidelium | E54: Fondo PE | G54: 150 | H54: 2024 | L54: Riccardo Wagner | N54: ASC | O54: RIM | P54: PAD | S54: =+COUNTA(W54:BX54) -> 1 | T54: 45601 | U54: =IF(T54>0,IF(TODAY()>T54,TODAY()-T54,""),"") -> 63 | BM54: Call | BY54: |
C55: FIEE | E55: Fondo PE | G55: 200 | H55: 2024 | K55: Efficienza Energetica | L55: Gianluca Caporaso | N55: ASC | O55: PAD | S55: =+COUNTA(W55:BX55) -> 2 | T55: 45544 | U55: =IF(T55>0,IF(TODAY()>T55,TODAY()-T55,""),"") -> 120 | BD55: Olimpia | BE55: Sunrise | BY55: |
C56: First Capital | E56: Fondo PE | K56: Pre-IPO | N56: ROS | O56: PAD | S56: =+COUNTA(W56:BX56) -> 2 | U56: =IF(T56>0,IF(TODAY()>T56,TODAY()-T56,""),"") | AL56: Fusto | BD56: Kilometro Verde | BY56: |
C57: Fondo Italiano di Investimento | E57: Fondo PE | G57: 400 | H57: 2020 | I57: 20-50M€ | J57: 10 - 20M€ | K57: Generalista | L57: Filippo Monti | N57: ASC | O57: RIM | Q57: Meccatronica, Turismo (HNH), Filiera moda BSB | S57: =+COUNTA(W57:BX57) -> 3 | T57: 45327 | U57: =IF(T57>0,IF(TODAY()>T57,TODAY()-T57,""),"") -> 337 | Y57: SILFA | Z57: SPICA | BN57: Call | BY57: |
C58: Fondo Italiano di Investimento FIAF | E58: Fondo PE | G58: 250 | H58: 2020 | I58: 10 - 20M€ | K58: Agro | L58: Andrea Reale | N58: GIM | O58: PAD | S58: =+COUNTA(W58:BX58) -> 1 | T58: 45583 | U58: =IF(T58>0,IF(TODAY()>T58,TODAY()-T58,""),"") -> 81 | BJ58: Call conoscitiva - Project Mars | BY58: |
C59: Friulia | E59: Fondo PE | K59: Generalista | L59: Andrea Fioravanti | N59: ASC | Q59: Regionale solo FVG | S59: =+COUNTA(W59:BX59) -> 2 | T59: 45572 | U59: =IF(T59>0,IF(TODAY()>T59,TODAY()-T59,""),"") -> 92 | BG59: Call | BJ59: Forum Mergermarket | BY59: |
C60: Futura SGR | E60: Fondo VC | K60: Tech | L60: Gabriele Benedetto | N60: FCA | O60: ASP | S60: =+COUNTA(W60:BX60) -> 1 | T60: 45506 | U60: =IF(T60>0,IF(TODAY()>T60,TODAY()-T60,""),"") -> 158 | AX60: PMC | BY60: |
A61: G | C61: Gradiente | E61: Fondo PE | G61: 140 | H61: 2022 | I61: 10 - 15M€ | K61: Generalista | L61: Fabrizio Grasso | N61: ASC | O61: RIM | S61: =+COUNTA(W61:BX61) -> 2 | T61: 45327 | U61: =IF(T61>0,IF(TODAY()>T61,TODAY()-T61,""),"") -> 337 | Y61: SILFA | BM61: Call | BY61: |
C62: Green Arrow | E62: Private Debt | K62: Generalista | L62: Marco Meda | N62: ROS | O62: PAD | S62: =+COUNTA(W62:BX62) -> 2 | T62: 45582 | U62: =IF(T62>0,IF(TODAY()>T62,TODAY()-T62,""),"") -> 82 | BI62: Mars | BJ62: Call | BY62: |
C63: GSC-Rigeto | E63: Fondo PE | K63: Generalista | L63: Lorenzo Nardellotto | N63: ASC | O63: PAD | S63: =+COUNTA(W63:BX63) -> 3 | T63: 45460 | U63: =IF(T63>0,IF(TODAY()>T63,TODAY()-T63,""),"") -> 204 | AR63: 1° contatto | BD63: Olimpia | BF63: Wave, Mars, ILC Lube | BY63: |
A64: H | C64: H.I.G. Europe | E64: Fondo PE | N64: LOM | O64: PAD | S64: =+COUNTA(W64:BX64) -> 5 | T64: 45588 | U64: =IF(T64>0,IF(TODAY()>T64,TODAY()-T64,""),"") -> 76 | X64: Next HS | Z64: Intersistemi | BJ64: Forum Mergermarket | BM64: Meeting | BQ64: Add-on Berardi Group e Polygon | BY64: |
C65: Hyle Capital Partners (FFF) | D65: www.financeforfood.it | E65: Fondo PE | F65: Finance for Food One | G65: 80 | H65: 2019 | I65: 5 - 10M€ | K65: Food | L65: Matteo Chieregato | M65: x | N65: ASC | O65: LUS | S65: =+COUNTA(W65:BX65) -> 3 | T65: 45397 | U65: =IF(T65>0,IF(TODAY()>T65,TODAY()-T65,""),"") -> 267 | AI65: Sapori Veri e Fusto | BN65: Guaresi per BSF | BP65: Meeting | BY65: |
A66: I | C66: Ibla Capital | E66: Fondo PE | N66: ASC | O66: RIM | P66: GIM | S66: =+COUNTA(W66:BX66) -> 2 | T66: 45553 | U66: =IF(T66>0,IF(TODAY()>T66,TODAY()-T66,""),"") -> 111 | BE66: Cavanna | BF66: Erregierre | BY66: |
C67: ICG | D67: https://www.icgam.com/ | E67: Fondo PE | M67: x | N67: ASC | S67: =+COUNTA(W67:BX67) -> 0 | U67: =IF(T67>0,IF(TODAY()>T67,TODAY()-T67,""),"") | BY67: |
C68: IGI | E68: Fondo PE | I68: 5 - 20M€ | N68: ASC | O68: LUS | S68: =+COUNTA(W68:BX68) -> 1 | U68: =IF(T68>0,IF(TODAY()>T68,TODAY()-T68,""),"") | BR68: Call | BY68: |
C69: Impact Partners | D69: https://www.impact-partners.com/it/ | E69: Fondo PE | I69: 5 - 20M€ | L69: Riccardo Allegra | N69: ASC | S69: =+COUNTA(W69:BX69) -> 5 | T69: 45583 | U69: =IF(T69>0,IF(TODAY()>T69,TODAY()-T69,""),"") -> 81 | BI69: Call | BJ69: Edera | BK69: Mars | BM69: Call | BP69: Meeting | BY69: |
C70: Investindustrial | E70: Fondo PE | F70: Investindustrial Growth | L70: Martino Gobbi | N70: FCA | S70: =+COUNTA(W70:BX70) -> 5 | U70: =IF(T70>0,IF(TODAY()>T70,TODAY()-T70,""),"") | AB70: Fusto | AJ70: Meeting | AP70: PBL Srl | AR70: Meeting in CARIBA | AT70: Meeting con CURTI | BY70: |
A71: K | C71: Koinos | E71: Fondo PE | K71: Generalista | L71: Marco Morgese | N71: ASC | O71: PAD | S71: =+COUNTA(W71:BX71) -> 1 | T71: 45639 | U71: =IF(T71>0,IF(TODAY()>T71,TODAY()-T71,""),"") -> 25 | BQ71: Meeting | BY71: |
C72: KPS Capital Partners | E72: Fondo PE | I72: >20M€ | K72: Generalista | L72: Ryan Harrison | N72: ASC | O72: RIM | S72: =+COUNTA(W72:BX72) -> 5 | T72: 45555 | U72: =IF(T72>0,IF(TODAY()>T72,TODAY()-T72,""),"") -> 109 | Y72: SiderforgeRossi | Z72: Siman per Princess | AM72: FACE | AV72: Email a John Magliana | BE72: Pj Bitta | BY72: |
C73: KYIP | E73: Fondo PE | L73: Gianluca Losi | N73: LOM | O73: LUS | S73: =+COUNTA(W73:BX73) -> 2 | T73: 45590 | U73: =IF(T73>0,IF(TODAY()>T73,TODAY()-T73,""),"") -> 74 | BJ73: Edera | BN73: Call | BY73: |
C74: KYM | E74: Fondo PE | N74: LOM | O74: PAD | S74: =+COUNTA(W74:BX74) -> 1 | U74: =IF(T74>0,IF(TODAY()>T74,TODAY()-T74,""),"") | AS74: Agriges | BY74: |
A75: L | C75: LDUE | E75: Search Fund | L75: Niccolo Cavallaro | N75: LOM | O75: LUS | S75: =+COUNTA(W75:BX75) -> 2 | U75: =IF(T75>0,IF(TODAY()>T75,TODAY()-T75,""),"") | AQ75: Myes | BJ75: Edera | BY75: |
C76: Lian Group | E76: Fondo PE | L76: Matteo Cardarelli | N76: LUS | O76: LUS | S76: =+COUNTA(W76:BX76) -> 1 | U76: =IF(T76>0,IF(TODAY()>T76,TODAY()-T76,""),"") | BP76: Call | BY76: |
A77: M | C77: Metrika SGR | E77: Fondo PE | K77: Meccanica, detergenza | L77: Marco Giuseppini | O77: GIM | P77: RIM | S77: =+COUNTA(W77:BX77) -> 2 | T77: 45580 | U77: =IF(T77>0,IF(TODAY()>T77,TODAY()-T77,""),"") -> 84 | BJ77: Call | BM77: Lone Rider | BY77: |
C78: Mindful | E78: Fondo PE | L78: Lorenzo Stanca | N78: FCA | S78: =+COUNTA(W78:BX78) -> 0 | U78: =IF(T78>0,IF(TODAY()>T78,TODAY()-T78,""),"") | BY78: |
C79: Monforte Capital Partners | D79: https://www.monfortecp.com/ | E79: Fondo PE | M79: x | N79: LOM | O79: LUS | P79: GID | S79: =+COUNTA(W79:BX79) -> 2 | T79: 45594 | U79: =IF(T79>0,IF(TODAY()>T79,TODAY()-T79,""),"") -> 70 | BJ79: Edera | BK79: Call | BY79: |
C80: Montefiore | D80: https://montefiore.fr/en/ | E80: Fondo PE | F80: Montefiore Investment IV | G80: 1000 | H80: 2016 | I80: 20-50M€ | K80: Generalista (no manifatturiero) | L80: Marie Londero | M80: x | N80: ASC | O80: RIM | P80: GID | Q80: 6 settori di specializzazione: tech; B2C; B2B; Turismo & hospitality; Healthcare; immobiliare | S80: =+COUNTA(W80:BX80) -> 2 | T80: 45327 | U80: =IF(T80>0,IF(TODAY()>T80,TODAY()-T80,""),"") -> 337 | Y80: Panel_PE | AN80: Myes | BY80: |
C81: Motion Private Equity | D81: https://www.motionequitypartners.com/it/ | E81: Fondo PE | L81: Cedric Rays | M81: x | N81: LOM | O81: LUS | P81: GID | S81: =+COUNTA(W81:BX81) -> 1 | T81: 45449 | U81: =IF(T81>0,IF(TODAY()>T81,TODAY()-T81,""),"") -> 215 | AN81: Myes | BY81: |
A82: N | C82: NB Aurora | E82: Fondo PE | N82: LOM | O82: LUS | P82: GID | S82: =+COUNTA(W82:BX82) -> 3 | T82: 45546 | U82: =IF(T82>0,IF(TODAY()>T82,TODAY()-T82,""),"") -> 118 | AP82: SAFETY | AX82: Stewart | BD82: Target per Club del Sole | BY82: |
C83: NUO Capital | E83: Fondo PE | I83: >20M€ | K83: Angolo Cina | L83: Luca Bossi | N83: LOM | S83: =+COUNTA(W83:BX83) -> 1 | U83: =IF(T83>0,IF(TODAY()>T83,TODAY()-T83,""),"") | AQ83: FUA | BY83: |
A84: O | C84: Oltre Impact | E84: Fondo PE | F84: Oltre III | G84: 77 | H84: 2021 | I84: 5 - 10M€ | K84: Società ad impatto | L84: Raffaele Fedele | N84: LOM | O84: LUS | P84: GID | S84: =+COUNTA(W84:BX84) -> 1 | T84: 45448 | U84: =IF(T84>0,IF(TODAY()>T84,TODAY()-T84,""),"") -> 216 | AN84: Myes | BY84: |
C85: Orienta | E85: Club Deal | L85: Augusto Balestra | N85: FCA | S85: =+COUNTA(W85:BX85) -> 1 | T85: 45352 | U85: =IF(T85>0,IF(TODAY()>T85,TODAY()-T85,""),"") -> 312 | AQ85: Cristallina per Lauretana | BY85: |
A86: P | C86: Paragon | E86: Fondo PE | K86: Generalista | L86: Stefano Tatarella | N86: ASC | O86: RIM | P86: PAD | S86: =+COUNTA(W86:BX86) -> 1 | T86: 45356 | U86: =IF(T86>0,IF(TODAY()>T86,TODAY()-T86,""),"") -> 308 | AE86: Spica Fusto | BY86: |
C87: Peak35 | E87: Search Fund | K87: Generalista | L87: Mattia Ambrosini | N87: LOM | O87: LUS | S87: =+COUNTA(W87:BX87) -> 2 | U87: =IF(T87>0,IF(TODAY()>T87,TODAY()-T87,""),"") | BN87: Edera | BQ87: Call | BY87: |
C88: PM Partners | E88: Fondo PE | N88: LOM | O88: PAD | Q88: ASC con Rainone | S88: =+COUNTA(W88:BX88) -> 5 | T88: 45352 | U88: =IF(T88>0,IF(TODAY()>T88,TODAY()-T88,""),"") -> 312 | W88: Finestre | Z88: Spica | AL88: Fusto | BB88: LABEL | BE88: Meeting | BY88: |
C89: Portobello | E89: Fondo PE | K89: Generalista | L89: Antonio Todisco | N89: ASC | O89: RIM | S89: =+COUNTA(W89:BX89) -> 1 | T89: 45439 | U89: =IF(T89>0,IF(TODAY()>T89,TODAY()-T89,""),"") -> 225 | AJ89: Fusto | BY89: |
C90: Pricoa | E90: Private Debt | K90: Generalista | L90: Giacomo Barone | O90: RIM | S90: =+COUNTA(W90:BX90) -> 1 | T90: 45439 | U90: =IF(T90>0,IF(TODAY()>T90,TODAY()-T90,""),"") -> 225 | AJ90: Fusto | BY90: |
C91: Primo Ventures | E91: Fondo PE | G91: 60 | H91: 2023 | K91: Pharma | L91: Emiliano Tonelli | M91: \ | N91: ASC | O91: PAD | S91: =+COUNTA(W91:BX91) -> 1 | T91: 45630 | U91: =IF(T91>0,IF(TODAY()>T91,TODAY()-T91,""),"") -> 34 | BP91: Wimed | BY91: |
C92: ProA Capital | E92: Fondo PE | G92: 500 | I92: >20M€ | K92: Generalista | L92: Vito Torciano | N92: LOM | O92: PAD | S92: =+COUNTA(W92:BX92) -> 8 | T92: 45385 | U92: =IF(T92>0,IF(TODAY()>T92,TODAY()-T92,""),"") -> 279 | W92: Finestre Next HS | X92: Pergole W Group | AC92: SILFA | AI92: Brustor | AN92: Myes | BE92: Mars | BH92: Meeting | BR92: Call | BY92: |
C93: Progressio | E93: Fondo PE | L93: Alessandro Petraccia | N93: FCA | S93: =+COUNTA(W93:BX93) -> 1 | U93: =IF(T93>0,IF(TODAY()>T93,TODAY()-T93,""),"") | AQ93: Fusto | BY93: |
C94: Providence | E94: Fondo PE | L94: Borja Cabrera | N94: LUS | S94: =+COUNTA(W94:BX94) -> 1 | U94: =IF(T94>0,IF(TODAY()>T94,TODAY()-T94,""),"") | BR94: PROA | BY94: |
A95: Q | C95: Quadrivio | E95: Fondo PE | F95: Silver Economy | L95: Dario di Iorio | N95: FCA | S95: =+COUNTA(W95:BX95) -> 1 | U95: =IF(T95>0,IF(TODAY()>T95,TODAY()-T95,""),"") | AA95: Meeting | BY95: |
C96: QuattroR (Small-Mid) | E96: Fondo PE | G96: 200 | H96: 2024 | I96: 10 - 20M€ | K96: Generalista | L96: Paolo Cavagnino | N96: ASC | S96: =+COUNTA(W96:BX96) -> 6 | T96: 45561 | U96: =IF(T96>0,IF(TODAY()>T96,TODAY()-T96,""),"") -> 103 | AK96: Meeting | AN96: Fagioli PFW | AU96: Lunch | BF96: Fagioli PFW | BG96: Crich | BP96: Pitch - Fagioli PFW | BY96: |
A97: R | C97: Raise | E97: Fondo PE | G97: 250 | H97: 2019 | I97: 10 - 15M€ | K97: Impact Investing | L97: Moritz Schumann | N97: ROS | O97: PAD | P97: GID | S97: =+COUNTA(W97:BX97) -> 1 | T97: 45562 | U97: =IF(T97>0,IF(TODAY()>T97,TODAY()-T97,""),"") -> 102 | BG97: Mars | BY97: |
C98: Red Fish Kapital | E98: Inv Holding | K98: Generalista | M98: x | N98: ROS | O98: PAD | S98: =+COUNTA(W98:BX98) -> 2 | T98: 45320 | U98: =IF(T98>0,IF(TODAY()>T98,TODAY()-T98,""),"") -> 344 | BE98: Mars | BK98: Call | BY98: |
C99: Ring Capital | E99: Fondo PE | L99: Sara De Benedetti | M99: x | N99: ROS | O99: PAD | S99: =+COUNTA(W99:BX99) -> 1 | T99: 45617 | U99: =IF(T99>0,IF(TODAY()>T99,TODAY()-T99,""),"") -> 47 | BN99: Call intro | BY99: |
C100: Riverside | D100: www.riversidecompany.com | E100: Fondo PE | F100: Riverside Europe Fund VI | G100: 465 | H100: 2019 | K100: Generalista | L100: Tomasz Glowacki | M100: x | N100: ASC | O100: PAD | S100: =+COUNTA(W100:BX100) -> 1 | T100: 45320 | U100: =IF(T100>0,IF(TODAY()>T100,TODAY()-T100,""),"") -> 344 | X100: BioDue | BY100: |
...

Sheet Cold Call BETA
G1: NON MODIFICARE CELLE CONTENTENTI FORMULE | AJ1: In Touch - Positive | AK1: =+COUNTIF($B:$B,1) -> 220 | AM1: Negative | AN1: =+COUNTIF($B:$B,4) -> 359 | AP1: Ongoing | AQ1: =+COUNTIF($B:$B,1) -> 220 | AS1: No Answer | AT1: =+COUNTIF($B:$B,3) -> 118
B2: Ordine | C2: Stream | D2: Status | E2: Nome | F2: Codename | G2: Provincia | H2: P.IVA | I2: ATECO 2007 | J2: Settore | K2: Attività | L2: Riferimento cliente | M2: Azionista_1 | N2: Azionista_2 | O2: Presidente | P2: AD | Q2: Pres.Col.Sind | S2: Cons | T2: Anno | U2: Sales | V2: Ebitda | W2: Ebitda(%) | X2: Ut. Netto | Y2: IFN | AA2: Fonte | AB2: Segnalatore EXT | AC2: Relazione @BCA | AD2: In Charge @BCA | AE2: Contact @BCA | AJ2: Days since idea | AK2: Days since latest progress | AM2: Idea | AN2: 1° Contatto | AO2: Re-call | AP2: 2° Re-call | AQ2: Contatto aperto | AR2: Outcome | AS2: Progress | AT2: |
A3: =+COUNTIF(D:D, "Pending") -> 157 | B3: {=+_xlfn.IFS(D3="In Touch - Positive",2,D3="Pending",1,D3="No Answer",4,D3="In Touch - Negative",3)} -> 1 | C3: La Doria | D3: =+AR3 -> Pending | E3: Valli Estensi s.r.l. | J3: Food | K3: Produzione preparati e succhi di frutta | S3: no | T3: 2023 | AA3: Cold Call | AC3: ASP | AJ3: =+TODAY()-AM3 -> 0 | AK3: =+TODAY()-AS3 -> 0 | AL3: =+IF(D3="Pending",COUNTA(AM3:AQ3)/5,D3) -> 0.2 | AM3: 45664 | AR3: Pending | AS3: 45664
B4: {=+_xlfn.IFS(D4="In Touch - Positive",2,D4="Pending",1,D4="No Answer",4,D4="In Touch - Negative",3)} -> 1 | C4: La Doria | D4: =+AR4 -> Pending | E4: Dolomiti Fruits s.r.l. | J4: Food | K4: Produzione preparati e succhi di frutta | S4: no | T4: 2023 | AA4: Cold Call | AC4: ASP | AJ4: =+TODAY()-AM4 -> 0 | AK4: =+TODAY()-AS4 -> 0 | AL4: =+IF(D4="Pending",COUNTA(AM4:AQ4)/5,D4) -> 0.2 | AM4: 45664 | AR4: Pending | AS4: 45664
B5: {=+_xlfn.IFS(D5="In Touch - Positive",2,D5="Pending",1,D5="No Answer",4,D5="In Touch - Negative",3)} -> 1 | C5: La Doria | D5: =+AR5 -> Pending | E5: Alpenfrucht s.r.l. | J5: Food | K5: Produzione preparati e succhi di frutta | S5: no | T5: 2023 | AA5: Cold Call | AC5: ASP | AJ5: =+TODAY()-AM5 -> 0 | AK5: =+TODAY()-AS5 -> 0 | AL5: =+IF(D5="Pending",COUNTA(AM5:AQ5)/5,D5) -> 0.2 | AM5: 45664 | AR5: Pending | AS5: 45664
B6: {=+_xlfn.IFS(D6="In Touch - Positive",2,D6="Pending",1,D6="No Answer",4,D6="In Touch - Negative",3)} -> 1 | C6: La Doria | D6: =+AR6 -> Pending | E6: Italfrutta s.r.l. | J6: Food | K6: Produzione preparati e succhi di frutta | S6: no | T6: 2023 | AA6: Cold Call | AC6: ASP | AJ6: =+TODAY()-AM6 -> 0 | AK6: =+TODAY()-AS6 -> 0 | AL6: =+IF(D6="Pending",COUNTA(AM6:AQ6)/5,D6) -> 0.2 | AM6: 45664 | AR6: Pending | AS6: 45664
B7: {=+_xlfn.IFS(D7="In Touch - Positive",2,D7="Pending",1,D7="No Answer",4,D7="In Touch - Negative",3)} -> 1 | C7: La Doria | D7: =+AR7 -> Pending | E7: Cirillo Group S.p.A. | J7: Food | K7: Produzione conserve, sottoli, sughi e preparati | S7: no | T7: 2023 | AA7: Cold Call | AC7: ASP | AJ7: =+TODAY()-AM7 -> 0 | AK7: =+TODAY()-AS7 -> 0 | AL7: =+IF(D7="Pending",COUNTA(AM7:AQ7)/5,D7) -> 0.2 | AM7: 45664 | AR7: Pending | AS7: 45664
B8: {=+_xlfn.IFS(D8="In Touch - Positive",2,D8="Pending",1,D8="No Answer",4,D8="In Touch - Negative",3)} -> 1 | C8: La Doria | D8: =+AR8 -> Pending | E8: Bio Organica Italia s.r.l. | J8: Food | K8: Produzione conserve, sottoli, sughi e preparati | S8: no | T8: 2023 | AA8: Cold Call | AC8: ASP | AJ8: =+TODAY()-AM8 -> 0 | AK8: =+TODAY()-AS8 -> 0 | AL8: =+IF(D8="Pending",COUNTA(AM8:AQ8)/5,D8) -> 0.2 | AM8: 45664 | AR8: Pending | AS8: 45664
B9: {=+_xlfn.IFS(D9="In Touch - Positive",2,D9="Pending",1,D9="No Answer",4,D9="In Touch - Negative",3)} -> 1 | C9: La Doria | D9: =+AR9 -> Pending | E9: Gruppo Fini S.p.A. | J9: Food | K9: Produzione conserve, sottoli, sughi e preparati | S9: no | T9: 2023 | AA9: Cold Call | AC9: ASP | AJ9: =+TODAY()-AM9 -> 0 | AK9: =+TODAY()-AS9 -> 0 | AL9: =+IF(D9="Pending",COUNTA(AM9:AQ9)/5,D9) -> 0.2 | AM9: 45664 | AR9: Pending | AS9: 45664
B10: {=+_xlfn.IFS(D10="In Touch - Positive",2,D10="Pending",1,D10="No Answer",4,D10="In Touch - Negative",3)} -> 1 | C10: La Doria | D10: =+AR10 -> Pending | E10: Naturello S.p.A. | J10: Food | K10: Produzione conserve, sottoli, sughi e preparati | S10: no | T10: 2023 | AA10: Cold Call | AC10: ASP | AJ10: =+TODAY()-AM10 -> 0 | AK10: =+TODAY()-AS10 -> 0 | AL10: =+IF(D10="Pending",COUNTA(AM10:AQ10)/5,D10) -> 0.2 | AM10: 45664 | AR10: Pending | AS10: 45664
B11: {=+_xlfn.IFS(D11="In Touch - Positive",2,D11="Pending",1,D11="No Answer",4,D11="In Touch - Negative",3)} -> 1 | C11: La Doria | D11: =+AR11 -> Pending | E11: Citres S.p.A. | J11: Food | K11: Produzione conserve, sottoli, sughi e preparati | S11: no | T11: 2023 | AA11: Cold Call | AC11: ASP | AJ11: =+TODAY()-AM11 -> 0 | AK11: =+TODAY()-AS11 -> 0 | AL11: =+IF(D11="Pending",COUNTA(AM11:AQ11)/5,D11) -> 0.2 | AM11: 45664 | AR11: Pending | AS11: 45664
B12: {=+_xlfn.IFS(D12="In Touch - Positive",2,D12="Pending",1,D12="No Answer",4,D12="In Touch - Negative",3)} -> 1 | C12: Logistics | D12: =+AR12 -> Pending | E12: ITALSEMPIONE - SPEDIZIONI INTERNAZIONALI S.P.A. | J12: Logistics | AA12: Cold Call | AC12: RIM | AJ12: =+TODAY()-AM12 -> 1 | AK12: =+TODAY()-AS12 -> 1 | AL12: =+IF(D12="Pending",COUNTA(AM12:AQ12)/5,D12) -> 0.2 | AM12: 45663 | AR12: Pending | AS12: 45663
B13: {=+_xlfn.IFS(D13="In Touch - Positive",2,D13="Pending",1,D13="No Answer",4,D13="In Touch - Negative",3)} -> 1 | C13: Logistics | D13: =+AR13 -> Pending | E13: B. PACORINI S.P.A. | J13: Logistics | AA13: Cold Call | AC13: RIM | AJ13: =+TODAY()-AM13 -> 1 | AK13: =+TODAY()-AS13 -> 1 | AL13: =+IF(D13="Pending",COUNTA(AM13:AQ13)/5,D13) -> 0.2 | AM13: 45663 | AR13: Pending | AS13: 45663
B14: {=+_xlfn.IFS(D14="In Touch - Positive",2,D14="Pending",1,D14="No Answer",4,D14="In Touch - Negative",3)} -> 1 | C14: Logistics | D14: =+AR14 -> Pending | E14: SUSA-S.P.A. | J14: Logistics | AA14: Cold Call | AC14: RIM | AJ14: =+TODAY()-AM14 -> 1 | AK14: =+TODAY()-AS14 -> 1 | AL14: =+IF(D14="Pending",COUNTA(AM14:AQ14)/5,D14) -> 0.2 | AM14: 45663 | AR14: Pending | AS14: 45663
B15: {=+_xlfn.IFS(D15="In Touch - Positive",2,D15="Pending",1,D15="No Answer",4,D15="In Touch - Negative",3)} -> 1 | C15: Logistics | D15: =+AR15 -> Pending | E15: ITALTRANS S.P.A. | J15: Logistics | AA15: Cold Call | AC15: RIM | AJ15: =+TODAY()-AM15 -> 1 | AK15: =+TODAY()-AS15 -> 1 | AL15: =+IF(D15="Pending",COUNTA(AM15:AQ15)/5,D15) -> 0.2 | AM15: 45663 | AR15: Pending | AS15: 45663
B16: {=+_xlfn.IFS(D16="In Touch - Positive",2,D16="Pending",1,D16="No Answer",4,D16="In Touch - Negative",3)} -> 1 | C16: Logistics | D16: =+AR16 -> Pending | E16: LOGISTICA UNO EUROPE S.R.L. | J16: Logistics | AA16: Cold Call | AC16: RIM | AJ16: =+TODAY()-AM16 -> 1 | AK16: =+TODAY()-AS16 -> 1 | AL16: =+IF(D16="Pending",COUNTA(AM16:AQ16)/5,D16) -> 0.2 | AM16: 45663 | AR16: Pending | AS16: 45663
B17: {=+_xlfn.IFS(D17="In Touch - Positive",2,D17="Pending",1,D17="No Answer",4,D17="In Touch - Negative",3)} -> 1 | C17: Logistics | D17: =+AR17 -> Pending | E17: ARCO SPEDIZIONI S.P.A. | J17: Logistics | AA17: Cold Call | AC17: RIM | AJ17: =+TODAY()-AM17 -> 1 | AK17: =+TODAY()-AS17 -> 1 | AL17: =+IF(D17="Pending",COUNTA(AM17:AQ17)/5,D17) -> 0.2 | AM17: 45663 | AR17: Pending | AS17: 45663
B18: {=+_xlfn.IFS(D18="In Touch - Positive",2,D18="Pending",1,D18="No Answer",4,D18="In Touch - Negative",3)} -> 1 | C18: Logistics | D18: =+AR18 -> Pending | E18: ALBERTI GERMANO E SANTI ROMANO S.R.L. | J18: Logistics | AA18: Cold Call | AC18: RIM | AJ18: =+TODAY()-AM18 -> 1 | AK18: =+TODAY()-AS18 -> 1 | AL18: =+IF(D18="Pending",COUNTA(AM18:AQ18)/5,D18) -> 0.2 | AM18: 45663 | AR18: Pending | AS18: 45663
B19: {=+_xlfn.IFS(D19="In Touch - Positive",2,D19="Pending",1,D19="No Answer",4,D19="In Touch - Negative",3)} -> 1 | C19: Logistics | D19: =+AR19 -> Pending | E19: SAMER & CO. SHIPPING S.P.A. | J19: Logistics | AA19: Cold Call | AC19: RIM | AJ19: =+TODAY()-AM19 -> 1 | AK19: =+TODAY()-AS19 -> 1 | AL19: =+IF(D19="Pending",COUNTA(AM19:AQ19)/5,D19) -> 0.2 | AM19: 45663 | AR19: Pending | AS19: 45663
B20: {=+_xlfn.IFS(D20="In Touch - Positive",2,D20="Pending",1,D20="No Answer",4,D20="In Touch - Negative",3)} -> 1 | C20: Logistics | D20: =+AR20 -> Pending | E20: CST LOGISTICA TRASPORTI S.R.L. | J20: Logistics | AA20: Cold Call | AC20: RIM | AJ20: =+TODAY()-AM20 -> 1 | AK20: =+TODAY()-AS20 -> 1 | AL20: =+IF(D20="Pending",COUNTA(AM20:AQ20)/5,D20) -> 0.2 | AM20: 45663 | AR20: Pending | AS20: 45663
B21: {=+_xlfn.IFS(D21="In Touch - Positive",2,D21="Pending",1,D21="No Answer",4,D21="In Touch - Negative",3)} -> 1 | C21: Logistics | D21: =+AR21 -> Pending | E21: BETA-TRANS S.P.A. | J21: Logistics | AA21: Cold Call | AC21: RIM | AJ21: =+TODAY()-AM21 -> 1 | AK21: =+TODAY()-AS21 -> 1 | AL21: =+IF(D21="Pending",COUNTA(AM21:AQ21)/5,D21) -> 0.2 | AM21: 45663 | AR21: Pending | AS21: 45663
B22: {=+_xlfn.IFS(D22="In Touch - Positive",2,D22="Pending",1,D22="No Answer",4,D22="In Touch - Negative",3)} -> 1 | C22: Logistics | D22: =+AR22 -> Pending | E22: GIANESINI ERMINIO - SOCIETA' A RESPONSABILITA' LIMITATA | J22: Logistics | AA22: Cold Call | AC22: RIM | AJ22: =+TODAY()-AM22 -> 1 | AK22: =+TODAY()-AS22 -> 1 | AL22: =+IF(D22="Pending",COUNTA(AM22:AQ22)/5,D22) -> 0.2 | AM22: 45663 | AR22: Pending | AS22: 45663
B23: {=+_xlfn.IFS(D23="In Touch - Positive",2,D23="Pending",1,D23="No Answer",4,D23="In Touch - Negative",3)} -> 1 | C23: Logistics | D23: =+AR23 -> Pending | E23: ORMESANI S.R.L. | J23: Logistics | AA23: Cold Call | AC23: RIM | AJ23: =+TODAY()-AM23 -> 1 | AK23: =+TODAY()-AS23 -> 1 | AL23: =+IF(D23="Pending",COUNTA(AM23:AQ23)/5,D23) -> 0.2 | AM23: 45663 | AR23: Pending | AS23: 45663
... B32: {=+_xlfn.IFS(D32="In Touch - Positive",2,D32="Pending",1,D32="No Answer",4,D32="In Touch - Negative",3)} -> 1 | C32: Logistics | D32: =+AR32 -> Pending | E32: TRIMAR - SOCIETA' A RESPONSABILITA' LIMITATA | J32: Logistics | AA32: Cold Call | AC32: RIM | AJ32: =+TODAY()-AM32 -> 1 | AK32: =+TODAY()-AS32 -> 1 | AL32: =+IF(D32="Pending",COUNTA(AM32:AQ32)/5,D32) -> 0.2 | AM32: 45663 | AR32: Pending | AS32: 45663
B33: {=+_xlfn.IFS(D33="In Touch - Positive",2,D33="Pending",1,D33="No Answer",4,D33="In Touch - Negative",3)} -> 1 | C33: Add-on Almac-Wise | D33: =+AR33 -> Pending | E33: Easy Lift Srl | G33: RE | H33: 02192530356 | J33: Machinery | K33: Produzione di gru e piattaforme aeree | M33: Michele Sorianini | O33: Michele Sorianini | S33: no | T33: 2023 | U33: 20.3 | V33: 2.1 | W33: =+V33/U33 -> 0.10344828 | Y33: 1.69 | AA33: Cold Call | AC33: GIM | AD33: LOM | AE33: PAD | AJ33: =+TODAY()-AM33 -> 23 | AK33: =+TODAY()-AS33 -> 0 | AL33: =+IF(D33="Pending",COUNTA(AM33:AQ33)/5,D33) -> 0.4 | AM33: 45641 | AN33: 45664 | AR33: Pending | AS33: 45664
B34: {=+_xlfn.IFS(D34="In Touch - Positive",2,D34="Pending",1,D34="No Answer",4,D34="In Touch - Negative",3)} -> 1 | C34: Add-on Almac-Wise | D34: =+AR34 -> Pending | E34: Gruniverpal Srl | G34: CN | H34: 00180660045 | J34: Machinery | K34: Produzione di gru e piattaforme aeree | M34: Emanuele Antonio Giovanni Tranchero | P34: Emanuele Antonio Giovanni Tranchero | S34: no | T34: 2023 | U34: 4.2 | V34: 1.2 | W34: =+V34/U34 -> 0.28571429 | Y34: -2.19 | AA34: Cold Call | AC34: GIM | AD34: LOM | AE34: PAD | AJ34: =+TODAY()-AM34 -> 23 | AK34: =+TODAY()-AS34 -> 0 | AL34: =+IF(D34="Pending",COUNTA(AM34:AQ34)/5,D34) -> 0.4 | AM34: 45641 | AN34: 45664 | AR34: Pending | AS34: 45664
B35: {=+_xlfn.IFS(D35="In Touch - Positive",2,D35="Pending",1,D35="No Answer",4,D35="In Touch - Negative",3)} -> 1 | C35: Add-on Almac-Wise | D35: =+AR35 -> Pending | E35: JMG Cranes SpA | G35: CR | H35: 05896090965 | J35: Machinery | K35: Produzione di gru e piattaforme aeree | M35: Maurizio Manzini | P35: Maurizio Manzini | S35: no | T35: 2023 | U35: 32.7 | V35: 5.2 | W35: =+V35/U35 -> 0.15902141 | Y35: 2.88 | AA35: Cold Call | AC35: GIM | AD35: LOM | AE35: PAD | AJ35: =+TODAY()-AM35 -> 23 | AK35: =+TODAY()-AS35 -> 0 | AL35: =+IF(D35="Pending",COUNTA(AM35:AQ35)/5,D35) -> 0.4 | AM35: 45641 | AN35: 45664 | AR35: Pending | AS35: 45664
B36: {=+_xlfn.IFS(D36="In Touch - Positive",2,D36="Pending",1,D36="No Answer",4,D36="In Touch - Negative",3)} -> 1 | C36: Add-on Almac-Wise | D36: =+AR36 -> Pending | E36: Benelli Crane e Platform S.r.l. | G36: RE | H36: 02867920353 | J36: Machinery | K36: Produzione di gru e piattaforme aeree | M36: Claudio Fiorini | P36: Giovanni Luca Caltagirone | S36: no | T36: 2023 | U36: 4.1 | V36: 0.6 | W36: =+V36/U36 -> 0.14634146 | Y36: -0.46 | AA36: Cold Call | AC36: GIM | AD36: LOM | AE36: PAD | AJ36: =+TODAY()-AM36 -> 23 | AK36: =+TODAY()-AS36 -> 0 | AL36: =+IF(D36="Pending",COUNTA(AM36:AQ36)/5,D36) -> 0.4 | AM36: 45641 | AN36: 45664 | AR36: Pending | AS36: 45664
B37: {=+_xlfn.IFS(D37="In Touch - Positive",2,D37="Pending",1,D37="No Answer",4,D37="In Touch - Negative",3)} -> 1 | C37: Higher Education | D37: =+AR37 -> Pending | E37: AGORA SERVIZI Srl | G37: MI | J37: Education | K37: Formazione professionale (medicina estetica) | L37: Alessandra Zanelli | S37: no | T37: 2023 | U37: 3.781 | V37: 0.744 | W37: =+V37/U37 -> 0.19677334 | AA37: Cold Call | AC37: LUS | AD37: LUS | AE37: LUS | AJ37: =+TODAY()-AM37 -> 32 | AK37: =+TODAY()-AS37 -> 32 | AL37: =+IF(D37="Pending",COUNTA(AM37:AQ37)/5,D37) -> 0.6 | AM37: 45632 | AN37: 45632 | AO37: na | AR37: Pending | AS37: 45632
B38: {=+_xlfn.IFS(D38="In Touch - Positive",2,D38="Pending",1,D38="No Answer",4,D38="In Touch - Negative",3)} -> 1 | C38: Higher Education | D38: =+AR38 -> Pending | E38: VALET srl | G38: BO | J38: Education | K38: Formazione professionale (medicina estetica) | L38: Federico Monti | S38: no | T38: 2023 | U38: 2.305 | V38: 0.687 | W38: =+V38/U38 -> 0.29804772 | AA38: Cold Call | AC38: LUS | AD38: LUS | AE38: LUS | AJ38: =+TODAY()-AM38 -> 32 | AK38: =+TODAY()-AS38 -> 32 | AL38: =+IF(D38="Pending",COUNTA(AM38:AQ38)/5,D38) -> 0.6 | AM38: 45632 | AN38: 45632 | AO38: na | AR38: Pending | AS38: 45632
B39: {=+_xlfn.IFS(D39="In Touch - Positive",2,D39="Pending",1,D39="No Answer",4,D39="In Touch - Negative",3)} -> 1 | C39: Cliniche Estetiche | D39: =+AR39 -> Pending | E39: HANUNA S.R.L.S. | G39: MI | J39: Healthcare | K39: Clinica estetica | L39: Hen Ifrach | S39: no | T39: 2023 | U39: 0.413 | V39: 0.244 | W39: =+V39/U39 -> 0.59079903 | AA39: Cold Call | AC39: LUS | AD39: LUS | AE39: LUS | AJ39: =+TODAY()-AM39 -> 34 | AK39: =+TODAY()-AS39 -> 33 | AL39: =+IF(D39="Pending",COUNTA(AM39:AQ39)/5,D39) -> 0.6 | AM39: 45630 | AN39: 45631 | AO39: na | AR39: Pending | AS39: 45631
B40: {=+_xlfn.IFS(D40="In Touch - Positive",2,D40="Pending",1,D40="No Answer",4,D40="In Touch - Negative",3)} -> 1 | C40: Cliniche Estetiche | D40: =+AR40 -> Pending | E40: STUDIO MB S.R.L. | G40: VI | J40: Healthcare | K40: Clinica estetica | L40: Michele Buratto | S40: no | T40: 2023 | U40: 0.75 | V40: 0.253 | W40: =+V40/U40 -> 0.33733333 | AA40: Cold Call | AC40: LUS | AD40: LUS | AE40: LUS | AJ40: =+TODAY()-AM40 -> 34 | AK40: =+TODAY()-AS40 -> 33 | AL40: =+IF(D40="Pending",COUNTA(AM40:AQ40)/5,D40) -> 0.6 | AM40: 45630 | AN40: 45631 | AO40: na | AR40: Pending | AS40: 45631
B41: {=+_xlfn.IFS(D41="In Touch - Positive",2,D41="Pending",1,D41="No Answer",4,D41="In Touch - Negative",3)} -> 1 | C41: Cliniche Estetiche | D41: =+AR41 -> Pending | E41: GESTIMED S.R.L. | G41: MI | J41: Healthcare | K41: Clinica estetica | L41: Giovanni Luigi Rizzi | S41: no | T41: 2023 | U41: 1.679 | V41: 0.27 | W41: =+V41/U41 -> 0.16081001 | AA41: Cold Call | AC41: LUS | AD41: LUS | AE41: LUS | AJ41: =+TODAY()-AM41 -> 34 | AK41: =+TODAY()-AS41 -> 33 | AL41: =+IF(D41="Pending",COUNTA(AM41:AQ41)/5,D41) -> 0.6 | AM41: 45630 | AN41: 45631 | AO41: na | AR41: Pending | AS41: 45631
B42: {=+_xlfn.IFS(D42="In Touch - Positive",2,D42="Pending",1,D42="No Answer",4,D42="In Touch - Negative",3)} -> 1 | C42: Cliniche Estetiche | D42: =+AR42 -> Pending | E42: RF CLINICS S.R.L. | G42: CO | J42: Healthcare | K42: Clinica estetica | L42: Riccardo Forte | S42: no | T42: 2023 | U42: 0.747 | V42: 0.382 | W42: =+V42/U42 -> 0.51137885 | AA42: Cold Call | AC42: LUS | AD42: LUS | AE42: LUS | AJ42: =+TODAY()-AM42 -> 34 | AK42: =+TODAY()-AS42 -> 33 | AL42: =+IF(D42="Pending",COUNTA(AM42:AQ42)/5,D42) -> 0.6 | AM42: 45630 | AN42: 45631 | AO42: na | AR42: Pending | AS42: 45631
B43: {=+_xlfn.IFS(D43="In Touch - Positive",2,D43="Pending",1,D43="No Answer",4,D43="In Touch - Negative",3)} -> 1 | C43: Cliniche Estetiche | D43: =+AR43 -> Pending | E43: MCB MEDICA STP SRL | G43: VE | J43: Healthcare | K43: Clinica estetica | L43: Alessandro Giovanni Morelli Coghi | S43: no | T43: 2023 | U43: 0.465 | V43: 0.401 | W43: =+V43/U43 -> 0.86236559 | AA43: Cold Call | AC43: LUS | AD43: LUS | AE43: LUS | AJ43: =+TODAY()-AM43 -> 34 | AK43: =+TODAY()-AS43 -> 33 | AL43: =+IF(D43="Pending",COUNTA(AM43:AQ43)/5,D43) -> 0.6 | AM43: 45630 | AN43: 45631 | AO43: na | AR43: Pending | AS43: 45631
B44: {=+_xlfn.IFS(D44="In Touch - Positive",2,D44="Pending",1,D44="No Answer",4,D44="In Touch - Negative",3)} -> 1 | C44: Cliniche Estetiche | D44: =+AR44 -> Pending | E44: LONDEICLINIC S.R.L. | G44: PD | J44: Healthcare | K44: Clinica estetica | L44: Giorgio Londei | S44: no | T44: 2023 | U44: 1.974 | V44: 0.5 | W44: =+V44/U44 -> 0.25329281 | AA44: Cold Call | AC44: LUS | AD44: LUS | AE44: LUS | AJ44: =+TODAY()-AM44 -> 34 | AK44: =+TODAY()-AS44 -> 34 | AL44: =+IF(D44="Pending",COUNTA(AM44:AQ44)/5,D44) -> 0.6 | AM44: 45630 | AN44: 45630 | AO44: na | AR44: Pending | AS44: 45630
B45: {=+_xlfn.IFS(D45="In Touch - Positive",2,D45="Pending",1,D45="No Answer",4,D45="In Touch - Negative",3)} -> 1 | C45: Cliniche Estetiche | D45: =+AR45 -> Pending | E45: MY PLASTIC SURGERY S.R.L. | G45: MI | J45: Healthcare | K45: Clinica estetica | L45: Mauro Valente | S45: no | T45: 2023 | U45: 1.075 | V45: 0.651 | W45: =+V45/U45 -> 0.6055814 | AA45: Cold Call | AC45: LUS | AD45: LUS | AE45: LUS | AJ45: =+TODAY()-AM45 -> 34 | AK45: =+TODAY()-AS45 -> 34 | AL45: =+IF(D45="Pending",COUNTA(AM45:AQ45)/5,D45) -> 0.6 | AM45: 45630 | AN45: 45630 | AO45: na | AR45: Pending | AS45: 45630
B46: {=+_xlfn.IFS(D46="In Touch - Positive",2,D46="Pending",1,D46="No Answer",4,D46="In Touch - Negative",3)} -> 1 | C46: Cliniche Estetiche | D46: =+AR46 -> Pending | E46: MANUELA PILI S.R.L. | G46: SS | J46: Healthcare | K46: Clinica estetica | L46: Manuela Pili | S46: no | T46: 2023 | U46: 1.966 | V46: 0.799 | W46: =+V46/U46 -> 0.40640895 | AA46: Cold Call | AC46: LUS | AD46: LUS | AE46: LUS | AJ46: =+TODAY()-AM46 -> 34 | AK46: =+TODAY()-AS46 -> 34 | AL46: =+IF(D46="Pending",COUNTA(AM46:AQ46)/5,D46) -> 0.6 | AM46: 45630 | AN46: 45630 | AO46: na | AR46: Pending | AS46: 45630
B47: {=+_xlfn.IFS(D47="In Touch - Positive",2,D47="Pending",1,D47="No Answer",4,D47="In Touch - Negative",3)} -> 1 | C47: Fitness Retail | D47: =+AR47 -> Pending | E47: PRIMA A R.L. | G47: AN | J47: Fitness | K47: Gestione di palestre | L47: Emanuele Mancinelli | S47: no | T47: 2023 | U47: 4.6 | V47: 0.45 | W47: =+V47/U47 -> 0.097826087 | AA47: Cold Call | AC47: LUS | AD47: LUS | AE47: LUS | AJ47: =+TODAY()-AM47 -> 50 | AK47: =+TODAY()-AS47 -> 43 | AL47: =+IF(D47="Pending",COUNTA(AM47:AQ47)/5,D47) -> 0.6 | AM47: 45614 | AN47: 45618 | AO47: na | AR47: Pending | AS47: 45621
B48: {=+_xlfn.IFS(D48="In Touch - Positive",2,D48="Pending",1,D48="No Answer",4,D48="In Touch - Negative",3)} -> 1 | C48: Scouting buy-side | D48: =+AR48 -> Pending | E48: RICERFARMA SRL | G48: MI | H48: 12603470159 | J48: Chemicals | K48: Prodotti farmaceutici e chimica farmaceutica | M48: Matteo Rinaldo Macchi | N48: Andrea Antonio Macchi | S48: no | T48: 2023 | U48: 21.238057 | V48: 13.423319 | W48: =+V48/U48 -> 0.63204082 | X48: 11.318201 | Y48: -8.530461 | AA48: Cold Call | AC48: GIM | AD48: ASC | AE48: GIM | AJ48: =+TODAY()-AM48 -> 22 | AK48: =+TODAY()-AS48 -> 22 | AL48: =+IF(D48="Pending",COUNTA(AM48:AQ48)/5,D48) -> 0.2 | AM48: 45642 | AR48: Pending | AS48: 45642
B49: {=+_xlfn.IFS(D49="In Touch - Positive",2,D49="Pending",1,D49="No Answer",4,D49="In Touch - Negative",3)} -> 1 | C49: Scouting buy-side | D49: =+AR49 -> Pending | E49: PONZIO S.R.L. | G49: TE | H49: 00061490678 | J49: Arredamento | K49: Infissi in alluminio | M49: Emilio Ponzio | N49: Edoardo Ponzio | S49: si | T49: 2023 | U49: 77.52894 | V49: 11.82858 | W49: =+V49/U49 -> 0.15256987 | X49: 5.039875 | Y49: 24.305701 | AA49: Cold Call | AC49: GIM | AD49: ASC | AE49: GIM | AJ49: =+TODAY()-AM49 -> 22 | AK49: =+TODAY()-AS49 -> 22 | AL49: =+IF(D49="Pending",COUNTA(AM49:AQ49)/5,D49) -> 0.2 | AM49: 45642 | AR49: Pending | AS49: 45642
B50: {=+_xlfn.IFS(D50="In Touch - Positive",2,D50="Pending",1,D50="No Answer",4,D50="In Touch - Negative",3)} -> 1 | C50: Scouting buy-side | D50: =+AR50 -> Pending | E50: MESSERSI' PACKAGING S.R.L. | G50: AN | H50: 01267390423 | J50: Machinery | K50: Soluzioni per il packaging / macchinari fine linea | M50: Maurizio Messersi | N50: Mariola Villani | S50: no | T50: 2023 | U50: 65.406658 | V50: 11.016576 | W50: =+V50/U50 -> 0.16843203 | X50: 5.891749 | Y50: -13.177834 | AA50: Cold Call | AC50: GIM | AD50: ASC | AE50: GIM | AJ50: =+TODAY()-AM50 -> 22 | AK50: =+TODAY()-AS50 -> 22 | AL50: =+IF(D50="Pending",COUNTA(AM50:AQ50)/5,D50) -> 0.2 | AM50: 45642 | AR50: Pending | AS50: 45642
B51: {=+_xlfn.IFS(D51="In Touch - Positive",2,D51="Pending",1,D51="No Answer",4,D51="In Touch - Negative",3)} -> 1 | C51: Scouting buy-side | D51: =+AR51 -> Pending | E51: CAPELLO S.R.L. | G51: CN | H51: 03247430048 | J51: Machinery | K51: Attrezzature agricole per la raccolta dei cereali | M51: Elio Luigi Capello | N51: Alberto Capello | S51: no | T51: 2023 | U51: 55.700043 | V51: 10.710388 | W51: =+V51/U51 -> 0.19228689 | X51: 6.896572 | Y51: 2.573675 | AA51: Cold Call | AC51: GIM | AD51: ASC | AE51: GIM | AJ51: =+TODAY()-AM51 -> 22 | AK51: =+TODAY()-AS51 -> 22 | AL51: =+IF(D51="Pending",COUNTA(AM51:AQ51)/5,D51) -> 0.2 | AM51: 45642 | AR51: Pending | AS51: 45642
B52: {=+_xlfn.IFS(D52="In Touch - Positive",2,D52="Pending",1,D52="No Answer",4,D52="In Touch - Negative",3)} -> 1 | C52: Scouting buy-side | D52: =+AR52 -> Pending | E52: SIFA S.P.A. | G52: FM | H52: 01242720447 | J52: Packaging | K52: Produzione di scatole e altri lavorati in cartone | M52: Roberto Trasarti | N52: Alessia Trasarti | S52: no | T52: 2023 | U52: 80.925899 | V52: 10.634332 | W52: =+V52/U52 -> 0.13140827 | X52: 6.058595 | Y52: -4.994481 | AA52: Cold Call | AC52: GIM | AD52: ASC | AE52: GIM | AJ52: =+TODAY()-AM52 -> 22 | AK52: =+TODAY()-AS52 -> 22 | AL52: =+IF(D52="Pending",COUNTA(AM52:AQ52)/5,D52) -> 0.2 | AM52: 45642 | AR52: Pending | AS52: 45642
B53: {=+_xlfn.IFS(D53="In Touch - Positive",2,D53="Pending",1,D53="No Answer",4,D53="In Touch - Negative",3)} -> 1 | C53: Digital e Idrotech (EIMA) | D53: =+AR53 -> Pending | E53: TECOMEC S.R.L. | G53: RE | H53: 01219320353 | J53: Agricoltura | L53: Francesco Crotti | S53: no | T53: 2023 | U53: 62.9 | V53: 8.99 | W53: =+V53/U53 -> 0.14292528 | X53: 5.6 | Y53: 19.8 | AA53: Cold Call | AC53: FCA | AD53: FCA | AE53: FCA | AJ53: =+TODAY()-AM53 -> 29 | AK53: =+TODAY()-AS53 -> 29 | AL53: =+IF(D53="Pending",COUNTA(AM53:AQ53)/5,D53) -> 0.6 | AM53: 45635 | AN53: 45636 | AO53: 45670 | AR53: Pending | AS53: 45635
B54: {=+_xlfn.IFS(D54="In Touch - Positive",2,D54="Pending",1,D54="No Answer",4,D54="In Touch - Negative",3)} -> 1 | C54: Digital e Idrotech (EIMA) | D54: =+AR54 -> Pending | E54: RICCINI S.R.L. | G54: PG | H54: 00644190548 | J54: Agricoltura | L54: Fabio Riccini | S54: no | T54: 2023 | U54: 33.7 | V54: 8.6 | W54: =+V54/U54 -> 0.25519288 | X54: 5.5 | Y54: -4.5 | AA54: Cold Call | AC54: FCA | AD54: FCA | AE54: FCA | AJ54: =+TODAY()-AM54 -> 29 | AK54: =+TODAY()-AS54 -> 29 | AL54: =+IF(D54="Pending",COUNTA(AM54:AQ54)/5,D54) -> 0.6 | AM54: 45635 | AN54: 45636 | AO54: 45670 | AR54: Pending | AS54: 45635
B55: {=+_xlfn.IFS(D55="In Touch - Positive",2,D55="Pending",1,D55="No Answer",4,D55="In Touch - Negative",3)} -> 1 | C55: Digital e Idrotech (EIMA) | D55: =+AR55 -> Pending | E55: GUARNIFLON S.P.A. | G55: MI | H55: 01406020162 | J55: Agricoltura | L55: Luca Mazza | S55: no | T55: 2023 | U55: 86.6 | V55: 10.3 | W55: =+V55/U55 -> 0.11893764 | X55: 4.6 | Y55: 14.7 | AA55: Cold Call | AC55: ASP | AD55: ASP | AE55: ASP | AJ55: =+TODAY()-AM55 -> 29 | AK55: =+TODAY()-AS55 -> 29 | AL55: =+IF(D55="Pending",COUNTA(AM55:AQ55)/5,D55) -> 0.6 | AM55: 45635 | AN55: 45636 | AO55: 45670 | AR55: Pending | AS55: 45635
B56: {=+_xlfn.IFS(D56="In Touch - Positive",2,D56="Pending",1,D56="No Answer",4,D56="In Touch - Negative",3)} -> 1 | C56: Digital e Idrotech (EIMA) | D56: =+AR56 -> Pending | E56: GREEN POWER SYSTEMS S.R.L. | G56: PU | H56: 02018810412 | J56: Agricoltura | L56: Fam Brugnettini | S56: no | T56: 2023 | U56: 107.9 | V56: 9.6 | W56: =+V56/U56 -> 0.08897127 | X56: 5.7 | Y56: 23.1 | AA56: Cold Call | AC56: ASP | AD56: ASP | AE56: ASP | AJ56: =+TODAY()-AM56 -> 29 | AK56: =+TODAY()-AS56 -> 29 | AL56: =+IF(D56="Pending",COUNTA(AM56:AQ56)/5,D56) -> 0.6 | AM56: 45635 | AN56: 45636 | AO56: 45670 | AR56: Pending | AS56: 45635
B57: {=+_xlfn.IFS(D57="In Touch - Positive",2,D57="Pending",1,D57="No Answer",4,D57="In Touch - Negative",3)} -> 1 | C57: Digital e Idrotech (EIMA) | D57: =+AR57 -> Pending | E57: CASELLA MACCHINE AGRICOLE S.R.L. | G57: PC | H57: 00103940334 | J57: Agricoltura | L57: Fam Casella | S57: no | T57: 2023 | U57: 105.6 | V57: 9.4 | W57: =+V57/U57 -> 0.089015152 | X57: 5.5 | Y57: 16.1 | AA57: Cold Call | AC57: ASP | AD57: ASP | AE57: ASP | AJ57: =+TODAY()-AM57 -> 29 | AK57: =+TODAY()-AS57 -> 29 | AL57: =+IF(D57="Pending",COUNTA(AM57:AQ57)/5,D57) -> 0.6 | AM57: 45635 | AN57: 45636 | AO57: 45670 | AR57: Pending | AS57: 45635
B58: {=+_xlfn.IFS(D58="In Touch - Positive",2,D58="Pending",1,D58="No Answer",4,D58="In Touch - Negative",3)} -> 1 | C58: Digital e Idrotech (EIMA) | D58: =+AR58 -> Pending | E58: ROVATTI A.& FIGLI POMPE SOCIETA' PER AZIONI O IN FORMA ABBREVIATA ROVATTI A.& FIGLI POMPE S.P.A. | G58: RE | H58: 00146150354 | J58: Agricoltura | L58: Andrea Rovatti | S58: no | T58: 2023 | U58: 32.8 | V58: 8.7 | W58: =+V58/U58 -> 0.2652439 | X58: 6.1 | Y58: -12.6 | AA58: Cold Call | AC58: ASP | AD58: ASP | AE58: ASP | AJ58: =+TODAY()-AM58 -> 29 | AK58: =+TODAY()-AS58 -> 29 | AL58: =+IF(D58="Pending",COUNTA(AM58:AQ58)/5,D58) -> 0.6 | AM58: 45635 | AN58: 45636 | AO58: 45670 | AR58: Pending | AS58: 45635
B59: {=+_xlfn.IFS(D59="In Touch - Positive",2,D59="Pending",1,D59="No Answer",4,D59="In Touch - Negative",3)} -> 1 | C59: Digital e Idrotech (EIMA) | D59: =+AR59 -> Pending | E59: SAB S.P.A. | G59: PU | H59: 02138950411 | J59: Agricoltura | L59: Emiliano Boscarini | S59: no | T59: 2023 | U59: 38.6 | V59: 7.6 | W59: =+V59/U59 -> 0.19689119 | X59: 4.07 | Y59: -6 | AA59: Cold Call | AC59: ASP | AD59: ASP | AE59: ASP | AJ59: =+TODAY()-AM59 -> 29 | AK59: =+TODAY()-AS59 -> 29 | AL59: =+IF(D59="Pending",COUNTA(AM59:AQ59)/5,D59) -> 0.6 | AM59: 45635 | AN59: 45636 | AO59: 45670 | AR59: Pending | AS59: 45635
B60: {=+_xlfn.IFS(D60="In Touch - Positive",2,D60="Pending",1,D60="No Answer",4,D60="In Touch - Negative",3)} -> 1 | C60: Digital e Idrotech (EIMA) | D60: =+AR60 -> Pending | E60: STONEX S.R.L. | G60: MB | H60: 06830030968 | J60: Agricoltura | L60: Andrea Bianchi | S60: no | T60: 2023 | U60: 28.2 | V60: 6.7 | W60: =+V60/U60 -> 0.23758865 | X60: 4.66 | Y60: -11.3 | AA60: Cold Call | AC60: ASP | AD60: ASP | AE60: ASP | AJ60: =+TODAY()-AM60 -> 29 | AK60: =+TODAY()-AS60 -> 29 | AL60: =+IF(D60="Pending",COUNTA(AM60:AQ60)/5,D60) -> 0.6 | AM60: 45635 | AN60: 45636 | AO60: 45670 | AR60: Pending | AS60: 45635
B61: {=+_xlfn.IFS(D61="In Touch - Positive",2,D61="Pending",1,D61="No Answer",4,D61="In Touch - Negative",3)} -> 1 | C61: Digital e Idrotech (EIMA) | D61: =+AR61 -> Pending | E61: LA.RE.TER. LAVORAZIONE RESINE TERMOPLASTICHE - S.P.A. | G61: GE | H61: 01079200299 | J61: Agricoltura | L61: Francesca Libanori | S61: no | T61: 2023 | U61: 32.1 | V61: 6.2 | W61: =+V61/U61 -> 0.19314642 | X61: 3.9 | Y61: 0.7 | AA61: Cold Call | AC61: ASP | AD61: ASP | AE61: ASP | AJ61: =+TODAY()-AM61 -> 29 | AK61: =+TODAY()-AS61 -> 29 | AL61: =+IF(D61="Pending",COUNTA(AM61:AQ61)/5,D61) -> 0.6 | AM61: 45635 | AN61: 45636 | AO61: 45670 | AR61: Pending | AS61: 45635
B62: {=+_xlfn.IFS(D62="In Touch - Positive",2,D62="Pending",1,D62="No Answer",4,D62="In Touch - Negative",3)} -> 1 | C62: Digital e Idrotech (EIMA) | D62: =+AR62 -> Pending | E62: BRAGLIA S.R.L. | G62: RE | H62: 00443530357 | J62: Agricoltura | L62: Fam. Braglia | S62: no | T62: 2023 | U62: 19 | V62: 5.29 | W62: =+V62/U62 -> 0.27842105 | X62: 3.7 | Y62: -0.3 | AA62: Cold Call | AC62: ASP | AD62: ASP | AE62: ASP | AJ62: =+TODAY()-AM62 -> 29 | AK62: =+TODAY()-AS62 -> 29 | AL62: =+IF(D62="Pending",COUNTA(AM62:AQ62)/5,D62) -> 0.6 | AM62: 45635 | AN62: 45636 | AO62: 45670 | AR62: Pending | AS62: 45635
B63: {=+_xlfn.IFS(D63="In Touch - Positive",2,D63="Pending",1,D63="No Answer",4,D63="In Touch - Negative",3)} -> 1 | C63: Digital e Idrotech (EIMA) | D63: =+AR63 -> Pending | E63: R.P.E. S.R.L. | G63: CO | H63: 02303440131 | J63: Agricoltura | L63: Fam. Ravazzani | S63: no | T63: 2023 | U63: 30.4 | V63: 5.1 | W63: =+V63/U63 -> 0.16776316 | X63: 2.8 | Y63: -5.9 | AA63: Cold Call | AC63: ASP | AD63: ASP | AE63: ASP | AJ63: =+TODAY()-AM63 -> 29 | AK63: =+TODAY()-AS63 -> 29 | AL63: =+IF(D63="Pending",COUNTA(AM63:AQ63)/5,D63) -> 0.6 | AM63: 45635 | AN63: 45636 | AO63: 45670 | AR63: Pending | AS63: 45635
B64: {=+_xlfn.IFS(D64="In Touch - Positive",2,D64="Pending",1,D64="No Answer",4,D64="In Touch - Negative",3)} -> 1 | C64: Digital e Idrotech (EIMA) | D64: =+AR64 -> Pending | E64: SATI GROUP S.P.A. | G64: BO | H64: 03882680378 | J64: Agricoltura | L64: Riccardo Tonelli | S64: no | T64: 2023 | U64: 39 | V64: 4.9 | W64: =+V64/U64 -> 0.12564103 | X64: 2.8 | Y64: 2.9 | AA64: Cold Call | AC64: ASP | AD64: ASP | AE64: ASP | AJ64: =+TODAY()-AM64 -> 29 | AK64: =+TODAY()-AS64 -> 29 | AL64: =+IF(D64="Pending",COUNTA(AM64:AQ64)/5,D64) -> 0.6 | AM64: 45635 | AN64: 45636 | AO64: 45670 | AR64: Pending | AS64: 45635
... B66: {=+_xlfn.IFS(D66="In Touch - Positive",2,D66="Pending",1,D66="No Answer",4,D66="In Touch - Negative",3)} -> 1 | C66: Digital e Idrotech (EIMA) | D66: =+AR66 -> Pending | E66: DINAMICA GENERALE S.P.A. | G66: MN | H66: 01599500202 | J66: Agricoltura | L66: Andrea Ghirlandi | S66: no | T66: 2023 | U66: 26.5 | V66: 4.5 | W66: =+V66/U66 -> 0.16981132 | X66: 2.4 | Y66: -2.2 | AA66: Cold Call | AC66: ASP | AD66: ASP | AE66: ASP | AJ66: =+TODAY()-AM66 -> 29 | AK66: =+TODAY()-AS66 -> 29 | AL66: =+IF(D66="Pending",COUNTA(AM66:AQ66)/5,D66) -> 0.6 | AM66: 45635 | AN66: 45636 | AO66: 45670 | AR66: Pending | AS66: 45635
B67: {=+_xlfn.IFS(D67="In Touch - Positive",2,D67="Pending",1,D67="No Answer",4,D67="In Touch - Negative",3)} -> 1 | C67: Digital e Idrotech (EIMA) | D67: =+AR67 -> Pending | E67: RM S.P.A. | G67: PR | H67: 00153210349 | J67: Agricoltura | S67: no | T67: 2023 | U67: 26.4 | V67: 3.87 | W67: =+V67/U67 -> 0.14659091 | X67: 2.3 | Y67: 0.7 | AA67: Cold Call | AC67: ASP | AD67: ASP | AE67: ASP | AJ67: =+TODAY()-AM67 -> 29 | AK67: =+TODAY()-AS67 -> 29 | AL67: =+IF(D67="Pending",COUNTA(AM67:AQ67)/5,D67) -> 0.6 | AM67: 45635 | AN67: 45636 | AO67: 45670 | AR67: Pending | AS67: 45635
B68: {=+_xlfn.IFS(D68="In Touch - Positive",2,D68="Pending",1,D68="No Answer",4,D68="In Touch - Negative",3)} -> 1 | C68: Digital e Idrotech (EIMA) | D68: =+AR68 -> Pending | E68: SCARABELLI IRRIGAZIONE S.R.L. | G68: BO | H68: 01128570379 | J68: Agricoltura | L68: Andrea Scarabelli | S68: no | T68: 2023 | U68: 25.7 | V68: 3.7 | W68: =+V68/U68 -> 0.14396887 | X68: -1.3 | Y68: 20.8 | AA68: Cold Call | AC68: ASP | AD68: ASP | AE68: ASP | AJ68: =+TODAY()-AM68 -> 29 | AK68: =+TODAY()-AS68 -> 29 | AL68: =+IF(D68="Pending",COUNTA(AM68:AQ68)/5,D68) -> 0.6 | AM68: 45635 | AN68: 45636 | AO68: 45670 | AR68: Pending | AS68: 45635
B69: {=+_xlfn.IFS(D69="In Touch - Positive",2,D69="Pending",1,D69="No Answer",4,D69="In Touch - Negative",3)} -> 1 | C69: Digital e Idrotech (EIMA) | D69: =+AR69 -> Pending | E69: TECO - S.R.L. | G69: RA | H69: 01075610392 | J69: Agricoltura | L69: Massimo Turci | S69: no | T69: 2023 | U69: 14.5 | V69: 3.1 | W69: =+V69/U69 -> 0.2137931 | X69: 2 | Y69: -2.9 | AA69: Cold Call | AC69: ASP | AD69: ASP | AE69: ASP | AJ69: =+TODAY()-AM69 -> 29 | AK69: =+TODAY()-AS69 -> 29 | AL69: =+IF(D69="Pending",COUNTA(AM69:AQ69)/5,D69) -> 0.6 | AM69: 45635 | AN69: 45636 | AO69: 45670 | AR69: Pending | AS69: 45635
B70: {=+_xlfn.IFS(D70="In Touch - Positive",2,D70="Pending",1,D70="No Answer",4,D70="In Touch - Negative",3)} -> 1 | C70: Digital e Idrotech (EIMA) | D70: =+AR70 -> Pending | E70: VERZELLESI S.R.L. | G70: RE | H70: 00253540355 | J70: Agricoltura | L70: Sauro Verzellesi | S70: no | T70: 2023 | U70: 15.2 | V70: 2.9 | W70: =+V70/U70 -> 0.19078947 | X70: 1.8 | Y70: -0.7 | AA70: Cold Call | AC70: ASP | AD70: ASP | AE70: ASP | AJ70: =+TODAY()-AM70 -> 29 | AK70: =+TODAY()-AS70 -> 29 | AL70: =+IF(D70="Pending",COUNTA(AM70:AQ70)/5,D70) -> 0.6 | AM70: 45635 | AN70: 45636 | AO70: 45670 | AR70: Pending | AS70: 45635
B71: {=+_xlfn.IFS(D71="In Touch - Positive",2,D71="Pending",1,D71="No Answer",4,D71="In Touch - Negative",3)} -> 1 | C71: Omegro | D71: =+AR71 -> Pending | E71: E-TIME | G71: VR | H71: 03256040233 | J71: Technology | K71: System integrators, CRM, ERP | L71: Matteo Gelmetti | S71: no | T71: 2023 | U71: 2.17 | V71: -0.2 | W71: =+V71/U71 -> -0.092165899 | X71: 0.01 | Y71: -0.08 | AA71: Cold Call | AC71: ASP | AD71: ASP | AE71: ASP | AJ71: =+TODAY()-AM71 -> 98 | AK71: =+TODAY()-AS71 -> 34 | AL71: =+IF(D71="Pending",COUNTA(AM71:AQ71)/5,D71) -> 0.4 | AM71: 45566 | AN71: 45630 | AR71: Pending | AS71: 45630
B72: {=+_xlfn.IFS(D72="In Touch - Positive",2,D72="Pending",1,D72="No Answer",4,D72="In Touch - Negative",3)} -> 1 | C72: Omegro | D72: =+AR72 -> Pending | E72: MADE IN BIT | G72: FI | H72: 05358190485 | J72: Technology | K72: System integrators, CRM, ERP | L72: Leonardo Balestri | S72: no | T72: 2023 | U72: 2.35 | V72: 0.07 | W72: =+V72/U72 -> 0.029787234 | X72: 0.02 | Y72: 0.07 | AA72: Cold Call | AC72: ASP | AD72: ASP | AE72: ASP | AJ72: =+TODAY()-AM72 -> 98 | AK72: =+TODAY()-AS72 -> 34 | AL72: =+IF(D72="Pending",COUNTA(AM72:AQ72)/5,D72) -> 0.4 | AM72: 45566 | AN72: 45630 | AR72: Pending | AS72: 45630
B73: {=+_xlfn.IFS(D73="In Touch - Positive",2,D73="Pending",1,D73="No Answer",4,D73="In Touch - Negative",3)} -> 1 | C73: Fitness Retail | D73: =+AR73 -> Pending | E73: EASYFIT SOCIETA' SPORTIVA DILETTANTISTICA A RESPONSABILITA' LIMITATA ABBREVIATO EASYFIT S.S.D. A R.L. | G73: MI | J73: Fitness | K73: Gestione di palestre | L73: Marco Sammartino | S73: no | T73: 2023 | U73: 2.282 | V73: 1.139 | W73: =+V73/U73 -> 0.49912358 | AA73: Cold Call | AC73: LUS | AD73: LUS | AE73: LUS | AJ73: =+TODAY()-AM73 -> 50 | AK73: =+TODAY()-AS73 -> 41 | AL73: =+IF(D73="Pending",COUNTA(AM73:AQ73)/5,D73) -> 0.4 | AM73: 45614 | AN73: 45623 | AR73: Pending | AS73: 45623
B74: {=+_xlfn.IFS(D74="In Touch - Positive",2,D74="Pending",1,D74="No Answer",4,D74="In Touch - Negative",3)} -> 1 | C74: Fitness Retail | D74: =+AR74 -> Pending | E74: EASY FIT PALESTRE S.S.D. | G74: RM | J74: Fitness | K74: Gestione di palestre | L74: Daniele Pavan | S74: no | T74: 2023 | U74: 3.797 | V74: 0.568 | W74: =+V74/U74 -> 0.14959178 | Y74: 4.447 | AA74: Cold Call | AC74: LUS | AD74: LUS | AE74: LUS | AJ74: =+TODAY()-AM74 -> 50 | AK74: =+TODAY()-AS74 -> 46 | AL74: =+IF(D74="Pending",COUNTA(AM74:AQ74)/5,D74) -> 0.4 | AM74: 45614 | AN74: 45618 | AR74: Pending | AS74: 45618
B75: {=+_xlfn.IFS(D75="In Touch - Positive",2,D75="Pending",1,D75="No Answer",4,D75="In Touch - Negative",3)} -> 1 | C75: Pj Despatch | D75: =+AR75 -> Pending | E75: Trans Isole | J75: Logistics | L75: Michele Spighetto | W75: =+V75/U75 -> #DIV/0! | AA75: Cold Call | AC75: LUS | AD75: LUS | AE75: LUS | AJ75: =+TODAY()-AM75 -> 50 | AK75: =+TODAY()-AS75 -> 50 | AL75: =+IF(D75="Pending",COUNTA(AM75:AQ75)/5,D75) -> 0.4 | AM75: 45614 | AN75: 45614 | AR75: Pending | AS75: 45614
B76: {=+_xlfn.IFS(D76="In Touch - Positive",2,D76="Pending",1,D76="No Answer",4,D76="In Touch - Negative",3)} -> 1 | C76: Scouting buy-side | D76: =+AR76 -> Pending | E76: OLEARIA DESANTIS S.P.A. | G76: BA | H76: 03671870727 | J76: Food | K76: Produzione di olio d'oliva | L76: Nicola Desantis Vincenzo Desantis Vito Desantis | M76: Vincenzo Desantis | N76: Vito Desantis | P76: Nicola Desantis Vincenzo Desantis Vito Desantis | S76: no | T76: 2023 | U76: 154.95708 | V76: 17.307323 | W76: =+V76/U76 -> 0.11169107 | X76: 11.940548 | Y76: -1.22644 | AA76: Cold Call | AC76: GIM | AD76: ASC | AE76: GIM | AJ76: =+TODAY()-AM76 -> 29 | AK76: =+TODAY()-AS76 -> 22 | AL76: =+IF(D76="Pending",COUNTA(AM76:AQ76)/5,D76) -> 0.4 | AM76: 45635 | AN76: 45642 | AR76: Pending | AS76: 45642
B77: {=+_xlfn.IFS(D77="In Touch - Positive",2,D77="Pending",1,D77="No Answer",4,D77="In Touch - Negative",3)} -> 1 | C77: Scouting buy-side | D77: =+AR77 -> Pending | E77: RUBINETTERIA PAFFONI S.P.A. | G77: NO | H77: 00250430030 | J77: Arredamento | K77: Produzione di rubinetteria e altri accessori | L77: Francesca Paffoni Daniela Paffoni | M77: Daniela Paffoni (50% tramite Mepa Finanziaria SpA) | N77: Francesca Paffoni (50% tramite Mepa Finanziaria SpA) | P77: Francesca Paffoni Daniela Paffoni | S77: no | T77: 2023 | U77: 78.596618 | V77: 15.347507 | W77: =+V77/U77 -> 0.19526931 | X77: 8.734977 | Y77: -22.406753 | AA77: Cold Call | AC77: GIM | AD77: ASC | AE77: GIM | AJ77: =+TODAY()-AM77 -> 29 | AK77: =+TODAY()-AS77 -> 22 | AL77: =+IF(D77="Pending",COUNTA(AM77:AQ77)/5,D77) -> 0.4 | AM77: 45635 | AN77: 45642 | AR77: Pending | AS77: 45642
B78: {=+_xlfn.IFS(D78="In Touch - Positive",2,D78="Pending",1,D78="No Answer",4,D78="In Touch - Negative",3)} -> 1 | C78: Scouting buy-side | D78: =+AR78 -> Pending | E78: KASK S.P.A. | G78: BG | H78: 03116700166 | J78: Outdoor equipement | K78: Produzione di cashi e occhiali sportivi | L78: Angelo Gotti | M78: Angelo Gotti | N78: - | P78: Angelo Gotti | S78: si | T78: 2023 | U78: 81.44 | V78: 12.27 | W78: =+V78/U78 -> 0.15066306 | X78: 3.589 | Y78: -16.947 | AA78: Cold Call | AC78: GIM | AD78: ASC | AE78: GIM | AJ78: =+TODAY()-AM78 -> 29 | AK78: =+TODAY()-AS78 -> 22 | AL78: =+IF(D78="Pending",COUNTA(AM78:AQ78)/5,D78) -> 0.4 | AM78: 45635 | AN78: 45642 | AR78: Pending | AS78: 45642
B79: {=+_xlfn.IFS(D79="In Touch - Positive",2,D79="Pending",1,D79="No Answer",4,D79="In Touch - Negative",3)} -> 1 | C79: Scouting buy-side | D79: =+AR79 -> Pending | E79: COMACCHIO S.P.A. | G79: TV | H79: 02019450267 | J79: Machinery | K79: Produzioni di macchine industriali per perforazioni ed esplorazioni minerarie | L79: Patrizio Comacchio Renzo Comacchio | M79: Fam Comacchio | P79: Patrizio Comacchio Renzo Comacchio | S79: si | T79: 2023 | U79: 129.244 | V79: 18.485 | W79: =+V79/U79 -> 0.14302405 | X79: 11.714 | Y79: -6.313 | AA79: Cold Call | AC79: GIM | AD79: ASC | AE79: GIM | AJ79: =+TODAY()-AM79 -> 29 | AK79: =+TODAY()-AS79 -> 22 | AL79: =+IF(D79="Pending",COUNTA(AM79:AQ79)/5,D79) -> 0.4 | AM79: 45635 | AN79: 45642 | AR79: Pending | AS79: 45642
B80: {=+_xlfn.IFS(D80="In Touch - Positive",2,D80="Pending",1,D80="No Answer",4,D80="In Touch - Negative",3)} -> 1 | C80: Scouting buy-side | D80: =+AR80 -> Pending | E80: J DENTAL CARE SRL | G80: MO | H80: 03071260362 | J80: Healthcare | K80: Impiantistica dentale | L80: Giacomo Grandi | M80: Giacomo Grandi | N80: Tommaso Grandi | O80: Giacomo Grandi | S80: no | T80: 2023 | U80: 41.458236 | V80: 18.683499 | W80: =+V80/U80 -> 0.45065832 | X80: 14.071492 | Y80: -8.218129 | AA80: Cold Call | AC80: GIM | AD80: ASC | AE80: GIM | AJ80: =+TODAY()-AM80 -> 37 | AK80: =+TODAY()-AS80 -> 22 | AL80: =+IF(D80="Pending",COUNTA(AM80:AQ80)/5,D80) -> 0.6 | AM80: 45627 | AN80: 45635 | AO80: 45642 | AR80: Pending | AS80: 45642
B81: {=+_xlfn.IFS(D81="In Touch - Positive",2,D81="Pending",1,D81="No Answer",4,D81="In Touch - Negative",3)} -> 1 | C81: Scouting buy-side | D81: =+AR81 -> Pending | E81: VEM SISTEMI S.P.A. | G81: FC | H81: 01803850401 | J81: ICT | K81: Software per aziende | L81: Gabriella Attanasio | M81: Gabriella Attanasio | N81: Stefano Bossi | O81: Davide Stefanelli | P81: Gabriella Attanasio | Q81: Aride Missiroli | S81: no | T81: 2023 | U81: 82.871052 | V81: 18.3744 | W81: =+V81/U81 -> 0.22172278 | X81: 12.765036 | Y81: -25.747962 | AA81: Cold Call | AC81: GIM | AD81: ASC | AE81: GIM | AJ81: =+TODAY()-AM81 -> 37 | AK81: =+TODAY()-AS81 -> 22 | AL81: =+IF(D81="Pending",COUNTA(AM81:AQ81)/5,D81) -> 0.6 | AM81: 45627 | AN81: 45635 | AO81: 45642 | AR81: Pending | AS81: 45642
B82: {=+_xlfn.IFS(D82="In Touch - Positive",2,D82="Pending",1,D82="No Answer",4,D82="In Touch - Negative",3)} -> 1 | C82: Omegro | D82: =+AR82 -> Pending | E82: LCS Group | G82: MB | H82: 12327220153 | J82: Technology | K82: Software CRM, ERP | L82: Gianfranco Silpigni | M82: Camilla Silipigni | N82: Danilo Ripamonti | S82: no | T82: 2023 | U82: 13.5 | V82: 1.73 | W82: =+V82/U82 -> 0.12814815 | Y82: -4.24 | AA82: Cold Call | AC82: FCA | AD82: ASP | AE82: ASP | AJ82: =+TODAY()-AM82 -> 62 | AK82: =+TODAY()-AS82 -> 62 | AL82: =+IF(D82="Pending",COUNTA(AM82:AQ82)/5,D82) -> 0.4 | AM82: 45602 | AN82: 45615 | AR82: Pending | AS82: 45602
B83: {=+_xlfn.IFS(D83="In Touch - Positive",2,D83="Pending",1,D83="No Answer",4,D83="In Touch - Negative",3)} -> 1 | C83: Food | D83: =+AR83 -> Pending | E83: Tartuflanghe | G83: CN | H83: 03062420041 | J83: Food | K83: Produzione di prodotti gastronomici a base di tartufo | L83: Paolo Montanaro | M83: Paolo Montanaro | N83: Stefania Montanaro | S83: no | T83: 2023 | U83: 17.6 | V83: 4.2 | W83: =+V83/U83 -> 0.23863636 | X83: 2.786 | Y83: -6.171 | AA83: Cold Call | AC83: ASC | AD83: GID | AE83: GID | AJ83: =+TODAY()-AM83 -> 61 | AK83: =+TODAY()-AS83 -> 32 | AL83: =+IF(D83="Pending",COUNTA(AM83:AQ83)/5,D83) -> 0.6 | AM83: 45603 | AN83: 45632 | AO83: 45664 | AR83: Pending | AS83: 45632
